Workbook
Name ___________________b70000: #REF!
Name ___________________b70000: #REF!
Name ___________________b70000: #REF!
Name ___________________b70000: #REF!
Name ___________________b70000: #REF!
Name ___________________b70000: #REF!
Name ___________________b70000: #REF!
Name ___________________b70000: #REF!
Name ___________________b70000: #REF!
Name ___________________b70000: #REF!
Name ___________________b70000: #REF!
Name ___________________b70005: #REF!
Name ___________________b70005: #REF!
Name ___________________b70005: #REF!
Name ___________________b70005: #REF!
Name ___________________b70005: #REF!
Name ___________________b70005: #REF!
Name ___________________b70005: #REF!
Name ___________________b70005: #REF!
Name ___________________b70005: #REF!
Name ___________________b70005: #REF!
Name ___________________b70005: #REF!
Name __________________b70000: #REF!
Name __________________b70000: #REF!
Name __________________b70000: #REF!
Name __________________b70000: #REF!
Name __________________b70000: #REF!
Name __________________b70000: #REF!
Name __________________b70000: #REF!
Name __________________b70000: #REF!
Name __________________b70000: #REF!
Name __________________b70000: #REF!
Name __________________b70000: #REF!
Name __________________b70005: #REF!
Name __________________b70005: #REF!
Name __________________b70005: #REF!
Name __________________b70005: #REF!
Name __________________b70005: #REF!
Name __________________b70005: #REF!
Name __________________b70005: #REF!
Name __________________b70005: #REF!
Name __________________b70005: #REF!
Name __________________b70005: #REF!
Name __________________b70005: #REF!
Name _________________b70000: #REF!
Name _________________b70000: #REF!
Name _________________b70000: #REF!
Name _________________b70000: #REF!
Name _________________b70000: #REF!
Name _________________b70000: #REF!
Name _________________b70000: #REF!
Name _________________b70000: #REF!
Name _________________b70000: #REF!
Name _________________b70000: #REF!
Name _________________b70000: #REF!
Name _________________b70005: #REF!
Name _________________b70005: #REF!
Name _________________b70005: #REF!
Name _________________b70005: #REF!
Name _________________b70005: #REF!

Sheet CPC prévisionnel
A1: Synthèse Budget par domaine | B1: 104 | C1: 105 | D1: 106 | E1: 107 | F1: 114 | G1: 19/20 | H1: 18/19 | I1: BUD-REEL | J1: %
A2: Sup Tot (ha) | B2: =+'104_Synthèse'!N3 -> 0 | C2: =+'105_Synthèse'!N3 -> 0 | D2: =+'106_Synthèse'!N3 -> 5.575 | G2: =SUM(B2:D2) -> 5.575 | H2: =+Synthèse!O3 -> 17.3 | I2: =+G2-H2 -> -11.725 | J2: =+I2/H2 -> -0.67774566
A3: Vol (kg) | B3: =+'104_Synthèse'!N5 -> 1972475 | C3: =+'105_Synthèse'!N5 -> 728325 | D3: =+'106_Synthèse'!N5 -> 728325000 | G3: =SUM(B3:D3) -> 731025800 | H3: =+Synthèse!O5 -> 1982993.5 | I3: =+G3-H3 -> 7.2904281e+08 | J3: =+I3/H3 -> 367.6476
A4: rendement (t/ha) | B4: =+B3/B2/1000 -> #DIV/0! | C4: =+C3/C2/1000 -> #DIV/0! | D4: =+D3/D2/1000 -> 130641.26 | G4: =+G3/G2/1000 -> 131125.7 | H4: =+H3/H2/1000 -> 114.6239 | I4: =+G4-H4 -> 131011.08 | J4: =+I4/H4 -> 1142.9648
A5: Chiffre d'affaires (MAD) | B5: ='104_Synthèse'!N7 -> 17652500 | C5: ='105_Synthèse'!N7 -> 0 | D5: ='106_Synthèse'!N7 -> 0 | G5: =SUM(B5:D5) -> 17652500 | H5: =Synthèse!O7+Synthèse!O9 -> 12803957 | I5: =+G5-H5 -> 4848543.1 | J5: =+I5/H5 -> 0.37867537
A6: Intrants | B6: =+'104_Synthèse'!N18 -> 3255984 | C6: =+'105_Synthèse'!N18 -> 0 | D6: =+'106_Synthèse'!N18 -> 94.8 | G6: =SUM(B6:D6) -> 3256078.8 | H6: =+Synthèse!O18 -> 5773682.9 | I6: =+G6-H6 -> -2517604.1 | J6: =+I6/H6 -> -0.43604821
A7: à l'hectare | B7: =B6/$B$2 -> #DIV/0! | C7: =C6/$C$2 -> #DIV/0! | D7: =D6/$D$2 -> 17.004484 | G7: =G6/$G$2 -> 584050.01 | H7: =H6/$H$2 -> 333738.9 | I7: =+G7-H7 -> 250311.11 | J7: =+I7/H7 -> 0.75002079
A8: Main d'œuvre directe | B8: ='104_Synthèse'!N25 -> 2548032.9 | C8: ='105_Synthèse'!N25 -> 0 | D8: ='106_Synthèse'!N25 -> 705.88235 | G8: =SUM(B8:D8) -> 2548738.8 | H8: =Synthèse!O25 -> 3967234.3 | I8: =+G8-H8 -> -1418495.5 | J8: =+I8/H8 -> -0.35755275
A9: à l'hectare | B9: =B8/$B$2 -> #DIV/0! | C9: =C8/$C$2 -> #DIV/0! | D9: =D8/$D$2 -> 126.61567 | G9: =G8/$G$2 -> 457172.87 | H9: =H8/$H$2 -> 229319.9 | I9: =+G9-H9 -> 227852.97 | J9: =+I9/H9 -> 0.99360312
A10: Energie | B10: ='104_Synthèse'!N21 -> 0 | C10: ='105_Synthèse'!N21 -> #DIV/0! | D10: ='106_Synthèse'!N21 -> 0 | G10: =SUM(B10:D10) -> #DIV/0! | H10: =Synthèse!O21 -> 298133.26 | I10: =+G10-H10 -> #DIV/0! | J10: =+I10/H10 -> #DIV/0!
A11: à l'hectare | B11: =B10/$B$2 -> #DIV/0! | C11: =C10/$C$2 -> #DIV/0! | D11: =D10/$D$2 -> 0 | G11: =G10/$G$2 -> #DIV/0! | H11: =H10/$H$2 -> 17233.136 | I11: =+G11-H11 -> #DIV/0! | J11: =+I11/H11 -> #DIV/0!
A12: Transport sur ventes | B12: ='104_Synthèse'!N28 -> 1.3239375e+08 | C12: ='105_Synthèse'!N28 -> 0 | D12: ='106_Synthèse'!N28 -> 0 | G12: =SUM(B12:D12) -> 1.3239375e+08 | H12: =Synthèse!O28 -> 142933 | I12: =+G12-H12 -> 1.3225082e+08 | J12: =+I12/H12 -> 925.2644
A13: à l'hectare | B13: =B12/$B$2 -> #DIV/0! | C13: =C12/$C$2 -> #DIV/0! | D13: =D12/$D$2 -> 0 | G13: =G12/$G$2 -> 23747758 | H13: =H12/$H$2 -> 8262.0231 | I13: =+G13-H13 -> 23739496 | J13: =+I13/H13 -> 2873.3272
A14: Charges variables (MAD) | B14: =+B12+B10+B8+B6 -> 1.3819777e+08 | C14: =+C12+C10+C8+C6 -> #DIV/0! | D14: =+D12+D10+D8+D6 -> 800.68235 | G14: =SUM(B14:D14) -> #DIV/0! | H14: =+H12+H10+H8+H6 -> 10181983 | I14: =+G14-H14 -> #DIV/0! | J14: =+I14/H14 -> #DIV/0!
A15: à l'hectare | B15: =B14/$B$2 -> #DIV/0! | C15: =C14/$C$2 -> #DIV/0! | D15: =D14/$D$2 -> 143.62015 | G15: =G14/$G$2 -> #DIV/0! | H15: =H14/$H$2 -> 588553.96 | I15: =+G15-H15 -> #DIV/0! | J15: =+I15/H15 -> #DIV/0!
A16: Main d'œuvre Adm. & Tech | B16: =+'104_Synthèse'!N26+'104_Synthèse'!N27 -> 364794.45 | C16: =+'105_Synthèse'!N26+'105_Synthèse'!N27 -> 423805.32 | D16: =+'106_Synthèse'!N26+'106_Synthèse'!N27 -> 139480.23 | G16: =SUM(B16:D16) -> 928080 | H16: =+Synthèse!O26+Synthèse!O27 -> 1212671.6 | I16: =+G16-H16 -> -284591.61 | J16: =+I16/H16 -> -0.23468152
A17: à l'hectare | B17: =B16/$B$2 -> #DIV/0! | C17: =C16/$C$2 -> #DIV/0! | D17: =D16/$D$2 -> 25018.876 | G17: =G16/$G$2 -> 166471.75 | H17: =H16/$H$2 -> 70096.625 | I17: =+G17-H17 -> 96375.124 | J17: =+I17/H17 -> 1.3748896
A18: Loyers fermes | B18: ='104_Synthèse'!N23 -> 451470.59 | C18: ='105_Synthèse'!N23 -> 0 | D18: ='106_Synthèse'!N23 -> 0 | G18: =SUM(B18:D18) -> 451470.59 | H18: =Synthèse!O23 -> 625000 | I18: =+G18-H18 -> -173529.41 | J18: =+I18/H18 -> -0.27764706
A19: à l'hectare | B19: =B18/$B$2 -> #DIV/0! | C19: =C18/$C$2 -> #DIV/0! | D19: =D18/$D$2 -> 0 | G19: =G18/$G$2 -> 80981.271 | H19: =H18/$H$2 -> 36127.168 | I19: =+G19-H19 -> 44854.104 | J19: =+I19/H19 -> 1.2415616
A20: Entretien & maintenance | B20: =+'104_Synthèse'!N24 -> 125618.64 | C20: =+'105_Synthèse'!N24 -> 17535.26 | D20: =+'106_Synthèse'!N24 -> 5771.0983 | G20: =SUM(B20:D20) -> 148925 | H20: =+Synthèse!O24 -> 308852.95 | I20: =+G20-H20 -> -159927.95 | J20: =+I20/H20 -> -0.5178126
A21: à l'hectare | B21: =B20/$B$2 -> #DIV/0! | C21: =C20/$C$2 -> #DIV/0! | D21: =D20/$D$2 -> 1035.1746 | G21: =G20/$G$2 -> 26713.004 | H21: =H20/$H$2 -> 17852.771 | I21: =+G21-H21 -> 8860.233 | J21: =+I21/H21 -> 0.49629454
A22: Autres Frais Généraux | B22: ='104_Synthèse'!N29+'104_Synthèse'!N22 -> 184979.19 | C22: =+'105_Synthèse'!N29+'105_Synthèse'!N22 -> 143569.94 | D22: =+'106_Synthèse'!N22+'106_Synthèse'!N29 -> 47250.867 | G22: =SUM(B22:D22) -> 375800 | H22: =+Synthèse!O29+Synthèse!O22 -> 253848.78 | I22: =+G22-H22 -> 121951.22 | J22: =+I22/H22 -> 0.48040891
A23: à l'hectare | B23: =B22/$B$2 -> #DIV/0! | C23: =C22/$C$2 -> #DIV/0! | D23: =D22/$D$2 -> 8475.4918 | G23: =G22/$G$2 -> 67408.072 | H23: =H22/$H$2 -> 14673.34 | I23: =+G23-H23 -> 52734.732 | J23: =+I23/H23 -> 3.5939146
A24: Charges fixes (MAD) | B24: =+B22+B20+B18+B16 -> 1126862.9 | C24: =+C22+C20+C18+C16 -> 584910.52 | D24: =+D22+D20+D18+D16 -> 192502.2 | G24: =SUM(B24:D24) -> 1904275.6 | H24: =+H22+H20+H18+H16 -> 2400373.3 | I24: =+G24-H24 -> -496097.76 | J24: =+I24/H24 -> -0.20667525
A25: à l'hectare | B25: =B24/$B$2 -> #DIV/0! | C25: =C24/$C$2 -> #DIV/0! | D25: =D24/$D$2 -> 34529.542 | G25: =G24/$G$2 -> 341574.1 | H25: =H24/$H$2 -> 138749.9 | I25: =+G25-H25 -> 202824.19 | J25: =+I25/H25 -> 1.461797
A26: EBITDA (MAD) | B26: =+B5-B14-B24 -> -1.2167213e+08 | C26: =+C5-C14-C24 -> #DIV/0! | D26: =+D5-D14-D24 -> -193302.88 | G26: =SUM(B26:D26) -> #DIV/0! | H26: =+H5-H14-H24 -> 221600.11 | I26: =+G26-H26 -> #DIV/0! | J26: =+I26/H26 -> #DIV/0!
A27: à l'hectare | B27: =B26/$B$2 -> #DIV/0! | C27: =C26/$C$2 -> #DIV/0! | D27: =D26/$D$2 -> -34673.162 | G27: =G26/$G$2 -> #DIV/0! | H27: =H26/$H$2 -> 12809.255 | I27: =+G27-H27 -> #DIV/0! | J27: =+I27/H27 -> #DIV/0!
A28: En % du chiffre d'affaires | B28: =B26/$B$5 -> -6.8926288 | C28: =C26/$C$5 -> #DIV/0! | D28: =D26/$D$5 -> #DIV/0! | G28: =G26/$G$5 -> #DIV/0! | H28: =H26/$H$5 -> 0.017307158 | I28: =+G28-H28 -> #DIV/0!
A29: Amortissements | B29: ='104_Synthèse'!N32 -> 1019827.7 | C29: ='105_Synthèse'!N32 -> 1580439.4 | D29: ='106_Synthèse'!N32 -> 292852.23 | G29: =SUM(B29:D29) -> 2893119.4 | H29: =Synthèse!O32 -> 2724261.2 | I29: =+G29-H29 -> 168858.2 | J29: =+I29/H29 -> 0.061983115
A30: à l'hectare | B30: =B29/$B$2 -> #DIV/0! | C30: =C29/$C$2 -> #DIV/0! | D30: =D29/$D$2 -> 52529.549 | G30: =G29/$G$2 -> 518945.18 | H30: =H29/$H$2 -> 157471.75 | I30: =+G30-H30 -> 361473.44 | J30: =+I30/H30 -> 2.2954812
A31: Résultat d'exploitation | B31: =+B26-B29 -> -1.2269196e+08 | C31: =+C26-C29 -> #DIV/0! | D31: =+D26-D29 -> -486155.11 | G31: =SUM(B31:D31) -> #DIV/0! | H31: =+H26-H29 -> -2502661.1 | I31: =+G31-H31 -> #DIV/0! | J31: =+I31/H31 -> #DIV/0!
A32: En % du chiffre d'affaires | B32: =B31/$B$5 -> -6.9504012 | C32: =C31/$B$5 -> #DIV/0! | D32: =D31/$B$5 -> -0.027540298 | G32: =G31/$B$5 -> #DIV/0! | H32: =H31/$B$5 -> -0.14177375 | I32: =+G32-H32 -> #DIV/0!
A35: Ceck centralisation | G35: =G31-Synthèse!N33 -> #DIV/0! | H35: =H31-Synthèse!O33 -> 0

Sheet Synthèse
B1: BUD | C1: BUD | D1: BUD | E1: BUD | F1: BUD | G1: BUD | H1: BUD | I1: BUD | J1: BUD | K1: BUD | L1: BUD | M1: BUD | N1: BUD | O1: REEL | P1: VARIATION | Q1: VARIATION
A2: Analyse totale (MAD) | B2: 45839 | C2: =+B2+31 -> 45870 | D2: =+C2+31 -> 45901 | E2: =+D2+31 -> 45932 | F2: =+E2+31 -> 45963 | G2: =+F2+31 -> 45994 | H2: =+G2+31 -> 46025 | I2: =+H2+31 -> 46056 | J2: =+I2+31 -> 46087 | ... M2: =+L2+31 -> 46180 | N2: 25/26 | O2: 18/19 | P2: BUD-REEL | Q2: % | R2: source | S2: check
A3: Sup Tot (ha) | B3: =+'104_Synthèse'!B3+'105_Synthèse'!B3+'106_Synthèse'!B3 -> 5.575 | C3: =+'104_Synthèse'!C3+'105_Synthèse'!C3+'106_Synthèse'!C3 -> 5.575 | D3: =+'104_Synthèse'!D3+'105_Synthèse'!D3+'106_Synthèse'!D3 -> 5.575 | E3: =+'104_Synthèse'!E3+'105_Synthèse'!E3+'106_Synthèse'!E3 -> 5.575 | F3: =+'104_Synthèse'!F3+'105_Synthèse'!F3+'106_Synthèse'!F3 -> 5.575 | G3: =+'104_Synthèse'!G3+'105_Synthèse'!G3+'106_Synthèse'!G3 -> 5.575 | H3: =+'104_Synthèse'!H3+'105_Synthèse'!H3+'106_Synthèse'!H3 -> 5.575 | I3: =+'104_Synthèse'!I3+'105_Synthèse'!I3+'106_Synthèse'!I3 -> 5.575 | ... M3: =+'104_Synthèse'!M3+'105_Synthèse'!M3+'106_Synthèse'!M3 -> 5.575 | N3: =+'106_Synthèse'!N3+'104_Synthèse'!N3+'105_Synthèse'!N3 -> 5.575 | O3: =+'104_Synthèse'!O3+'105_Synthèse'!O3++'106_Synthèse'!O3 -> 17.3 | P3: =+N3-O3 -> -11.725 | Q3: =+P3/O3 -> -0.67774566 | R3: =+'Plan de culture 104 '!B3+'Plan de culture 105'!B3+'Plan de culture 106'!C3 -> 5.575 | S3: =+N3-R3 -> 0
A4: Sup productive | B4: =+'104_Synthèse'!B4+'105_Synthèse'!B4+'106_Synthèse'!B4 -> 26.14 | C4: =+'104_Synthèse'!C4+'105_Synthèse'!C4+'106_Synthèse'!C4 -> 26.14 | D4: =+'104_Synthèse'!D4+'105_Synthèse'!D4+'106_Synthèse'!D4 -> 26.14 | E4: =+'104_Synthèse'!E4+'105_Synthèse'!E4+'106_Synthèse'!E4 -> 26.14 | F4: =+'104_Synthèse'!F4+'105_Synthèse'!F4+'106_Synthèse'!F4 -> 26.14 | G4: =+'104_Synthèse'!G4+'105_Synthèse'!G4+'106_Synthèse'!G4 -> 26.14 | H4: =+'104_Synthèse'!H4+'105_Synthèse'!H4+'106_Synthèse'!H4 -> 26.14 | I4: =+'104_Synthèse'!I4+'105_Synthèse'!I4+'106_Synthèse'!I4 -> 26.14 | ... M4: =+'104_Synthèse'!M4+'105_Synthèse'!M4+'106_Synthèse'!M4 -> 26.14 | N4: =+'106_Synthèse'!N4+'104_Synthèse'!N4+'105_Synthèse'!N4 -> 26.14 | O4: =+'104_Synthèse'!O4+'105_Synthèse'!O4++'106_Synthèse'!O4 -> 17.3 | P4: =+N4-O4 -> 8.84 | Q4: =+P4/O4 -> 0.51098266 | R4: ='106_Synthèse'!N4+'104_Synthèse'!N4+'105_Synthèse'!N4 -> 26.14 | S4: =+N4-R4 -> 0
A5: Vol (kg) | B5: =+'104_Synthèse'!B5+'105_Synthèse'!B5+'106_Synthèse'!B5 -> 0 | C5: =+'104_Synthèse'!C5+'105_Synthèse'!C5+'106_Synthèse'!C5 -> 0 | D5: =+'104_Synthèse'!D5+'105_Synthèse'!D5+'106_Synthèse'!D5 -> 0 | E5: =+'104_Synthèse'!E5+'105_Synthèse'!E5+'106_Synthèse'!E5 -> 1.080386e+08 | F5: =+'104_Synthèse'!F5+'105_Synthèse'!F5+'106_Synthèse'!F5 -> 1.083456e+08 | G5: =+'104_Synthèse'!G5+'105_Synthèse'!G5+'106_Synthèse'!G5 -> 81259200 | H5: =+'104_Synthèse'!H5+'105_Synthèse'!H5+'106_Synthèse'!H5 -> 81259200 | I5: =+'104_Synthèse'!I5+'105_Synthèse'!I5+'106_Synthèse'!I5 -> 1.083456e+08 | ... M5: =+'104_Synthèse'!M5+'105_Synthèse'!M5+'106_Synthèse'!M5 -> 27086400 | N5: =SUM(B5:M5) -> 731025800 | O5: =+'104_Synthèse'!O5+'105_Synthèse'!O5++'106_Synthèse'!O5 -> 1982993.5 | P5: =+N5-O5 -> 7.2904281e+08 | Q5: =+P5/O5 -> 367.6476 | R5: ='106_Synthèse'!N5+'104_Synthèse'!N5+'105_Synthèse'!N5 -> 731025800 | S5: =+N5-R5 -> 0
A6: rendement (t/ha) | B6: =+B5/B4/1000 -> 0 | C6: =+C5/C4/1000 -> 0 | D6: =+D5/D4/1000 -> 0 | E6: =+E5/E4/1000 -> 4133.0757 | F6: =+F5/F4/1000 -> 4144.8202 | G6: =+G5/G4/1000 -> 3108.6151 | H6: =+H5/H4/1000 -> 3108.6151 | I6: =+I5/I4/1000 -> 4144.8202 | ... O6: =+O5/O4/1000 -> 114.6239 | P6: =+N6-O6 -> 27851.168 | Q6: =+P6/O6 -> 242.97871 | R6: =+R5/R4/1000 -> 27965.792 | S6: =+N6-R6 -> 0
A7: CA EXPORT(MAD) | B7: =+'104_Synthèse'!B7+'105_Synthèse'!B7+'106_Synthèse'!B7 -> 0 | C7: =+'104_Synthèse'!C7+'105_Synthèse'!C7+'106_Synthèse'!C7 -> 0 | D7: =+'104_Synthèse'!D7+'105_Synthèse'!D7+'106_Synthèse'!D7 -> 0 | E7: =+'104_Synthèse'!E7+'105_Synthèse'!E7+'106_Synthèse'!E7 -> 0 | F7: =+'104_Synthèse'!F7+'105_Synthèse'!F7+'106_Synthèse'!F7 -> 3070000 | G7: =+'104_Synthèse'!G7+'105_Synthèse'!G7+'106_Synthèse'!G7 -> 2302500 | H7: =+'104_Synthèse'!H7+'105_Synthèse'!H7+'106_Synthèse'!H7 -> 2302500 | I7: =+'104_Synthèse'!I7+'105_Synthèse'!I7+'106_Synthèse'!I7 -> 3070000 | ... M7: =+'104_Synthèse'!M7+'105_Synthèse'!M7+'106_Synthèse'!M7 -> 767500 | N7: =SUM(B7:M7) -> 17652500 | O7: =+'104_Synthèse'!O7+'105_Synthèse'!O7++'106_Synthèse'!O7 -> 11264311 | P7: =+N7-O7 -> 6388189.1 | Q7: =+P7/O7 -> 0.56711761 | R7: ='106_Synthèse'!N7+'104_Synthèse'!N7+'105_Synthèse'!N7 -> 17652500 | S7: =+N7-R7 -> 0
A8: CA MARCHE LOCAL(MAD)
A9: Autres revenus (MAD) | B9: =+'104_Synthèse'!B9+'105_Synthèse'!B9+'106_Synthèse'!B9 -> 0 | C9: =+'104_Synthèse'!C9+'105_Synthèse'!C9+'106_Synthèse'!C9 -> 0 | D9: =+'104_Synthèse'!D9+'105_Synthèse'!D9+'106_Synthèse'!D9 -> 0 | E9: =+'104_Synthèse'!E9+'105_Synthèse'!E9+'106_Synthèse'!E9 -> 0 | F9: =+'104_Synthèse'!F9+'105_Synthèse'!F9+'106_Synthèse'!F9 -> 0 | G9: =+'104_Synthèse'!G9+'105_Synthèse'!G9+'106_Synthèse'!G9 -> 0 | H9: =+'104_Synthèse'!H9+'105_Synthèse'!H9+'106_Synthèse'!H9 -> 0 | I9: =+'104_Synthèse'!I9+'105_Synthèse'!I9+'106_Synthèse'!I9 -> 0 | ... M9: =+'104_Synthèse'!M9+'105_Synthèse'!M9+'106_Synthèse'!M9 -> 0 | N9: =SUM(B9:M9) -> 0 | O9: =+'104_Synthèse'!O9+'105_Synthèse'!O9++'106_Synthèse'!O9 -> 1539646 | P9: =+N9-O9 -> -1539646 | Q9: =+P9/O9 -> -1 | R9: ='106_Synthèse'!N9+'104_Synthèse'!N9+'105_Synthèse'!N9 -> 0 | S9: =+N9-R9 -> 0
A10: Production encours (MAD) | B10: =+'104_Synthèse'!B10+'105_Synthèse'!B10+'106_Synthèse'!B10 -> #DIV/0! | C10: =+'104_Synthèse'!C10+'105_Synthèse'!C10+'106_Synthèse'!C10 -> #DIV/0! | D10: =+'104_Synthèse'!D10+'105_Synthèse'!D10+'106_Synthèse'!D10 -> #DIV/0! | E10: =+'104_Synthèse'!E10+'105_Synthèse'!E10+'106_Synthèse'!E10 -> #DIV/0! | F10: =+'104_Synthèse'!F10+'105_Synthèse'!F10+'106_Synthèse'!F10 -> #DIV/0! | G10: =+'104_Synthèse'!G10+'105_Synthèse'!G10+'106_Synthèse'!G10 -> #DIV/0! | H10: =+'104_Synthèse'!H10+'105_Synthèse'!H10+'106_Synthèse'!H10 -> #DIV/0! | I10: =+'104_Synthèse'!I10+'105_Synthèse'!I10+'106_Synthèse'!I10 -> #DIV/0! | ... M10: =+'104_Synthèse'!M10+'105_Synthèse'!M10+'106_Synthèse'!M10 -> #DIV/0! | N10: =SUM(B10:M10) -> #DIV/0! | O10: =+'104_Synthèse'!O10+'105_Synthèse'!O10++'106_Synthèse'!O10 -> 0 | P10: =+N10-O10 -> #DIV/0! | Q10: =+P10/O10 -> #DIV/0! | R10: ='106_Synthèse'!N10+'104_Synthèse'!N10+'105_Synthèse'!N10 -> #DIV/0! | S10: =+N10-R10 -> #DIV/0!
A11: Production totale (MAD) | B11: =+B10+B7+B9 -> #DIV/0! | C11: =+C10+C7+C9 -> #DIV/0! | D11: =+D10+D7+D9 -> #DIV/0! | E11: =+E10+E7+E9 -> #DIV/0! | F11: =+F10+F7+F9 -> #DIV/0! | G11: =+G10+G7+G9 -> #DIV/0! | H11: =+H10+H7+H9 -> #DIV/0! | I11: =+I10+I7+I9 -> #DIV/0! | ... M11: =+M10+M7+M9 -> #DIV/0! | N11: =SUM(B11:M11) -> #DIV/0! | O11: =+O10+O7+O9 -> 12803957 | P11: =+N11-O11 -> #DIV/0! | Q11: =+P11/O11 -> #DIV/0! | R11: ='106_Synthèse'!N11+'104_Synthèse'!N11+'105_Synthèse'!N11 -> #DIV/0! | S11: =+N11-R11 -> #DIV/0!
A12: Consommation Semences | B12: =+'104_Synthèse'!B12+'105_Synthèse'!B12+'106_Synthèse'!B12 -> 3.2 | C12: =+'104_Synthèse'!C12+'105_Synthèse'!C12+'106_Synthèse'!C12 -> 1494603.2 | D12: =+'104_Synthèse'!D12+'105_Synthèse'!D12+'106_Synthèse'!D12 -> 3.2 | E12: =+'104_Synthèse'!E12+'105_Synthèse'!E12+'106_Synthèse'!E12 -> 3.2 | F12: =+'104_Synthèse'!F12+'105_Synthèse'!F12+'106_Synthèse'!F12 -> 3.2 | G12: =+'104_Synthèse'!G12+'105_Synthèse'!G12+'106_Synthèse'!G12 -> 3.2 | H12: =+'104_Synthèse'!H12+'105_Synthèse'!H12+'106_Synthèse'!H12 -> 3.2 | I12: =+'104_Synthèse'!I12+'105_Synthèse'!I12+'106_Synthèse'!I12 -> 3.2 | ... M12: =+'104_Synthèse'!M12+'105_Synthèse'!M12+'106_Synthèse'!M12 -> 3.2 | N12: =SUM(B12:M12) -> 1494638.4 | O12: =+'104_Synthèse'!O12+'105_Synthèse'!O12++'106_Synthèse'!O12 -> 1487208.2 | P12: =+N12-O12 -> 7430.15 | Q12: =+P12/O12 -> 0.0049960387 | R12: ='106_Synthèse'!N12+'104_Synthèse'!N12+'105_Synthèse'!N12 -> 1494638.4 | S12: =+N12-R12 -> 0
A13: Consommation Engrais | B13: =+'104_Synthèse'!B13+'105_Synthèse'!B13+'106_Synthèse'!B13 -> 0 | C13: =+'104_Synthèse'!C13+'105_Synthèse'!C13+'106_Synthèse'!C13 -> 0 | D13: =+'104_Synthèse'!D13+'105_Synthèse'!D13+'106_Synthèse'!D13 -> 0 | E13: =+'104_Synthèse'!E13+'105_Synthèse'!E13+'106_Synthèse'!E13 -> 0 | F13: =+'104_Synthèse'!F13+'105_Synthèse'!F13+'106_Synthèse'!F13 -> 0 | G13: =+'104_Synthèse'!G13+'105_Synthèse'!G13+'106_Synthèse'!G13 -> 0 | H13: =+'104_Synthèse'!H13+'105_Synthèse'!H13+'106_Synthèse'!H13 -> 0 | I13: =+'104_Synthèse'!I13+'105_Synthèse'!I13+'106_Synthèse'!I13 -> 0 | ... M13: =+'104_Synthèse'!M13+'105_Synthèse'!M13+'106_Synthèse'!M13 -> 0 | N13: =SUM(B13:M13) -> 0 | O13: =+'104_Synthèse'!O13+'105_Synthèse'!O13++'106_Synthèse'!O13 -> 1893892.2 | P13: =+N13-O13 -> -1893892.2 | Q13: =+P13/O13 -> -1 | R13: ='106_Synthèse'!N13+'104_Synthèse'!N13+'105_Synthèse'!N13 -> 0 | S13: =+N13-R13 -> 0
A14: Consommation Plants | B14: =+'104_Synthèse'!B14+'105_Synthèse'!B14+'106_Synthèse'!B14 -> 0 | C14: =+'104_Synthèse'!C14+'105_Synthèse'!C14+'106_Synthèse'!C14 -> 1113000 | D14: =+'104_Synthèse'!D14+'105_Synthèse'!D14+'106_Synthèse'!D14 -> 0 | E14: =+'104_Synthèse'!E14+'105_Synthèse'!E14+'106_Synthèse'!E14 -> 0 | F14: =+'104_Synthèse'!F14+'105_Synthèse'!F14+'106_Synthèse'!F14 -> 0 | G14: =+'104_Synthèse'!G14+'105_Synthèse'!G14+'106_Synthèse'!G14 -> 0 | H14: =+'104_Synthèse'!H14+'105_Synthèse'!H14+'106_Synthèse'!H14 -> 0 | I14: =+'104_Synthèse'!I14+'105_Synthèse'!I14+'106_Synthèse'!I14 -> 0 | ... M14: =+'104_Synthèse'!M14+'105_Synthèse'!M14+'106_Synthèse'!M14 -> 0 | N14: =SUM(B14:M14) -> 1113000 | O14: =+'104_Synthèse'!O14+'105_Synthèse'!O14++'106_Synthèse'!O14 -> 670159.2 | P14: =+N14-O14 -> 442840.8 | Q14: =+P14/O14 -> 0.6607994 | R14: ='106_Synthèse'!N14+'104_Synthèse'!N14+'105_Synthèse'!N14 -> 1113000 | S14: =+N14-R14 -> 0
A15: Consommation Phytos | B15: =+'104_Synthèse'!B15+'105_Synthèse'!B15+'106_Synthèse'!B15 -> 0 | C15: =+'104_Synthèse'!C15+'105_Synthèse'!C15+'106_Synthèse'!C15 -> 0 | D15: =+'104_Synthèse'!D15+'105_Synthèse'!D15+'106_Synthèse'!D15 -> 0 | E15: =+'104_Synthèse'!E15+'105_Synthèse'!E15+'106_Synthèse'!E15 -> 0 | F15: =+'104_Synthèse'!F15+'105_Synthèse'!F15+'106_Synthèse'!F15 -> 0 | G15: =+'104_Synthèse'!G15+'105_Synthèse'!G15+'106_Synthèse'!G15 -> 0 | H15: =+'104_Synthèse'!H15+'105_Synthèse'!H15+'106_Synthèse'!H15 -> 0 | I15: =+'104_Synthèse'!I15+'105_Synthèse'!I15+'106_Synthèse'!I15 -> 0 | ... M15: =+'104_Synthèse'!M15+'105_Synthèse'!M15+'106_Synthèse'!M15 -> 0 | N15: =SUM(B15:M15) -> 0 | O15: =+'104_Synthèse'!O15+'105_Synthèse'!O15++'106_Synthèse'!O15 -> 1272725.3 | P15: =+N15-O15 -> -1272725.3 | Q15: =+P15/O15 -> -1 | R15: ='106_Synthèse'!N15+'104_Synthèse'!N15+'105_Synthèse'!N15 -> 0 | S15: =+N15-R15 -> 0
A16: Consommation Insectes | B16: =+'104_Synthèse'!B16+'105_Synthèse'!B16+'106_Synthèse'!B16 -> 4.7 | C16: =+'104_Synthèse'!C16+'105_Synthèse'!C16+'106_Synthèse'!C16 -> 4.7 | D16: =+'104_Synthèse'!D16+'105_Synthèse'!D16+'106_Synthèse'!D16 -> 4.7 | E16: =+'104_Synthèse'!E16+'105_Synthèse'!E16+'106_Synthèse'!E16 -> 4.7 | F16: =+'104_Synthèse'!F16+'105_Synthèse'!F16+'106_Synthèse'!F16 -> 4.7 | G16: =+'104_Synthèse'!G16+'105_Synthèse'!G16+'106_Synthèse'!G16 -> 4.7 | H16: =+'104_Synthèse'!H16+'105_Synthèse'!H16+'106_Synthèse'!H16 -> 4.7 | I16: =+'104_Synthèse'!I16+'105_Synthèse'!I16+'106_Synthèse'!I16 -> 4.7 | ... M16: =+'104_Synthèse'!M16+'105_Synthèse'!M16+'106_Synthèse'!M16 -> 4.7 | N16: =SUM(B16:M16) -> 56.4 | O16: =+'104_Synthèse'!O16+'105_Synthèse'!O16++'106_Synthèse'!O16 -> 307765.01 | P16: =+N16-O16 -> -307708.61 | Q16: =+P16/O16 -> -0.99981674 | R16: ='106_Synthèse'!N16+'104_Synthèse'!N16+'105_Synthèse'!N16 -> 56.4 | S16: =+N16-R16 -> 0
A17: Autres fournitures agricoles | B17: =+'104_Synthèse'!B17+'105_Synthèse'!B17+'106_Synthèse'!B17 -> 479534 | C17: =+'104_Synthèse'!C17+'105_Synthèse'!C17+'106_Synthèse'!C17 -> 15350 | D17: =+'104_Synthèse'!D17+'105_Synthèse'!D17+'106_Synthèse'!D17 -> 15350 | E17: =+'104_Synthèse'!E17+'105_Synthèse'!E17+'106_Synthèse'!E17 -> 15350 | F17: =+'104_Synthèse'!F17+'105_Synthèse'!F17+'106_Synthèse'!F17 -> 15350 | G17: =+'104_Synthèse'!G17+'105_Synthèse'!G17+'106_Synthèse'!G17 -> 15350 | H17: =+'104_Synthèse'!H17+'105_Synthèse'!H17+'106_Synthèse'!H17 -> 15350 | I17: =+'104_Synthèse'!I17+'105_Synthèse'!I17+'106_Synthèse'!I17 -> 15350 | ... M17: =+'104_Synthèse'!M17+'105_Synthèse'!M17+'106_Synthèse'!M17 -> 15350 | N17: =SUM(B17:M17) -> 648384 | O17: =+'104_Synthèse'!O17+'105_Synthèse'!O17++'106_Synthèse'!O17 -> 141932.94 | P17: =+N17-O17 -> 506451.06 | Q17: =+P17/O17 -> 3.5682418 | R17: ='106_Synthèse'!N17+'104_Synthèse'!N17+'105_Synthèse'!N17 -> 648384 | S17: =+N17-R17 -> 0
A18: Total consommation Intrants | B18: =SUM(B12:B17) -> 479541.9 | C18: =SUM(C12:C17) -> 2622957.9 | D18: =SUM(D12:D17) -> 15357.9 | E18: =SUM(E12:E17) -> 15357.9 | F18: =SUM(F12:F17) -> 15357.9 | G18: =SUM(G12:G17) -> 15357.9 | H18: =SUM(H12:H17) -> 15357.9 | I18: =SUM(I12:I17) -> 15357.9 | ... M18: =SUM(M12:M17) -> 15357.9 | N18: =SUM(B18:M18) -> 3256078.8 | O18: =SUM(O12:O17) -> 5773682.9 | P18: =+N18-O18 -> -2517604.1 | Q18: =+P18/O18 -> -0.43604821 | R18: ='106_Synthèse'!N18+'104_Synthèse'!N18+'105_Synthèse'!N18 -> 3256078.8 | S18: =+N18-R18 -> 0
A19: Electricité | B19: =+'104_Synthèse'!B19+'105_Synthèse'!B19+'106_Synthèse'!B19 -> 0 | C19: =+'104_Synthèse'!C19+'105_Synthèse'!C19+'106_Synthèse'!C19 -> 0 | D19: =+'104_Synthèse'!D19+'105_Synthèse'!D19+'106_Synthèse'!D19 -> 0 | E19: =+'104_Synthèse'!E19+'105_Synthèse'!E19+'106_Synthèse'!E19 -> 0 | F19: =+'104_Synthèse'!F19+'105_Synthèse'!F19+'106_Synthèse'!F19 -> 0 | G19: =+'104_Synthèse'!G19+'105_Synthèse'!G19+'106_Synthèse'!G19 -> 0 | H19: =+'104_Synthèse'!H19+'105_Synthèse'!H19+'106_Synthèse'!H19 -> 0 | I19: =+'104_Synthèse'!I19+'105_Synthèse'!I19+'106_Synthèse'!I19 -> 0 | ... M19: =+'104_Synthèse'!M19+'105_Synthèse'!M19+'106_Synthèse'!M19 -> 0 | N19: =SUM(B19:M19) -> 0 | O19: =+'104_Synthèse'!O19+'105_Synthèse'!O19++'106_Synthèse'!O19 -> 250614.88 | P19: =+N19-O19 -> -250614.88 | Q19: =+P19/O19 -> -1 | R19: ='106_Synthèse'!N19+'104_Synthèse'!N19+'105_Synthèse'!N19 -> 0 | S19: =+N19-R19 -> 0
A20: Eau | B20: =+'104_Synthèse'!B20+'105_Synthèse'!B20+'106_Synthèse'!B20 -> #DIV/0! | C20: =+'104_Synthèse'!C20+'105_Synthèse'!C20+'106_Synthèse'!C20 -> #DIV/0! | D20: =+'104_Synthèse'!D20+'105_Synthèse'!D20+'106_Synthèse'!D20 -> #DIV/0! | E20: =+'104_Synthèse'!E20+'105_Synthèse'!E20+'106_Synthèse'!E20 -> #DIV/0! | F20: =+'104_Synthèse'!F20+'105_Synthèse'!F20+'106_Synthèse'!F20 -> #DIV/0! | G20: =+'104_Synthèse'!G20+'105_Synthèse'!G20+'106_Synthèse'!G20 -> #DIV/0! | H20: =+'104_Synthèse'!H20+'105_Synthèse'!H20+'106_Synthèse'!H20 -> #DIV/0! | I20: =+'104_Synthèse'!I20+'105_Synthèse'!I20+'106_Synthèse'!I20 -> #DIV/0! | ... M20: =+'104_Synthèse'!M20+'105_Synthèse'!M20+'106_Synthèse'!M20 -> #DIV/0! | N20: =SUM(B20:M20) -> #DIV/0! | O20: =+'104_Synthèse'!O20+'105_Synthèse'!O20++'106_Synthèse'!O20 -> 47518.377 | P20: =+N20-O20 -> #DIV/0! | Q20: =+P20/O20 -> #DIV/0! | R20: ='106_Synthèse'!N20+'104_Synthèse'!N20+'105_Synthèse'!N20 -> #DIV/0! | S20: =+N20-R20 -> #DIV/0!
A21: Total consommation Energie | B21: =SUM(B19:B20) -> #DIV/0! | C21: =SUM(C19:C20) -> #DIV/0! | D21: =SUM(D19:D20) -> #DIV/0! | E21: =SUM(E19:E20) -> #DIV/0! | F21: =SUM(F19:F20) -> #DIV/0! | G21: =SUM(G19:G20) -> #DIV/0! | H21: =SUM(H19:H20) -> #DIV/0! | I21: =SUM(I19:I20) -> #DIV/0! | ... M21: =SUM(M19:M20) -> #DIV/0! | N21: =SUM(B21:M21) -> #DIV/0! | O21: =+O20+O19 -> 298133.26 | P21: =+N21-O21 -> #DIV/0! | Q21: =+P21/O21 -> #DIV/0! | R21: ='106_Synthèse'!N21+'104_Synthèse'!N21+'105_Synthèse'!N21 -> #DIV/0! | S21: =+N21-R21 -> #DIV/0!
A22: Prestations & analyses | B22: =+'104_Synthèse'!B22+'105_Synthèse'!B22+'106_Synthèse'!B22 -> 0 | C22: =+'104_Synthèse'!C22+'105_Synthèse'!C22+'106_Synthèse'!C22 -> 61400 | D22: =+'104_Synthèse'!D22+'105_Synthèse'!D22+'106_Synthèse'!D22 -> 0 | E22: =+'104_Synthèse'!E22+'105_Synthèse'!E22+'106_Synthèse'!E22 -> 0 | F22: =+'104_Synthèse'!F22+'105_Synthèse'!F22+'106_Synthèse'!F22 -> 0 | G22: =+'104_Synthèse'!G22+'105_Synthèse'!G22+'106_Synthèse'!G22 -> 0 | H22: =+'104_Synthèse'!H22+'105_Synthèse'!H22+'106_Synthèse'!H22 -> 0 | I22: =+'104_Synthèse'!I22+'105_Synthèse'!I22+'106_Synthèse'!I22 -> 0 | ... M22: =+'104_Synthèse'!M22+'105_Synthèse'!M22+'106_Synthèse'!M22 -> 0 | N22: =SUM(B22:M22) -> 61400 | O22: =+'104_Synthèse'!O22+'105_Synthèse'!O22++'106_Synthèse'!O22 -> 58498.533 | P22: =+N22-O22 -> 2901.4674 | Q22: =-+P22/O22 -> -0.049598978 | R22: ='106_Synthèse'!N22+'104_Synthèse'!N22+'105_Synthèse'!N22 -> 61400 | S22: =+N22-R22 -> 0
A23: Loyers fermes | B23: =+'104_Synthèse'!B23+'105_Synthèse'!B23+'106_Synthèse'!B23 -> 37622.549 | C23: =+'104_Synthèse'!C23+'105_Synthèse'!C23+'106_Synthèse'!C23 -> 37622.549 | D23: =+'104_Synthèse'!D23+'105_Synthèse'!D23+'106_Synthèse'!D23 -> 37622.549 | E23: =+'104_Synthèse'!E23+'105_Synthèse'!E23+'106_Synthèse'!E23 -> 37622.549 | F23: =+'104_Synthèse'!F23+'105_Synthèse'!F23+'106_Synthèse'!F23 -> 37622.549 | G23: =+'104_Synthèse'!G23+'105_Synthèse'!G23+'106_Synthèse'!G23 -> 37622.549 | H23: =+'104_Synthèse'!H23+'105_Synthèse'!H23+'106_Synthèse'!H23 -> 37622.549 | I23: =+'104_Synthèse'!I23+'105_Synthèse'!I23+'106_Synthèse'!I23 -> 37622.549 | ... M23: =+'104_Synthèse'!M23+'105_Synthèse'!M23+'106_Synthèse'!M23 -> 37622.549 | N23: =SUM(B23:M23) -> 451470.59 | O23: =+'104_Synthèse'!O23+'105_Synthèse'!O23++'106_Synthèse'!O23 -> 625000 | P23: =+N23-O23 -> -173529.41 | Q23: =+P23/O23 -> -0.27764706 | R23: ='106_Synthèse'!N23+'104_Synthèse'!N23+'105_Synthèse'!N23 -> 451470.59 | S23: =+N23-R23 -> 0
A24: Entretien | B24: =+'104_Synthèse'!B24+'105_Synthèse'!B24+'106_Synthèse'!B24 -> 12237.5 | C24: =+'104_Synthèse'!C24+'105_Synthèse'!C24+'106_Synthèse'!C24 -> 16075 | D24: =+'104_Synthèse'!D24+'105_Synthèse'!D24+'106_Synthèse'!D24 -> 16075 | E24: =+'104_Synthèse'!E24+'105_Synthèse'!E24+'106_Synthèse'!E24 -> 12237.5 | F24: =+'104_Synthèse'!F24+'105_Synthèse'!F24+'106_Synthèse'!F24 -> 12237.5 | G24: =+'104_Synthèse'!G24+'105_Synthèse'!G24+'106_Synthèse'!G24 -> 16075 | H24: =+'104_Synthèse'!H24+'105_Synthèse'!H24+'106_Synthèse'!H24 -> 16075 | I24: =+'104_Synthèse'!I24+'105_Synthèse'!I24+'106_Synthèse'!I24 -> 12237.5 | ... M24: =+'104_Synthèse'!M24+'105_Synthèse'!M24+'106_Synthèse'!M24 -> 3200 | N24: =SUM(B24:M24) -> 148925 | O24: =+'104_Synthèse'!O24+'105_Synthèse'!O24++'106_Synthèse'!O24 -> 308852.95 | P24: =+N24-O24 -> -159927.95 | Q24: =+P24/O24 -> -0.5178126 | R24: ='106_Synthèse'!N24+'104_Synthèse'!N24+'105_Synthèse'!N24 -> 148925 | S24: =+N24-R24 -> 0
A25: Main d'œuvre Directe | B25: =+'104_Synthèse'!B25+'105_Synthèse'!B25+'106_Synthèse'!B25 -> 354391.69 | C25: =+'104_Synthèse'!C25+'105_Synthèse'!C25+'106_Synthèse'!C25 -> 309277.47 | D25: =+'104_Synthèse'!D25+'105_Synthèse'!D25+'106_Synthèse'!D25 -> 278050.93 | E25: =+'104_Synthèse'!E25+'105_Synthèse'!E25+'106_Synthèse'!E25 -> 277413.75 | F25: =+'104_Synthèse'!F25+'105_Synthèse'!F25+'106_Synthèse'!F25 -> 271051.42 | G25: =+'104_Synthèse'!G25+'105_Synthèse'!G25+'106_Synthèse'!G25 -> 261371.35 | H25: =+'104_Synthèse'!H25+'105_Synthèse'!H25+'106_Synthèse'!H25 -> 259638.92 | I25: =+'104_Synthèse'!I25+'105_Synthèse'!I25+'106_Synthèse'!I25 -> 259783.08 | ... M25: =+'104_Synthèse'!M25+'105_Synthèse'!M25+'106_Synthèse'!M25 -> 6316.4706 | N25: =SUM(B25:M25) -> 2548738.8 | O25: =+'104_Synthèse'!O25+'105_Synthèse'!O25++'106_Synthèse'!O25 -> 3967234.3 | P25: =+N25-O25 -> -1418495.5 | Q25: =+P25/O25 -> -0.35755275 | R25: ='106_Synthèse'!N25+'104_Synthèse'!N25+'105_Synthèse'!N25 -> 2548738.8 | S25: =+N25-R25 -> 0
A26: Main d'œuvre Adm. | B26: =+'104_Synthèse'!B26+'105_Synthèse'!B26+'106_Synthèse'!B26 -> 77340 | C26: =+'104_Synthèse'!C26+'105_Synthèse'!C26+'106_Synthèse'!C26 -> 77340 | D26: =+'104_Synthèse'!D26+'105_Synthèse'!D26+'106_Synthèse'!D26 -> 77340 | E26: =+'104_Synthèse'!E26+'105_Synthèse'!E26+'106_Synthèse'!E26 -> 77340 | F26: =+'104_Synthèse'!F26+'105_Synthèse'!F26+'106_Synthèse'!F26 -> 77340 | G26: =+'104_Synthèse'!G26+'105_Synthèse'!G26+'106_Synthèse'!G26 -> 77340 | H26: =+'104_Synthèse'!H26+'105_Synthèse'!H26+'106_Synthèse'!H26 -> 77340 | I26: =+'104_Synthèse'!I26+'105_Synthèse'!I26+'106_Synthèse'!I26 -> 77340 | ... M26: =+'104_Synthèse'!M26+'105_Synthèse'!M26+'106_Synthèse'!M26 -> 77340 | N26: =SUM(B26:M26) -> 928080 | O26: =+'104_Synthèse'!O26+'105_Synthèse'!O26++'106_Synthèse'!O26 -> 815705.55 | P26: =+N26-O26 -> 112374.45 | Q26: =+P26/O26 -> 0.13776349 | R26: ='106_Synthèse'!N26+'104_Synthèse'!N26+'105_Synthèse'!N26 -> 928080 | S26: =+N26-R26 -> 0
A27: Refact. HIJOS DE FEDERICO LIS | B27: =+'104_Synthèse'!B27+'105_Synthèse'!B27+'106_Synthèse'!B27 -> 0 | C27: =+'104_Synthèse'!C27+'105_Synthèse'!C27+'106_Synthèse'!C27 -> 0 | D27: =+'104_Synthèse'!D27+'105_Synthèse'!D27+'106_Synthèse'!D27 -> 0 | E27: =+'104_Synthèse'!E27+'105_Synthèse'!E27+'106_Synthèse'!E27 -> 0 | F27: =+'104_Synthèse'!F27+'105_Synthèse'!F27+'106_Synthèse'!F27 -> 0 | G27: =+'104_Synthèse'!G27+'105_Synthèse'!G27+'106_Synthèse'!G27 -> 0 | H27: =+'104_Synthèse'!H27+'105_Synthèse'!H27+'106_Synthèse'!H27 -> 0 | I27: =+'104_Synthèse'!I27+'105_Synthèse'!I27+'106_Synthèse'!I27 -> 0 | ... M27: =+'104_Synthèse'!M27+'105_Synthèse'!M27+'106_Synthèse'!M27 -> 0 | N27: =SUM(B27:M27) -> 0 | O27: =+'104_Synthèse'!O27+'105_Synthèse'!O27++'106_Synthèse'!O27 -> 396966.06 | P27: =+N27-O27 -> -396966.06 | Q27: =+P27/O27 -> -1 | R27: ='106_Synthèse'!N27+'104_Synthèse'!N27+'105_Synthèse'!N27 -> 0 | S27: =+N27-R27 -> 0
A28: Transport | B28: =+'104_Synthèse'!B28+'105_Synthèse'!B28+'106_Synthèse'!B28 -> 0 | C28: =+'104_Synthèse'!C28+'105_Synthèse'!C28+'106_Synthèse'!C28 -> 0 | D28: =+'104_Synthèse'!D28+'105_Synthèse'!D28+'106_Synthèse'!D28 -> 0 | E28: =+'104_Synthèse'!E28+'105_Synthèse'!E28+'106_Synthèse'!E28 -> 0 | F28: =+'104_Synthèse'!F28+'105_Synthèse'!F28+'106_Synthèse'!F28 -> 23025000 | G28: =+'104_Synthèse'!G28+'105_Synthèse'!G28+'106_Synthèse'!G28 -> 17268750 | H28: =+'104_Synthèse'!H28+'105_Synthèse'!H28+'106_Synthèse'!H28 -> 17268750 | I28: =+'104_Synthèse'!I28+'105_Synthèse'!I28+'106_Synthèse'!I28 -> 23025000 | ... M28: =+'104_Synthèse'!M28+'105_Synthèse'!M28+'106_Synthèse'!M28 -> 5756250 | N28: =SUM(B28:M28) -> 1.3239375e+08 | O28: =+'104_Synthèse'!O28+'105_Synthèse'!O28++'106_Synthèse'!O28 -> 142933 | P28: =+N28-O28 -> 1.3225082e+08 | Q28: =+P28/O28 -> 925.2644 | R28: ='106_Synthèse'!N28+'104_Synthèse'!N28+'105_Synthèse'!N28 -> 1.3239375e+08 | S28: =+N28-R28 -> 0
A29: Autres frais généraux | B29: =+'104_Synthèse'!B29+'105_Synthèse'!B29+'106_Synthèse'!B29 -> 190150 | C29: =+'104_Synthèse'!C29+'105_Synthèse'!C29+'106_Synthèse'!C29 -> 9550 | D29: =+'104_Synthèse'!D29+'105_Synthèse'!D29+'106_Synthèse'!D29 -> 9550 | E29: =+'104_Synthèse'!E29+'105_Synthèse'!E29+'106_Synthèse'!E29 -> 9550 | F29: =+'104_Synthèse'!F29+'105_Synthèse'!F29+'106_Synthèse'!F29 -> 9550 | G29: =+'104_Synthèse'!G29+'105_Synthèse'!G29+'106_Synthèse'!G29 -> 9550 | H29: =+'104_Synthèse'!H29+'105_Synthèse'!H29+'106_Synthèse'!H29 -> 13750 | I29: =+'104_Synthèse'!I29+'105_Synthèse'!I29+'106_Synthèse'!I29 -> 9550 | ... M29: =+'104_Synthèse'!M29+'105_Synthèse'!M29+'106_Synthèse'!M29 -> 9550 | N29: =SUM(B29:M29) -> 314400 | O29: =+'104_Synthèse'!O29+'105_Synthèse'!O29++'106_Synthèse'!O29 -> 195350.25 | P29: =+N29-O29 -> 119049.75 | Q29: =+P29/O29 -> 0.60941693 | R29: ='106_Synthèse'!N29+'104_Synthèse'!N29+'105_Synthèse'!N29 -> 314400 | S29: =+N29-R29 -> 0
A30: Coût de revient total | B30: =SUM(B22:B29)+B21+B18 -> #DIV/0! | C30: =SUM(C22:C29)+C21+C18 -> #DIV/0! | D30: =SUM(D22:D29)+D21+D18 -> #DIV/0! | E30: =SUM(E22:E29)+E21+E18 -> #DIV/0! | F30: =SUM(F22:F29)+F21+F18 -> #DIV/0! | G30: =SUM(G22:G29)+G21+G18 -> #DIV/0! | H30: =SUM(H22:H29)+H21+H18 -> #DIV/0! | I30: =SUM(I22:I29)+I21+I18 -> #DIV/0! | ... M30: =SUM(M22:M29)+M21+M18 -> #DIV/0! | N30: =SUM(B30:M30) -> #DIV/0! | O30: =SUM(O22:O29)+O21+O18 -> 12582357 | P30: =+N30-O30 -> #DIV/0! | Q30: =+P30/O30 -> #DIV/0! | R30: ='106_Synthèse'!N30+'104_Synthèse'!N30+'105_Synthèse'!N30 -> #DIV/0! | S30: =+N30-R30 -> #DIV/0!
A31: EBITDA | B31: =B11-B30 -> #DIV/0! | C31: =C11-C30 -> #DIV/0! | D31: =D11-D30 -> #DIV/0! | E31: =E11-E30 -> #DIV/0! | F31: =F11-F30 -> #DIV/0! | G31: =G11-G30 -> #DIV/0! | H31: =H11-H30 -> #DIV/0! | I31: =I11-I30 -> #DIV/0! | ... O31: =O11-O30 -> 221600.11 | P31: =+N31-O31 -> #DIV/0! | Q31: =+P31/O31 -> #DIV/0! | R31: ='106_Synthèse'!N31+'104_Synthèse'!N31+'105_Synthèse'!N31 -> #DIV/0! | S31: =+N31-R31 -> #DIV/0!
A32: Amortissements | B32: =+'104_Synthèse'!B32+'105_Synthèse'!B32+'106_Synthèse'!B32 -> 240339.33 | C32: =+'104_Synthèse'!C32+'105_Synthèse'!C32+'106_Synthèse'!C32 -> 240339.33 | D32: =+'104_Synthèse'!D32+'105_Synthèse'!D32+'106_Synthèse'!D32 -> 240339.33 | E32: =+'104_Synthèse'!E32+'105_Synthèse'!E32+'106_Synthèse'!E32 -> 240339.33 | F32: =+'104_Synthèse'!F32+'105_Synthèse'!F32+'106_Synthèse'!F32 -> 240339.33 | G32: =+'104_Synthèse'!G32+'105_Synthèse'!G32+'106_Synthèse'!G32 -> 240339.33 | H32: =+'104_Synthèse'!H32+'105_Synthèse'!H32+'106_Synthèse'!H32 -> 240339.33 | I32: =+'104_Synthèse'!I32+'105_Synthèse'!I32+'106_Synthèse'!I32 -> 240339.33 | ... M32: =+'104_Synthèse'!M32+'105_Synthèse'!M32+'106_Synthèse'!M32 -> 243355.16 | N32: =SUM(B32:M32) -> 2893119.4 | O32: =+'104_Synthèse'!O32+'105_Synthèse'!O32++'106_Synthèse'!O32 -> 2724261.2 | P32: =+N32-O32 -> 168858.2 | Q32: =+P32/O32 -> 0.061983115 | R32: ='106_Synthèse'!N32+'104_Synthèse'!N32+'105_Synthèse'!N32 -> 2893119.4 | S32: =+N32-R32 -> 0
A33: Résultat d'exploitation | B33: =B31-B32 -> #DIV/0! | C33: =C31-C32 -> #DIV/0! | D33: =D31-D32 -> #DIV/0! | E33: =E31-E32 -> #DIV/0! | F33: =F31-F32 -> #DIV/0! | G33: =G31-G32 -> #DIV/0! | H33: =H31-H32 -> #DIV/0! | I33: =I31-I32 -> #DIV/0! | ... O33: =O31-O32 -> -2502661.1 | P33: =+N33-O33 -> #DIV/0! | Q33: =+P33/O33 -> #DIV/0! | R33: ='106_Synthèse'!N33+'104_Synthèse'!N33+'105_Synthèse'!N33 -> #DIV/0! | S33: =+N33-R33 -> #DIV/0!
A34: Résultat net en % du CA | N34: =+N33/N7 -> #DIV/0! | O34: =+O33/O7 -> -0.22217614 | P34: =+N34-O34 -> #DIV/0!
A35: EBITDA en % du CA | N35: =+N31/N7 -> #DIV/0! | O35: =+O31/O7 -> 0.019672762 | P35: =+N35-O35 -> #DIV/0!
A36: PMV au kg | B36: =+(B7)/B5 -> #DIV/0! | C36: =+(C7)/C5 -> #DIV/0! | D36: =+(D7)/D5 -> #DIV/0! | E36: =+(E7)/E5 -> 0 | F36: =+(F7)/F5 -> 0.028335253 | G36: =+(G7)/G5 -> 0.028335253 | H36: =+(H7)/H5 -> 0.028335253 | I36: =+(I7)/I5 -> 0.028335253 | ... O36: =+(O7)/O5 -> 5.6804578 | P36: =+N36-O36 -> -5.6563102 | Q36: =+P36/O36 -> -0.99574901 | S36: =+'104_Synthèse'!O33+'105_Synthèse'!O33+'106_Synthèse'!O33 -> -2502661.1
A37: CA à l'hectare prod | B37: =+B7/B4 -> 0 | C37: =+C7/C4 -> 0 | D37: =+D7/D4 -> 0 | E37: =+E7/E4 -> 0 | F37: =+F7/F4 -> 117444.53 | G37: =+G7/G4 -> 88083.397 | H37: =+H7/H4 -> 88083.397 | I37: =+I7/I4 -> 117444.53 | ... O37: =+O7/O4 -> 651116.24 | P37: =+N37-O37 -> 24189.806 | Q37: =+P37/O37 -> 0.037151287 | S37: =+O33-S36 -> 0
A38: Coût à l'hectare prod (hors Amort) | B38: =+(B30-B10)/B4 -> #DIV/0! | C38: =+(C30-C10)/C4 -> #DIV/0! | D38: =+(D30-D10)/D4 -> #DIV/0! | E38: =+(E30-E10)/E4 -> #DIV/0! | F38: =+(F30-F10)/F4 -> #DIV/0! | G38: =+(G30-G10)/G4 -> #DIV/0! | H38: =+(H30-H10)/H4 -> #DIV/0! | I38: =+(I30-I10)/I4 -> #DIV/0! | ... O38: =+(O30-O10)/O4 -> 727303.86 | P38: =+N38-O38 -> #DIV/0! | Q38: =+P38/O38 -> #DIV/0!
A39: EBITDA à l'hectare prod | B39: =+B31/B4 -> #DIV/0! | C39: =+C31/C4 -> #DIV/0! | D39: =+D31/D4 -> #DIV/0! | E39: =+E31/E4 -> #DIV/0! | F39: =+F31/F4 -> #DIV/0! | G39: =+G31/G4 -> #DIV/0! | H39: =+H31/H4 -> #DIV/0! | I39: =+I31/I4 -> #DIV/0! | ... O39: =+O31/O4 -> 12809.255 | P39: =+N39-O39 -> #DIV/0! | Q39: =+P39/O39 -> #DIV/0!
A40: Coût total à l'hectare prod | B40: =+(B30+B32-B10)/B4 -> #DIV/0! | C40: =+(C30+C32-C10)/C4 -> #DIV/0! | D40: =+(D30+D32-D10)/D4 -> #DIV/0! | E40: =+(E30+E32-E10)/E4 -> #DIV/0! | F40: =+(F30+F32-F10)/F4 -> #DIV/0! | G40: =+(G30+G32-G10)/G4 -> #DIV/0! | H40: =+(H30+H32-H10)/H4 -> #DIV/0! | I40: =+(I30+I32-I10)/I4 -> #DIV/0! | ... O40: =+(O30+O32-O10)/O4 -> 884775.61 | P40: =+N40-O40 -> #DIV/0! | Q40: =+P40/O40 -> #DIV/0!
A41: REX à l'hectare prod | B41: =B33/B4 -> #DIV/0! | C41: =C33/C4 -> #DIV/0! | D41: =D33/D4 -> #DIV/0! | E41: =E33/E4 -> #DIV/0! | F41: =F33/F4 -> #DIV/0! | G41: =G33/G4 -> #DIV/0! | H41: =H33/H4 -> #DIV/0! | I41: =I33/I4 -> #DIV/0! | ... O41: =O33/O4 -> -144662.49 | P41: =+N41-O41 -> #DIV/0! | Q41: =+P41/O41 -> #DIV/0!
A42: Détail des coûts à l'hectare
A43: Coût total à l'hectare | B43: =+(B30+B32)/B3 -> #DIV/0! | C43: =+(C30+C32)/C3 -> #DIV/0! | D43: =+(D30+D32)/D3 -> #DIV/0! | E43: =+(E30+E32)/E3 -> #DIV/0! | F43: =+(F30+F32)/F3 -> #DIV/0! | G43: =+(G30+G32)/G3 -> #DIV/0! | H43: =+(H30+H32)/H3 -> #DIV/0! | I43: =+(I30+I32)/I3 -> #DIV/0! | ... M43: =+(M30+M32)/M3 -> #DIV/0! | N43: =+(N30+N32-N10)/N3 -> #DIV/0! | O43: =+(O30+O32-O10)/O3 -> 884775.61 | P43: =+N43-O43 -> #DIV/0! | Q43: =+P43/O43 -> #DIV/0!
A44: Coût à l'hectare (hors Amort) | B44: =+B30/B3 -> #DIV/0! | C44: =+C30/C3 -> #DIV/0! | D44: =+D30/D3 -> #DIV/0! | E44: =+E30/E3 -> #DIV/0! | F44: =+F30/F3 -> #DIV/0! | G44: =+G30/G3 -> #DIV/0! | H44: =+H30/H3 -> #DIV/0! | I44: =+I30/I3 -> #DIV/0! | ... M44: =+M30/M3 -> #DIV/0! | N44: =+(N30-N10)/N3 -> #DIV/0! | O44: =+(O30-O10)/O3 -> 727303.86 | P44: =+N44-O44 -> #DIV/0! | Q44: =+P44/O44 -> #DIV/0!
A45: Semences | B45: =+B12/B3 -> 0.57399103 | C45: =+C12/C3 -> 268090.26 | D45: =+D12/D3 -> 0.57399103 | E45: =+E12/E3 -> 0.57399103 | F45: =+F12/F3 -> 0.57399103 | G45: =+G12/G3 -> 0.57399103 | H45: =+H12/H3 -> 0.57399103 | I45: =+I12/I3 -> 0.57399103 | ... O45: =+O12/O3 -> 85965.795 | P45: =+N45-O45 -> 182130.78 | Q45: =+P45/O45 -> 2.1186424
A46: Engrais | B46: =+B13/B3 -> 0 | C46: =+C13/C3 -> 0 | D46: =+D13/D3 -> 0 | E46: =+E13/E3 -> 0 | F46: =+F13/F3 -> 0 | G46: =+G13/G3 -> 0 | H46: =+H13/H3 -> 0 | I46: =+I13/I3 -> 0 | ... O46: =+O13/O3 -> 109473.54 | P46: =+N46-O46 -> -109473.54 | Q46: =+P46/O46 -> -1
A47: Plants | B47: =+B14/B3 -> 0 | C47: =+C14/C3 -> 199641.26 | D47: =+D14/D3 -> 0 | E47: =+E14/E3 -> 0 | F47: =+F14/F3 -> 0 | G47: =+G14/G3 -> 0 | H47: =+H14/H3 -> 0 | I47: =+I14/I3 -> 0 | ... O47: =+O14/O3 -> 38737.526 | P47: =+N47-O47 -> 160903.73 | Q47: =+P47/O47 -> 4.1536914
A48: Phytos | B48: =+B15/B3 -> 0 | C48: =+C15/C3 -> 0 | D48: =+D15/D3 -> 0 | E48: =+E15/E3 -> 0 | F48: =+F15/F3 -> 0 | G48: =+G15/G3 -> 0 | H48: =+H15/H3 -> 0 | I48: =+I15/I3 -> 0 | ... O48: =+O15/O3 -> 73567.936 | P48: =+N48-O48 -> -73567.936 | Q48: =+P48/O48 -> -1
A49: Insectes | B49: =+B16/B3 -> 0.84304933 | C49: =+C16/C3 -> 0.84304933 | D49: =+D16/D3 -> 0.84304933 | E49: =+E16/E3 -> 0.84304933 | F49: =+F16/F3 -> 0.84304933 | G49: =+G16/G3 -> 0.84304933 | H49: =+H16/H3 -> 0.84304933 | I49: =+I16/I3 -> 0.84304933 | ... O49: =+O16/O3 -> 17789.885 | P49: =+N49-O49 -> -17779.768 | Q49: =+P49/O49 -> -0.99943133
A50: Autres fournitures agricoles | B50: =+B17/B3 -> 86015.067 | C50: =+C17/C3 -> 2753.3632 | D50: =+D17/D3 -> 2753.3632 | E50: =+E17/E3 -> 2753.3632 | F50: =+F17/F3 -> 2753.3632 | G50: =+G17/G3 -> 2753.3632 | H50: =+H17/H3 -> 2753.3632 | I50: =+I17/I3 -> 2753.3632 | ... O50: =+O17/O3 -> 8204.2163 | P50: =+N50-O50 -> 108097.85 | Q50: =+P50/O50 -> 13.175889
A51: Electricité | B51: =+B19/B3 -> 0 | C51: =+C19/C3 -> 0 | D51: =+D19/D3 -> 0 | E51: =+E19/E3 -> 0 | F51: =+F19/F3 -> 0 | G51: =+G19/G3 -> 0 | H51: =+H19/H3 -> 0 | I51: =+I19/I3 -> 0 | ... O51: =+O19/O3 -> 14486.409 | P51: =+N51-O51 -> -14486.409 | Q51: =+P51/O51 -> -1
A52: Eau | B52: =+B20/B3 -> #DIV/0! | C52: =+C20/C3 -> #DIV/0! | D52: =+D20/D3 -> #DIV/0! | E52: =+E20/E3 -> #DIV/0! | F52: =+F20/F3 -> #DIV/0! | G52: =+G20/G3 -> #DIV/0! | H52: =+H20/H3 -> #DIV/0! | I52: =+I20/I3 -> #DIV/0! | ... O52: =+O20/O3 -> 2746.727 | P52: =+N52-O52 -> #DIV/0! | Q52: =+P52/O52 -> #DIV/0!
A53: Prestations & analyses | B53: =+B22/B3 -> 0 | C53: =+C22/C3 -> 11013.453 | D53: =+D22/D3 -> 0 | E53: =+E22/E3 -> 0 | F53: =+F22/F3 -> 0 | G53: =+G22/G3 -> 0 | H53: =+H22/H3 -> 0 | I53: =+I22/I3 -> 0 | ... O53: =+O22/O3 -> 3381.4181 | P53: =+N53-O53 -> 7632.0348 | Q53: =+P53/O53 -> 2.2570515
A54: Loyers fermes | B54: =+B23/B3 -> 6748.4393 | C54: =+C23/C3 -> 6748.4393 | D54: =+D23/D3 -> 6748.4393 | E54: =+E23/E3 -> 6748.4393 | F54: =+F23/F3 -> 6748.4393 | G54: =+G23/G3 -> 6748.4393 | H54: =+H23/H3 -> 6748.4393 | I54: =+I23/I3 -> 6748.4393 | ... O54: =+O23/O3 -> 36127.168 | P54: =+N54-O54 -> 44854.104 | Q54: =+P54/O54 -> 1.2415616
A55: Entretien | B55: =+B24/B3 -> 2195.0673 | C55: =+C24/C3 -> 2883.4081 | D55: =+D24/D3 -> 2883.4081 | E55: =+E24/E3 -> 2195.0673 | F55: =+F24/F3 -> 2195.0673 | G55: =+G24/G3 -> 2883.4081 | H55: =+H24/H3 -> 2883.4081 | I55: =+I24/I3 -> 2195.0673 | ... O55: =+O24/O3 -> 17852.771 | P55: =+N55-O55 -> 8860.233 | Q55: =+P55/O55 -> 0.49629454
A56: Main d'œuvre Directe | B56: =+B25/B3 -> 63568.016 | C56: =+C25/C3 -> 55475.78 | D56: =+D25/D3 -> 49874.606 | E56: =+E25/E3 -> 49760.313 | F56: =+F25/F3 -> 48619.088 | G56: =+G25/G3 -> 46882.754 | H56: =+H25/H3 -> 46572.004 | I56: =+I25/I3 -> 46597.862 | ... O56: =+O25/O3 -> 229319.9 | P56: =+N56-O56 -> 227852.97 | Q56: =+P56/O56 -> 0.99360312
A57: Main d'œuvre Adm. | B57: =+B26/B3 -> 13872.646 | C57: =+C26/C3 -> 13872.646 | D57: =+D26/D3 -> 13872.646 | E57: =+E26/E3 -> 13872.646 | F57: =+F26/F3 -> 13872.646 | G57: =+G26/G3 -> 13872.646 | H57: =+H26/H3 -> 13872.646 | I57: =+I26/I3 -> 13872.646 | ... O57: =+O26/O3 -> 47150.61 | P57: =+N57-O57 -> 119321.14 | Q57: =+P57/O57 -> 2.5306383
A58: Refact. HIJOS DE FEDERICO LIS | B58: =+B27/B3 -> 0 | C58: =+C27/C3 -> 0 | D58: =+D27/D3 -> 0 | E58: =+E27/E3 -> 0 | F58: =+F27/F3 -> 0 | G58: =+G27/G3 -> 0 | H58: =+H27/H3 -> 0 | I58: =+I27/I3 -> 0 | ... O58: =+O27/O3 -> 22946.015 | P58: =+N58-O58 -> -22946.015 | Q58: =+P58/O58 -> -1
A59: Transport | B59: =+B28/B3 -> 0 | C59: =+C28/C3 -> 0 | D59: =+D28/D3 -> 0 | E59: =+E28/E3 -> 0 | F59: =+F28/F3 -> 4130044.8 | G59: =+G28/G3 -> 3097533.6 | H59: =+H28/H3 -> 3097533.6 | I59: =+I28/I3 -> 4130044.8 | ... O59: =+O28/O3 -> 8262.0231 | P59: =+N59-O59 -> 23739496 | Q59: =+P59/O59 -> 2873.3272
A60: Autres frais généraux | B60: =+B29/B3 -> 34107.623 | C60: =+C29/C3 -> 1713.0045 | D60: =+D29/D3 -> 1713.0045 | E60: =+E29/E3 -> 1713.0045 | F60: =+F29/F3 -> 1713.0045 | G60: =+G29/G3 -> 1713.0045 | H60: =+H29/H3 -> 2466.3677 | I60: =+I29/I3 -> 1713.0045 | ... O60: =+O29/O3 -> 11291.922 | P60: =+N60-O60 -> 45102.697 | Q60: =+P60/O60 -> 3.9942445
A61: Amortissements | B61: =+B32/B3 -> 43110.193 | C61: =+C32/C3 -> 43110.193 | D61: =+D32/D3 -> 43110.193 | E61: =+E32/E3 -> 43110.193 | F61: =+F32/F3 -> 43110.193 | G61: =+G32/G3 -> 43110.193 | H61: =+H32/H3 -> 43110.193 | I61: =+I32/I3 -> 43110.193 | ... O61: =+O32/O3 -> 157471.75 | P61: =+N61-O61 -> 361473.44 | Q61: =+P61/O61 -> 2.2954812
A62: Calcul des encours
A63: Encours initial | D63: =+B10+C10+D10 -> #DIV/0!
A64: Coût des encours | D64: =+D63/N5 -> #DIV/0! | E64: =+D64 -> #DIV/0! | F64: =+E64 -> #DIV/0! | G64: =+F64 -> #DIV/0! | H64: =+G64 -> #DIV/0! | I64: =+H64 -> #DIV/0! | J64: =+I64 -> #DIV/0! | K64: =+J64 -> #DIV/0! | L64: =+K64 -> #DIV/0! | M64: =+L64 -> #DIV/0!
A65: Coût des ventes | E65: =+E64*E5 -> #DIV/0! | F65: =+F64*F5 -> #DIV/0! | G65: =+G64*G5 -> #DIV/0! | H65: =+H64*H5 -> #DIV/0! | I65: =+I64*I5 -> #DIV/0! | J65: =+J64*J5 -> #DIV/0! | K65: =+K64*K5 -> #DIV/0! | L65: =+L64*L5 -> #DIV/0! | M65: =+M64*M5 -> #DIV/0!
A66: Encours fin de période | E66: =+D63-E65 -> #DIV/0! | F66: =+E66-F65 -> #DIV/0! | G66: =+F66-G65 -> #DIV/0! | H66: =+G66-H65 -> #DIV/0! | I66: =+H66-I65 -> #DIV/0! | J66: =+I66-J65 -> #DIV/0! | K66: =+J66-K65 -> #DIV/0! | L66: =+K66-L65 -> #DIV/0! | M66: =+L66-M65 -> #DIV/0!
A67: Variation encours | E67: =+E66-D63 -> #DIV/0! | F67: =+F66-E66 -> #DIV/0! | G67: =+G66-F66 -> #DIV/0! | H67: =+H66-G66 -> #DIV/0! | I67: =+I66-H66 -> #DIV/0! | J67: =+J66-I66 -> #DIV/0! | K67: =+K66-J66 -> #DIV/0! | L67: =+L66-K66 -> #DIV/0! | M67: =+M66-L66 -> #DIV/0!

Sheet Feuil1

Sheet 104_Synthèse
B1: BUD | C1: BUD | D1: BUD | E1: BUD | F1: BUD | G1: BUD | H1: BUD | I1: BUD | J1: BUD | K1: BUD | L1: BUD | M1: BUD | N1: BUD | O1: REEL | P1: VARIATION | Q1: VARIATION
A2: 104 - Analyse totale (MAD) | B2: 45839 | C2: =+B2+31 -> 45870 | D2: =+C2+31 -> 45901 | E2: =+D2+31 -> 45932 | F2: =+E2+31 -> 45963 | G2: =+F2+31 -> 45994 | H2: =+G2+31 -> 46025 | I2: =+H2+31 -> 46056 | J2: =+I2+31 -> 46087 | ... M2: =+L2+31 -> 46180 | N2: 19/20 | O2: 18/19 | P2: BUD-REEL | Q2: % | R2: source | S2: check
A3: Sup Tot (ha) | B3: =+'Plan de culture 104 '!$B$3 -> 0 | C3: =+'Plan de culture 104 '!$B$3 -> 0 | D3: =+'Plan de culture 104 '!$B$3 -> 0 | E3: =+'Plan de culture 104 '!$B$3 -> 0 | F3: =+'Plan de culture 104 '!$B$3 -> 0 | G3: =+'Plan de culture 104 '!$B$3 -> 0 | H3: =+'Plan de culture 104 '!$B$3 -> 0 | I3: =+'Plan de culture 104 '!$B$3 -> 0 | ... N3: =+'Plan de culture 104 '!$B$3 -> 0 | O3: 6.8 | P3: =+N3-O3 -> -6.8 | Q3: =+P3/O3 -> -1 | R3: =+'Plan de culture 104 '!$B$3 -> 0 | S3: =+N3-R3 -> 0
A4: Sup productive | B4: ='Plan de culture 104 '!$C$3 -> 15.35 | C4: ='Plan de culture 104 '!$C$3 -> 15.35 | D4: ='Plan de culture 104 '!$C$3 -> 15.35 | E4: ='Plan de culture 104 '!$C$3 -> 15.35 | F4: ='Plan de culture 104 '!$C$3 -> 15.35 | G4: ='Plan de culture 104 '!$C$3 -> 15.35 | H4: ='Plan de culture 104 '!$C$3 -> 15.35 | I4: ='Plan de culture 104 '!$C$3 -> 15.35 | ... N4: ='Plan de culture 104 '!$C$3 -> 15.35 | O4: 6.8 | P4: =+N4-O4 -> 8.55 | Q4: =+P4/O4 -> 1.2573529 | R4: =+'Budget Volumes Export'!N8 -> 15.35 | S4: =+N4-R4 -> 0
A5: Vol (kg) | B5: =+'Budget Volumes Export'!B7+'Budget Volumes ML'!B7 -> 0 | C5: =+'Budget Volumes Export'!C7+'Budget Volumes ML'!C7 -> 0 | D5: =+'Budget Volumes Export'!D7+'Budget Volumes ML'!D7 -> 0 | E5: =+'Budget Volumes Export'!E7+'Budget Volumes ML'!E7 -> 30700 | F5: =+'Budget Volumes Export'!F7+'Budget Volumes ML'!F7 -> 337700 | G5: =+'Budget Volumes Export'!G7+'Budget Volumes ML'!G7 -> 253275 | H5: =+'Budget Volumes Export'!H7+'Budget Volumes ML'!H7 -> 253275 | I5: =+'Budget Volumes Export'!I7+'Budget Volumes ML'!I7 -> 337700 | ... M5: =+'Budget Volumes Export'!M7+'Budget Volumes ML'!M7 -> 84425 | N5: =SUM(B5:M5) -> 1972475 | O5: 1108263.7 | P5: =+N5-O5 -> 864211.32 | Q5: =+P5/O5 -> 0.77978854 | R5: =+'Budget Volumes Export'!N7*1000 -> 1.76525e+09 | S5: =+N5-R5 -> -1.7632775e+09
A6: rendement (t/ha) | B6: ='Budget Volumes Export'!B9+'Budget Volumes ML'!B9 -> 0 | C6: ='Budget Volumes Export'!C9+'Budget Volumes ML'!C9 -> 0 | D6: ='Budget Volumes Export'!D9+'Budget Volumes ML'!D9 -> 0 | E6: ='Budget Volumes Export'!E9+'Budget Volumes ML'!E9 -> 2000 | F6: ='Budget Volumes Export'!F9+'Budget Volumes ML'!F9 -> 22000 | G6: ='Budget Volumes Export'!G9+'Budget Volumes ML'!G9 -> 16500 | H6: ='Budget Volumes Export'!H9+'Budget Volumes ML'!H9 -> 16500 | I6: ='Budget Volumes Export'!I9+'Budget Volumes ML'!I9 -> 22000 | ... N6: ='Budget Volumes Export'!N9+'Budget Volumes ML'!N9 -> 128500 | O6: =+O5/O4/1000 -> 162.97995 | P6: =+N6-O6 -> 128337.02 | Q6: =+P6/O6 -> 787.44053 | R6: =+R5/R4/1000 -> 115000 | S6: =+N6-R6 -> 13500
A7: CA EXPORT(MAD) | B7: =+'Budget Commercial Export'!B7 -> 0 | C7: =+'Budget Commercial Export'!C7 -> 0 | D7: =+'Budget Commercial Export'!D7 -> 0 | E7: =+'Budget Commercial Export'!E7 -> 0 | F7: =+'Budget Commercial Export'!F7 -> 3070000 | G7: =+'Budget Commercial Export'!G7 -> 2302500 | H7: =+'Budget Commercial Export'!H7 -> 2302500 | I7: =+'Budget Commercial Export'!I7 -> 3070000 | ... M7: =+'Budget Commercial Export'!M7 -> 767500 | N7: =SUM(B7:M7) -> 17652500 | O7: 2538893.7 | P7: =+N7-O7 -> 15113606 | Q7: =+P7/O7 -> 5.9528315 | R7: =+'Budget Commercial Export'!N7 -> 17652500 | S7: =+N7-R7 -> 0
A8: CA MARCHE LOCAL(MAD) | B8: =+'Budget Commercial ML'!B7 -> 0 | C8: =+'Budget Commercial ML'!C7 -> 0 | D8: =+'Budget Commercial ML'!D7 -> 0 | E8: =+'Budget Commercial ML'!E7 -> 30700 | F8: =+'Budget Commercial ML'!F7 -> 30700 | G8: =+'Budget Commercial ML'!G7 -> 23025 | H8: =+'Budget Commercial ML'!H7 -> 23025 | I8: =+'Budget Commercial ML'!I7 -> 30700 | ... M8: =+'Budget Commercial ML'!M7 -> 7675 | N8: =SUM(B8:M8) -> 207225 | O8: 0 | P8: =+N8-O8 -> 207225 | Q8: =+P8/O8 -> #DIV/0!
A9: Autres revenus (MAD) | N9: =SUM(B9:M9) -> 0 | O9: 1023632.5 | P9: =+N9-O9 -> -1023632.5 | Q9: =+P9/O9 -> -1
A10: Production encours (MAD) | B10: =SUM(B68:B82) -> #DIV/0! | C10: =SUM(C68:C82) -> #DIV/0! | D10: =SUM(D68:D82) -> #DIV/0! | E10: =+E66 -> #DIV/0! | F10: =+F66 -> #DIV/0! | G10: =+G66 -> #DIV/0! | H10: =+H66 -> #DIV/0! | I10: =+I66 -> #DIV/0! | J10: =+J66 -> #DIV/0! | K10: =+K66 -> #DIV/0! | L10: =+L66 -> #DIV/0! | M10: =+M66 -> #DIV/0! | N10: =SUM(B10:M10) -> #DIV/0! | O10: 0 | P10: =+N10-O10 -> #DIV/0! | Q10: =+P10/O10 -> #DIV/0! | R10: 0 | S10: =+N10-R10 -> #DIV/0!
A11: Production totale (MAD) | B11: =+B10+B7+B9 -> #DIV/0! | C11: =+C10+C7+C9 -> #DIV/0! | D11: =+D10+D7+D9 -> #DIV/0! | E11: =+E10+E7+E9 -> #DIV/0! | F11: =+F10+F7+F9 -> #DIV/0! | G11: =+G10+G7+G9 -> #DIV/0! | H11: =+H10+H7+H9 -> #DIV/0! | I11: =+I10+I7+I9 -> #DIV/0! | ... M11: =+M10+M7+M9 -> #DIV/0! | N11: =SUM(B11:M11) -> #DIV/0! | O11: =+O10+O7+O9 -> 3562526.2 | P11: =+N11-O11 -> #DIV/0! | Q11: =+P11/O11 -> #DIV/0!
A12: Consommation Semences | B12: =+'Budget Semences'!B7 -> 0 | C12: =+'Budget Semences'!C10 -> 1494600 | D12: =+'Budget Semences'!D10 -> 0 | E12: =+'Budget Semences'!E10 -> 0 | F12: =+'Budget Semences'!F10 -> 0 | G12: =+'Budget Semences'!G10 -> 0 | H12: =+'Budget Semences'!H10 -> 0 | I12: =+'Budget Semences'!I10 -> 0 | J12: =+'Budget Semences'!J10 -> 0 | ... M12: =+'Budget Semences'!M10 -> 0 | N12: =SUM(B12:M12) -> 1494600 | O12: 202400 | P12: =+N12-O12 -> 1292200 | Q12: =+P12/O12 -> 6.3843874 | R12: =+'Budget Semences'!N7 -> 1494600 | S12: =+N12-R12 -> 0
A13: Consommation Engrais | B13: =+'Budget Engrais'!B7 -> 0 | C13: =+'Budget Engrais'!C7 -> 0 | D13: =+'Budget Engrais'!D7 -> 0 | E13: =+'Budget Engrais'!E7 -> 0 | F13: =+'Budget Engrais'!F7 -> 0 | G13: =+'Budget Engrais'!G7 -> 0 | H13: =+'Budget Engrais'!H7 -> 0 | I13: =+'Budget Engrais'!I7 -> 0 | ... M13: =+'Budget Engrais'!M7 -> 0 | N13: =SUM(B13:M13) -> 0 | O13: 537520.18 | P13: =+N13-O13 -> -537520.18 | Q13: =+P13/O13 -> -1 | R13: =+'Budget Engrais'!N7 -> 0 | S13: =+N13-R13 -> 0
A14: Consommation Plants | B14: =+'Budget Plants'!B7 -> 0 | C14: =+'Budget Plants'!C7 -> 1113000 | D14: =+'Budget Plants'!D7 -> 0 | E14: =+'Budget Plants'!E7 -> 0 | F14: =+'Budget Plants'!F7 -> 0 | G14: =+'Budget Plants'!G7 -> 0 | H14: =+'Budget Plants'!H7 -> 0 | I14: =+'Budget Plants'!I7 -> 0 | ... M14: =+'Budget Plants'!M7 -> 0 | N14: =SUM(B14:M14) -> 1113000 | O14: 254887 | P14: =+N14-O14 -> 858113 | Q14: =+P14/O14 -> 3.3666409 | R14: =+'Budget Plants'!N7 -> 1113000 | S14: =+N14-R14 -> 0
A15: Consommation Phytos | B15: =+'Budget Phytos'!B7 -> 0 | C15: =+'Budget Phytos'!C7 -> 0 | D15: =+'Budget Phytos'!D7 -> 0 | E15: =+'Budget Phytos'!E7 -> 0 | F15: =+'Budget Phytos'!F7 -> 0 | G15: =+'Budget Phytos'!G7 -> 0 | H15: =+'Budget Phytos'!H7 -> 0 | I15: =+'Budget Phytos'!I7 -> 0 | ... M15: =+'Budget Phytos'!M7 -> 0 | N15: =SUM(B15:M15) -> 0 | O15: 582668.22 | P15: =+N15-O15 -> -582668.22 | Q15: =+P15/O15 -> -1 | R15: =+'Budget Phytos'!N7 -> 0 | S15: =+N15-R15 -> 0
A16: Consommation Insectes | B16: =+'Budget Ruches'!B7 -> 0 | C16: =+'Budget Ruches'!C7 -> 0 | D16: =+'Budget Ruches'!D7 -> 0 | E16: =+'Budget Ruches'!E7 -> 0 | F16: =+'Budget Ruches'!F7 -> 0 | G16: =+'Budget Ruches'!G7 -> 0 | H16: =+'Budget Ruches'!H7 -> 0 | I16: =+'Budget Ruches'!I7 -> 0 | ... M16: =+'Budget Ruches'!M7 -> 0 | N16: =SUM(B16:M16) -> 0 | O16: 107635.05 | P16: =+N16-O16 -> -107635.05 | Q16: =+P16/O16 -> -1 | R16: =+'Budget Ruches'!N7 -> 0 | S16: =+N16-R16 -> 0
A17: Autres fournitures agricoles | B17: =+'Budget Fres Agri'!B7 -> 479534 | C17: =+'Budget Fres Agri'!C7 -> 15350 | D17: =+'Budget Fres Agri'!D7 -> 15350 | E17: =+'Budget Fres Agri'!E7 -> 15350 | F17: =+'Budget Fres Agri'!F7 -> 15350 | G17: =+'Budget Fres Agri'!G7 -> 15350 | H17: =+'Budget Fres Agri'!H7 -> 15350 | I17: =+'Budget Fres Agri'!I7 -> 15350 | ... M17: =+'Budget Fres Agri'!M7 -> 15350 | N17: =SUM(B17:M17) -> 648384 | O17: 73551.904 | P17: =+N17-O17 -> 574832.1 | Q17: =+P17/O17 -> 7.8153258 | R17: =+'Budget Fres Agri'!N7 -> 648384 | S17: =+N17-R17 -> 0
A18: Total consommation Intrants | B18: =SUM(B12:B17) -> 479534 | C18: =SUM(C12:C17) -> 2622950 | D18: =SUM(D12:D17) -> 15350 | E18: =SUM(E12:E17) -> 15350 | F18: =SUM(F12:F17) -> 15350 | G18: =SUM(G12:G17) -> 15350 | H18: =SUM(H12:H17) -> 15350 | I18: =SUM(I12:I17) -> 15350 | ... M18: =SUM(M12:M17) -> 15350 | N18: =SUM(B18:M18) -> 3255984 | O18: =SUM(O12:O17) -> 1758662.4 | P18: =+N18-O18 -> 1497321.6 | Q18: =+P18/O18 -> 0.85139802 | R18: =+'Budget Semences'!N7+'Budget Plants'!N7+'Budget Engrais'!N7+'Budget Phytos'!N7+'Budget Ruches'!N7+'Budget Fres Agri'!N7 -> 3255984 | S18: =+N18-R18 -> 0
A19: Electricité | B19: =+'Budget Energie'!B15+'Budget Energie'!B22 -> 0 | C19: =+'Budget Energie'!C15+'Budget Energie'!C22 -> 0 | D19: =+'Budget Energie'!D15+'Budget Energie'!D22 -> 0 | E19: =+'Budget Energie'!E15+'Budget Energie'!E22 -> 0 | F19: =+'Budget Energie'!F15+'Budget Energie'!F22 -> 0 | G19: =+'Budget Energie'!G15+'Budget Energie'!G22 -> 0 | H19: =+'Budget Energie'!H15+'Budget Energie'!H22 -> 0 | I19: =+'Budget Energie'!I15+'Budget Energie'!I22 -> 0 | ... M19: =+'Budget Energie'!M15+'Budget Energie'!M22 -> 0 | N19: =SUM(B19:M19) -> 0 | O19: 91727.417 | P19: =+N19-O19 -> -91727.417 | Q19: =+P19/O19 -> -1 | R19: =+'Budget Energie'!N15+'Budget Energie'!N22 -> 0 | S19: =+N19-R19 -> 0
A20: Eau | B20: =+'Budget Energie'!B13+'Budget Energie'!B20 -> 0 | C20: =+'Budget Energie'!C13+'Budget Energie'!C20 -> 0 | D20: =+'Budget Energie'!D13+'Budget Energie'!D20 -> 0 | E20: =+'Budget Energie'!E13+'Budget Energie'!E20 -> 0 | F20: =+'Budget Energie'!F13+'Budget Energie'!F20 -> 0 | G20: =+'Budget Energie'!G13+'Budget Energie'!G20 -> 0 | H20: =+'Budget Energie'!H13+'Budget Energie'!H20 -> 0 | I20: =+'Budget Energie'!I13+'Budget Energie'!I20 -> 0 | ... M20: =+'Budget Energie'!M13+'Budget Energie'!M20 -> 0 | N20: =SUM(B20:M20) -> 0 | O20: 20637.641 | P20: =+N20-O20 -> -20637.641 | Q20: =+P20/O20 -> -1 | R20: =+'Budget Energie'!N13+'Budget Energie'!N20 -> 0 | S20: =+N20-R20 -> 0
A21: Total consommation Energie | B21: =SUM(B19:B20) -> 0 | C21: =SUM(C19:C20) -> 0 | D21: =SUM(D19:D20) -> 0 | E21: =SUM(E19:E20) -> 0 | F21: =SUM(F19:F20) -> 0 | G21: =SUM(G19:G20) -> 0 | H21: =SUM(H19:H20) -> 0 | I21: =SUM(I19:I20) -> 0 | ... M21: =SUM(M19:M20) -> 0 | N21: =SUM(B21:M21) -> 0 | O21: =+O20+O19 -> 112365.06 | P21: =+N21-O21 -> -112365.06 | Q21: =+P21/O21 -> -1 | R21: =+'Budget Energie'!N7 -> 0 | S21: =+N21-R21 -> 0
A22: Prestations & analyses | B22: =+'Budget Ent & Analyses'!B14+'Budget Commun'!B19+'Budget Ent & Analyses'!B22 -> 0 | C22: =+'Budget Ent & Analyses'!C14+'Budget Commun'!C19+'Budget Ent & Analyses'!C22 -> 61400 | D22: =+'Budget Ent & Analyses'!D14+'Budget Commun'!D19+'Budget Ent & Analyses'!D22 -> 0 | E22: =+'Budget Ent & Analyses'!E14+'Budget Commun'!E19+'Budget Ent & Analyses'!E22 -> 0 | F22: =+'Budget Ent & Analyses'!F14+'Budget Commun'!F19+'Budget Ent & Analyses'!F22 -> 0 | G22: =+'Budget Ent & Analyses'!G14+'Budget Commun'!G19+'Budget Ent & Analyses'!G22 -> 0 | H22: =+'Budget Ent & Analyses'!H14+'Budget Commun'!H19+'Budget Ent & Analyses'!H22 -> 0 | I22: =+'Budget Ent & Analyses'!I14+'Budget Commun'!I19+'Budget Ent & Analyses'!I22 -> 0 | ... M22: =+'Budget Ent & Analyses'!M14+'Budget Commun'!M19+'Budget Ent & Analyses'!M22 -> 0 | N22: =SUM(B22:M22) -> 61400 | O22: 43594.909 | P22: =+N22-O22 -> 17805.091 | Q22: =+P22/O22 -> 0.40842133 | R22: =+'Budget Ent & Analyses'!N14+'Budget Commun'!N19+'Budget Ent & Analyses'!N22 -> 61400 | S22: =+N22-R22 -> 0
A23: Loyers fermes | B23: =+'Budget Loyers Fermes'!B7 -> 37622.549 | C23: =+'Budget Loyers Fermes'!C7 -> 37622.549 | D23: =+'Budget Loyers Fermes'!D7 -> 37622.549 | E23: =+'Budget Loyers Fermes'!E7 -> 37622.549 | F23: =+'Budget Loyers Fermes'!F7 -> 37622.549 | G23: =+'Budget Loyers Fermes'!G7 -> 37622.549 | H23: =+'Budget Loyers Fermes'!H7 -> 37622.549 | I23: =+'Budget Loyers Fermes'!I7 -> 37622.549 | ... M23: =+'Budget Loyers Fermes'!M7 -> 37622.549 | N23: =SUM(B23:M23) -> 451470.59 | O23: 191666.67 | P23: =+N23-O23 -> 259803.92 | Q23: =+P23/O23 -> 1.3554987 | R23: =+'Budget Loyers Fermes'!N7 -> 451470.59 | S23: =+N23-R23 -> 0
A24: Entretien | B24: =+'Budget Ent & Analyses'!B7-'Budget Ent & Analyses'!B14-'Budget Ent & Analyses'!B22+'Budget Commun'!B27 -> 10295.303 | C24: =+'Budget Ent & Analyses'!C7-'Budget Ent & Analyses'!C14-'Budget Ent & Analyses'!C22+'Budget Commun'!C27 -> 14132.803 | D24: =+'Budget Ent & Analyses'!D7-'Budget Ent & Analyses'!D14-'Budget Ent & Analyses'!D22+'Budget Commun'!D27 -> 14132.803 | E24: =+'Budget Ent & Analyses'!E7-'Budget Ent & Analyses'!E14-'Budget Ent & Analyses'!E22+'Budget Commun'!E27 -> 10295.303 | F24: =+'Budget Ent & Analyses'!F7-'Budget Ent & Analyses'!F14-'Budget Ent & Analyses'!F22+'Budget Commun'!F27 -> 10295.303 | G24: =+'Budget Ent & Analyses'!G7-'Budget Ent & Analyses'!G14-'Budget Ent & Analyses'!G22+'Budget Commun'!G27 -> 14132.803 | H24: =+'Budget Ent & Analyses'!H7-'Budget Ent & Analyses'!H14-'Budget Ent & Analyses'!H22+'Budget Commun'!H27 -> 14132.803 | I24: =+'Budget Ent & Analyses'!I7-'Budget Ent & Analyses'!I14-'Budget Ent & Analyses'!I22+'Budget Commun'!I27 -> 10295.303 | ... M24: =+'Budget Ent & Analyses'!M7-'Budget Ent & Analyses'!M14-'Budget Ent & Analyses'!M22+'Budget Commun'!M27 -> 1257.8035 | N24: =SUM(B24:M24) -> 125618.64 | O24: 105442.18 | P24: =+N24-O24 -> 20176.466 | Q24: =+P24/O24 -> 0.19135101 | R24: ='Budget Ent & Analyses'!N7-'Budget Ent & Analyses'!N14-'Budget Ent & Analyses'!N22+'Budget Commun'!N27 -> 125618.64 | S24: =+N24-R24 -> 0
A25: Main d'œuvre Directe | B25: =+'Budget MOD'!B7 -> 354391.69 | C25: =+'Budget MOD'!C7 -> 309277.47 | D25: =+'Budget MOD'!D7 -> 277874.46 | E25: =+'Budget MOD'!E7 -> 277413.75 | F25: =+'Budget MOD'!F7 -> 271051.42 | G25: =+'Budget MOD'!G7 -> 261194.88 | H25: =+'Budget MOD'!H7 -> 259638.92 | I25: =+'Budget MOD'!I7 -> 259783.08 | ... M25: =+'Budget MOD'!M7 -> 6140 | N25: =SUM(B25:M25) -> 2548032.9 | O25: 1390695.8 | P25: =+N25-O25 -> 1157337.1 | Q25: =+P25/O25 -> 0.83220007 | R25: =+'Budget MOD'!N7 -> 2548032.9 | S25: =+N25-R25 -> 0
A26: Main d'œuvre Adm. | B26: =+'Budget Commun'!B54 -> 30399.538 | C26: =+'Budget Commun'!C54 -> 30399.538 | D26: =+'Budget Commun'!D54 -> 30399.538 | E26: =+'Budget Commun'!E54 -> 30399.538 | F26: =+'Budget Commun'!F54 -> 30399.538 | G26: =+'Budget Commun'!G54 -> 30399.538 | H26: =+'Budget Commun'!H54 -> 30399.538 | I26: =+'Budget Commun'!I54 -> 30399.538 | ... M26: =+'Budget Commun'!M54 -> 30399.538 | N26: =SUM(B26:M26) -> 364794.45 | O26: 319900.43 | P26: =+N26-O26 -> 44894.019 | Q26: =+P26/O26 -> 0.14033748 | R26: =+'Budget Commun'!N54 -> 364794.45 | S26: =+N26-R26 -> 0
A27: Refact. HIJOS DE FEDERICO LIS | B27: =+'Budget Commun'!B47 -> 0 | C27: =+'Budget Commun'!C47 -> 0 | D27: =+'Budget Commun'!D47 -> 0 | E27: =+'Budget Commun'!E47 -> 0 | F27: =+'Budget Commun'!F47 -> 0 | G27: =+'Budget Commun'!G47 -> 0 | H27: =+'Budget Commun'!H47 -> 0 | I27: =+'Budget Commun'!I47 -> 0 | ... M27: =+'Budget Commun'!M47 -> 0 | N27: =SUM(B27:M27) -> 0 | O27: 156940.07 | P27: =+N27-O27 -> -156940.07 | Q27: =+P27/O27 -> -1 | R27: =+'Budget Commun'!N47 -> 0 | S27: =+N27-R27 -> 0
A28: Transport | B28: =+'Budget Transp Ventes'!B7 -> 0 | C28: =+'Budget Transp Ventes'!C7 -> 0 | D28: =+'Budget Transp Ventes'!D7 -> 0 | E28: =+'Budget Transp Ventes'!E7 -> 0 | F28: =+'Budget Transp Ventes'!F7 -> 23025000 | G28: =+'Budget Transp Ventes'!G7 -> 17268750 | H28: =+'Budget Transp Ventes'!H7 -> 17268750 | I28: =+'Budget Transp Ventes'!I7 -> 23025000 | ... M28: =+'Budget Transp Ventes'!M7 -> 5756250 | N28: =SUM(B28:M28) -> 1.3239375e+08 | O28: 70540.186 | P28: =+N28-O28 -> 1.3232321e+08 | Q28: =+P28/O28 -> 1875.8557 | R28: =+'Budget Transp Ventes'!N7 -> 1.3239375e+08 | S28: =+N28-R28 -> 0
A29: Autres frais généraux | B29: =+'Budget Commun'!B43+'Budget Commun'!B34 -> 74741.04 | C29: =+'Budget Commun'!C43+'Budget Commun'!C34 -> 3753.7572 | D29: =+'Budget Commun'!D43+'Budget Commun'!D34 -> 3753.7572 | E29: =+'Budget Commun'!E43+'Budget Commun'!E34 -> 3753.7572 | F29: =+'Budget Commun'!F43+'Budget Commun'!F34 -> 3753.7572 | G29: =+'Budget Commun'!G43+'Budget Commun'!G34 -> 3753.7572 | H29: =+'Budget Commun'!H43+'Budget Commun'!H34 -> 5404.6243 | I29: =+'Budget Commun'!I43+'Budget Commun'!I34 -> 3753.7572 | ... M29: =+'Budget Commun'!M43+'Budget Commun'!M34 -> 3753.7572 | N29: =SUM(B29:M29) -> 123579.19 | O29: 79354.347 | P29: =+N29-O29 -> 44224.844 | Q29: =+P29/O29 -> 0.5573084 | R29: =+'Budget Commun'!N34+'Budget Commun'!N43 -> 123579.19 | S29: =+N29-R29 -> 0
A30: Coût de revient total | B30: =SUM(B22:B29)+B21+B18 -> 986984.12 | C30: =SUM(C22:C29)+C21+C18 -> 3079536.1 | D30: =SUM(D22:D29)+D21+D18 -> 379133.11 | E30: =SUM(E22:E29)+E21+E18 -> 374834.89 | F30: =SUM(F22:F29)+F21+F18 -> 23393473 | G30: =SUM(G22:G29)+G21+G18 -> 17631204 | H30: =SUM(H22:H29)+H21+H18 -> 17631298 | I30: =SUM(I22:I29)+I21+I18 -> 23382204 | ... M30: =SUM(M22:M29)+M21+M18 -> 5850773.6 | N30: =SUM(B30:M30) -> 1.3932463e+08 | O30: =SUM(O22:O29)+O21+O18 -> 4229162 | P30: =+N30-O30 -> 1.3509547e+08 | Q30: =+P30/O30 -> 31.943791
A31: EBITDA | B31: =B11-B30 -> #DIV/0! | C31: =C11-C30 -> #DIV/0! | D31: =D11-D30 -> #DIV/0! | E31: =E11-E30 -> #DIV/0! | F31: =F11-F30 -> #DIV/0! | G31: =G11-G30 -> #DIV/0! | H31: =H11-H30 -> #DIV/0! | I31: =I11-I30 -> #DIV/0! | ... O31: =O11-O30 -> -666635.78 | P31: =+N31-O31 -> #DIV/0! | Q31: =+P31/O31 -> #DIV/0!
A32: Amortissements | B32: =+'Budget Commun'!B14+'Budget Invest& Amort'!B9 -> 84231.686 | C32: =+'Budget Commun'!C14+'Budget Invest& Amort'!C9 -> 84231.686 | D32: =+'Budget Commun'!D14+'Budget Invest& Amort'!D9 -> 84231.686 | E32: =+'Budget Commun'!E14+'Budget Invest& Amort'!E9 -> 84231.686 | F32: =+'Budget Commun'!F14+'Budget Invest& Amort'!F9 -> 84231.686 | G32: =+'Budget Commun'!G14+'Budget Invest& Amort'!G9 -> 84231.686 | H32: =+'Budget Commun'!H14+'Budget Invest& Amort'!H9 -> 84231.686 | I32: =+'Budget Commun'!I14+'Budget Invest& Amort'!I9 -> 84231.686 | ... M32: =+'Budget Commun'!M14+'Budget Invest& Amort'!M9 -> 87247.519 | N32: =SUM(B32:M32) -> 1019827.7 | O32: 823053.01 | P32: =+N32-O32 -> 196774.71 | Q32: =+P32/O32 -> 0.23907903 | R32: =+'Budget Commun'!N14+'Budget Invest& Amort'!N9 -> 1019827.7 | S32: =+N32-R32 -> 0
A33: Résultat d'exploitation | B33: =B31-B32 -> #DIV/0! | C33: =C31-C32 -> #DIV/0! | D33: =D31-D32 -> #DIV/0! | E33: =E31-E32 -> #DIV/0! | F33: =F31-F32 -> #DIV/0! | G33: =G31-G32 -> #DIV/0! | H33: =H31-H32 -> #DIV/0! | I33: =I31-I32 -> #DIV/0! | ... O33: =O31-O32 -> -1489688.8 | P33: =+N33-O33 -> #DIV/0! | Q33: =+P33/O33 -> #DIV/0!
A34: EBITDA en % du CA | N34: =+N31/N7 -> #DIV/0! | O34: =+O31/O7 -> -0.26256939 | P34: =+N34-O34 -> #DIV/0!
A35: PMV au kg | B35: =+(B7)/B5 -> #DIV/0! | C35: =+(C7)/C5 -> #DIV/0! | D35: =+(D7)/D5 -> #DIV/0! | E35: =+(E7)/E5 -> 0 | F35: =+(F7)/F5 -> 9.0909091 | G35: =+(G7)/G5 -> 9.0909091 | H35: =+(H7)/H5 -> 9.0909091 | I35: =+(I7)/I5 -> 9.0909091 | ... O35: =+(O7)/O5 -> 2.2908751 | P35: =+N35-O35 -> 6.6585412 | Q35: =+P35/O35 -> 2.9065492
A36: CA à l'hectare prod | B36: =+B7/B4 -> 0 | C36: =+C7/C4 -> 0 | D36: =+D7/D4 -> 0 | E36: =+E7/E4 -> 0 | F36: =+F7/F4 -> 200000 | G36: =+G7/G4 -> 150000 | H36: =+H7/H4 -> 150000 | I36: =+I7/I4 -> 200000 | ... O36: =+O7/O4 -> 373366.72 | P36: =+N36-O36 -> 776633.28 | Q36: =+P36/O36 -> 2.0800817
A37: Coût à l'hectare prod (hors Amort) | B37: =+(B30-B10)/B4 -> #DIV/0! | C37: =+(C30-C10)/C4 -> #DIV/0! | D37: =+(D30-D10)/D4 -> #DIV/0! | E37: =+(E30-E10)/E4 -> #DIV/0! | F37: =+(F30-F10)/F4 -> #DIV/0! | G37: =+(G30-G10)/G4 -> #DIV/0! | H37: =+(H30-H10)/H4 -> #DIV/0! | I37: =+(I30-I10)/I4 -> #DIV/0! | ... O37: =+(O30-O10)/O4 -> 621935.58 | P37: =+N37-O37 -> #DIV/0! | Q37: =+P37/O37 -> #DIV/0!
A38: EBITDA à l'hectare prod | B38: =+B31/B4 -> #DIV/0! | C38: =+C31/C4 -> #DIV/0! | D38: =+D31/D4 -> #DIV/0! | E38: =+E31/E4 -> #DIV/0! | F38: =+F31/F4 -> #DIV/0! | G38: =+G31/G4 -> #DIV/0! | H38: =+H31/H4 -> #DIV/0! | I38: =+I31/I4 -> #DIV/0! | ... O38: =+O31/O4 -> -98034.674 | P38: =+N38-O38 -> #DIV/0! | Q38: =+P38/O38 -> #DIV/0!
A39: Coût total à l'hectare prod | B39: =+(B30+B32-B10)/B4 -> #DIV/0! | C39: =+(C30+C32-C10)/C4 -> #DIV/0! | D39: =+(D30+D32-D10)/D4 -> #DIV/0! | E39: =+(E30+E32-E10)/E4 -> #DIV/0! | F39: =+(F30+F32-F10)/F4 -> #DIV/0! | G39: =+(G30+G32-G10)/G4 -> #DIV/0! | H39: =+(H30+H32-H10)/H4 -> #DIV/0! | I39: =+(I30+I32-I10)/I4 -> #DIV/0! | ... O39: =+(O30+O32-O10)/O4 -> 742972.79 | P39: =+N39-O39 -> #DIV/0! | Q39: =+P39/O39 -> #DIV/0!
A40: REX à l'hectare prod | B40: =B33/B4 -> #DIV/0! | C40: =C33/C4 -> #DIV/0! | D40: =D33/D4 -> #DIV/0! | E40: =E33/E4 -> #DIV/0! | F40: =F33/F4 -> #DIV/0! | G40: =G33/G4 -> #DIV/0! | H40: =H33/H4 -> #DIV/0! | I40: =I33/I4 -> #DIV/0! | ... O40: =O33/O4 -> -219071.88 | P40: =+N40-O40 -> #DIV/0! | Q40: =+P40/O40 -> #DIV/0!
A41: Détail des coûts à l'hectare
A42: Coût total à l'hectare | B42: =+(B30+B32)/B3 -> #DIV/0! | C42: =+(C30+C32)/C3 -> #DIV/0! | D42: =+(D30+D32)/D3 -> #DIV/0! | E42: =+(E30+E32)/E3 -> #DIV/0! | F42: =+(F30+F32)/F3 -> #DIV/0! | G42: =+(G30+G32)/G3 -> #DIV/0! | H42: =+(H30+H32)/H3 -> #DIV/0! | I42: =+(I30+I32)/I3 -> #DIV/0! | ... M42: =+(M30+M32)/M3 -> #DIV/0! | N42: =+(N30+N32-N10)/N3 -> #DIV/0! | O42: =+(O30+O32-O10)/O3 -> 742972.79 | P42: =+N42-O42 -> #DIV/0! | Q42: =+P42/O42 -> #DIV/0!
A43: Coût à l'hectare (hors Amort) | B43: =+B30/B3 -> #DIV/0! | C43: =+C30/C3 -> #DIV/0! | D43: =+D30/D3 -> #DIV/0! | E43: =+E30/E3 -> #DIV/0! | F43: =+F30/F3 -> #DIV/0! | G43: =+G30/G3 -> #DIV/0! | H43: =+H30/H3 -> #DIV/0! | I43: =+I30/I3 -> #DIV/0! | ... M43: =+M30/M3 -> #DIV/0! | N43: =+(N30-N10)/N3 -> #DIV/0! | O43: =+(O30-O10)/O3 -> 621935.58 | P43: =+N43-O43 -> #DIV/0! | Q43: =+P43/O43 -> #DIV/0!
A44: Semences | B44: =+B12/B3 -> #DIV/0! | C44: =+C12/C3 -> #DIV/0! | D44: =+D12/D3 -> #DIV/0! | E44: =+E12/E3 -> #DIV/0! | F44: =+F12/F3 -> #DIV/0! | G44: =+G12/G3 -> #DIV/0! | H44: =+H12/H3 -> #DIV/0! | I44: =+I12/I3 -> #DIV/0! | ... O44: =+O12/O3 -> 29764.706 | P44: =+N44-O44 -> #DIV/0! | Q44: =+P44/O44 -> #DIV/0!
A45: Engrais | B45: =+B13/B3 -> #DIV/0! | C45: =+C13/C3 -> #DIV/0! | D45: =+D13/D3 -> #DIV/0! | E45: =+E13/E3 -> #DIV/0! | F45: =+F13/F3 -> #DIV/0! | G45: =+G13/G3 -> #DIV/0! | H45: =+H13/H3 -> #DIV/0! | I45: =+I13/I3 -> #DIV/0! | ... O45: =+O13/O3 -> 79047.086 | P45: =+N45-O45 -> #DIV/0! | Q45: =+P45/O45 -> #DIV/0!
A46: Plants | B46: =+B14/B3 -> #DIV/0! | C46: =+C14/C3 -> #DIV/0! | D46: =+D14/D3 -> #DIV/0! | E46: =+E14/E3 -> #DIV/0! | F46: =+F14/F3 -> #DIV/0! | G46: =+G14/G3 -> #DIV/0! | H46: =+H14/H3 -> #DIV/0! | I46: =+I14/I3 -> #DIV/0! | ... O46: =+O14/O3 -> 37483.382 | P46: =+N46-O46 -> #DIV/0! | Q46: =+P46/O46 -> #DIV/0!
A47: Phytos | B47: =+B15/B3 -> #DIV/0! | C47: =+C15/C3 -> #DIV/0! | D47: =+D15/D3 -> #DIV/0! | E47: =+E15/E3 -> #DIV/0! | F47: =+F15/F3 -> #DIV/0! | G47: =+G15/G3 -> #DIV/0! | H47: =+H15/H3 -> #DIV/0! | I47: =+I15/I3 -> #DIV/0! | ... O47: =+O15/O3 -> 85686.503 | P47: =+N47-O47 -> #DIV/0! | Q47: =+P47/O47 -> #DIV/0!
A48: Insectes | B48: =+B16/B3 -> #DIV/0! | C48: =+C16/C3 -> #DIV/0! | D48: =+D16/D3 -> #DIV/0! | E48: =+E16/E3 -> #DIV/0! | F48: =+F16/F3 -> #DIV/0! | G48: =+G16/G3 -> #DIV/0! | H48: =+H16/H3 -> #DIV/0! | I48: =+I16/I3 -> #DIV/0! | ... O48: =+O16/O3 -> 15828.683 | P48: =+N48-O48 -> #DIV/0! | Q48: =+P48/O48 -> #DIV/0!
A49: Autres fournitures agricoles | B49: =+B17/B3 -> #DIV/0! | C49: =+C17/C3 -> #DIV/0! | D49: =+D17/D3 -> #DIV/0! | E49: =+E17/E3 -> #DIV/0! | F49: =+F17/F3 -> #DIV/0! | G49: =+G17/G3 -> #DIV/0! | H49: =+H17/H3 -> #DIV/0! | I49: =+I17/I3 -> #DIV/0! | ... O49: =+O17/O3 -> 10816.456 | P49: =+N49-O49 -> #DIV/0! | Q49: =+P49/O49 -> #DIV/0!
A50: Electricité | B50: =+B19/B3 -> #DIV/0! | C50: =+C19/C3 -> #DIV/0! | D50: =+D19/D3 -> #DIV/0! | E50: =+E19/E3 -> #DIV/0! | F50: =+F19/F3 -> #DIV/0! | G50: =+G19/G3 -> #DIV/0! | H50: =+H19/H3 -> #DIV/0! | I50: =+I19/I3 -> #DIV/0! | ... O50: =+O19/O3 -> 13489.326 | P50: =+N50-O50 -> #DIV/0! | Q50: =+P50/O50 -> #DIV/0!
A51: Eau | B51: =+B20/B3 -> #DIV/0! | C51: =+C20/C3 -> #DIV/0! | D51: =+D20/D3 -> #DIV/0! | E51: =+E20/E3 -> #DIV/0! | F51: =+F20/F3 -> #DIV/0! | G51: =+G20/G3 -> #DIV/0! | H51: =+H20/H3 -> #DIV/0! | I51: =+I20/I3 -> #DIV/0! | ... O51: =+O20/O3 -> 3034.9473 | P51: =+N51-O51 -> #DIV/0! | Q51: =+P51/O51 -> #DIV/0!
A52: Prestations & analyses | B52: =+B22/B3 -> #DIV/0! | C52: =+C22/C3 -> #DIV/0! | D52: =+D22/D3 -> #DIV/0! | E52: =+E22/E3 -> #DIV/0! | F52: =+F22/F3 -> #DIV/0! | G52: =+G22/G3 -> #DIV/0! | H52: =+H22/H3 -> #DIV/0! | I52: =+I22/I3 -> #DIV/0! | ... O52: =+O22/O3 -> 6411.0161 | P52: =+N52-O52 -> #DIV/0! | Q52: =+P52/O52 -> #DIV/0!
A53: Loyers fermes | B53: =+B23/B3 -> #DIV/0! | C53: =+C23/C3 -> #DIV/0! | D53: =+D23/D3 -> #DIV/0! | E53: =+E23/E3 -> #DIV/0! | F53: =+F23/F3 -> #DIV/0! | G53: =+G23/G3 -> #DIV/0! | H53: =+H23/H3 -> #DIV/0! | I53: =+I23/I3 -> #DIV/0! | ... O53: =+O23/O3 -> 28186.275 | P53: =+N53-O53 -> #DIV/0! | Q53: =+P53/O53 -> #DIV/0!
A54: Entretien | B54: =+B24/B3 -> #DIV/0! | C54: =+C24/C3 -> #DIV/0! | D54: =+D24/D3 -> #DIV/0! | E54: =+E24/E3 -> #DIV/0! | F54: =+F24/F3 -> #DIV/0! | G54: =+G24/G3 -> #DIV/0! | H54: =+H24/H3 -> #DIV/0! | I54: =+I24/I3 -> #DIV/0! | ... O54: =+O24/O3 -> 15506.202 | P54: =+N54-O54 -> #DIV/0! | Q54: =+P54/O54 -> #DIV/0!
A55: Main d'œuvre Directe | B55: =+B25/B3 -> #DIV/0! | C55: =+C25/C3 -> #DIV/0! | D55: =+D25/D3 -> #DIV/0! | E55: =+E25/E3 -> #DIV/0! | F55: =+F25/F3 -> #DIV/0! | G55: =+G25/G3 -> #DIV/0! | H55: =+H25/H3 -> #DIV/0! | I55: =+I25/I3 -> #DIV/0! | ... O55: =+O25/O3 -> 204514.08 | P55: =+N55-O55 -> #DIV/0! | Q55: =+P55/O55 -> #DIV/0!
A56: Main d'œuvre Adm. | B56: =+B26/B3 -> #DIV/0! | C56: =+C26/C3 -> #DIV/0! | D56: =+D26/D3 -> #DIV/0! | E56: =+E26/E3 -> #DIV/0! | F56: =+F26/F3 -> #DIV/0! | G56: =+G26/G3 -> #DIV/0! | H56: =+H26/H3 -> #DIV/0! | I56: =+I26/I3 -> #DIV/0! | ... O56: =+O26/O3 -> 47044.181 | P56: =+N56-O56 -> #DIV/0! | Q56: =+P56/O56 -> #DIV/0!
A57: Refact. HIJOS DE FEDERICO LIS | B57: =+B27/B3 -> #DIV/0! | C57: =+C27/C3 -> #DIV/0! | D57: =+D27/D3 -> #DIV/0! | E57: =+E27/E3 -> #DIV/0! | F57: =+F27/F3 -> #DIV/0! | G57: =+G27/G3 -> #DIV/0! | H57: =+H27/H3 -> #DIV/0! | I57: =+I27/I3 -> #DIV/0! | ... O57: =+O27/O3 -> 23079.422 | P57: =+N57-O57 -> #DIV/0! | Q57: =+P57/O57 -> #DIV/0!
A58: Transport | B58: =+B28/B3 -> #DIV/0! | C58: =+C28/C3 -> #DIV/0! | D58: =+D28/D3 -> #DIV/0! | E58: =+E28/E3 -> #DIV/0! | F58: =+F28/F3 -> #DIV/0! | G58: =+G28/G3 -> #DIV/0! | H58: =+H28/H3 -> #DIV/0! | I58: =+I28/I3 -> #DIV/0! | ... O58: =+O28/O3 -> 10373.557 | P58: =+N58-O58 -> #DIV/0! | Q58: =+P58/O58 -> #DIV/0!
A59: Autres frais généraux | B59: =+B29/B3 -> #DIV/0! | C59: =+C29/C3 -> #DIV/0! | D59: =+D29/D3 -> #DIV/0! | E59: =+E29/E3 -> #DIV/0! | F59: =+F29/F3 -> #DIV/0! | G59: =+G29/G3 -> #DIV/0! | H59: =+H29/H3 -> #DIV/0! | I59: =+I29/I3 -> #DIV/0! | ... O59: =+O29/O3 -> 11669.757 | P59: =+N59-O59 -> #DIV/0! | Q59: =+P59/O59 -> #DIV/0!
A60: Amortissements | B60: =+B32/B3 -> #DIV/0! | C60: =+C32/C3 -> #DIV/0! | D60: =+D32/D3 -> #DIV/0! | E60: =+E32/E3 -> #DIV/0! | F60: =+F32/F3 -> #DIV/0! | G60: =+G32/G3 -> #DIV/0! | H60: =+H32/H3 -> #DIV/0! | I60: =+I32/I3 -> #DIV/0! | ... O60: =+O32/O3 -> 121037.21 | P60: =+N60-O60 -> #DIV/0! | Q60: =+P60/O60 -> #DIV/0!
A61: Calcul des encours
A62: Encours initial | D62: =SUM(B68:D84) -> #DIV/0!
A63: Coût des encours | D63: =+D62/('Budget Volumes Export'!N16) -> #DIV/0! | E63: =+D63 -> #DIV/0! | F63: =+E63 -> #DIV/0! | G63: =+F63 -> #DIV/0! | H63: =+G63 -> #DIV/0! | I63: =+H63 -> #DIV/0! | J63: =+I63 -> #DIV/0! | K63: =+J63 -> #DIV/0! | L63: =+K63 -> #DIV/0! | M63: =+L63 -> #DIV/0!
A64: Coût des ventes | E64: =+E63*'Budget Volumes Export'!E16 -> #DIV/0! | F64: =+F63*'Budget Volumes Export'!F16 -> #DIV/0! | G64: =+G63*'Budget Volumes Export'!G16 -> #DIV/0! | H64: =+H63*'Budget Volumes Export'!H16 -> #DIV/0! | I64: =+I63*'Budget Volumes Export'!I16 -> #DIV/0! | J64: =+J63*'Budget Volumes Export'!J16 -> #DIV/0! | K64: =+K63*'Budget Volumes Export'!K16 -> #DIV/0! | L64: =+L63*'Budget Volumes Export'!L16 -> #DIV/0! | M64: =+M63*'Budget Volumes Export'!M16 -> #DIV/0!
A65: Encours fin de période | E65: =+D62-E64 -> #DIV/0! | F65: =+E65-F64 -> #DIV/0! | G65: =+F65-G64 -> #DIV/0! | H65: =+G65-H64 -> #DIV/0! | I65: =+H65-I64 -> #DIV/0! | J65: =+I65-J64 -> #DIV/0! | K65: =+J65-K64 -> #DIV/0! | L65: =+K65-L64 -> #DIV/0! | M65: =+L65-M64 -> #DIV/0!
A66: Variation encours | E66: =+E65-D62 -> #DIV/0! | F66: =+F65-E65 -> #DIV/0! | G66: =+G65-F65 -> #DIV/0! | H66: =+H65-G65 -> #DIV/0! | I66: =+I65-H65 -> #DIV/0! | J66: =+J65-I65 -> #DIV/0! | K66: =+K65-J65 -> #DIV/0! | L66: =+L65-K65 -> #DIV/0! | M66: =+M65-L65 -> #DIV/0!
A67: Calcul encours initial culture hiver
A68: Semences | B68: =B12 -> 0 | C68: =C12 -> 1494600 | D68: =D12 -> 0
A69: Plants | B69: =B14 -> 0 | C69: =C14 -> 1113000 | D69: =D14 -> 0
A70: Fournitures agricoles | B70: =B17 -> 479534 | C70: =C17 -> 15350 | D70: =D17 -> 15350
A71: Engrais | B71: =B13*('Plan de culture 104 '!$X$13/'Plan de culture 104 '!$B$3) -> #DIV/0! | C71: =C13*('Plan de culture 104 '!$X$13/'Plan de culture 104 '!$B$3) -> #DIV/0! | D71: =D13*('Plan de culture 104 '!$X$13/'Plan de culture 104 '!$B$3) -> #DIV/0!
A72: Phytos | B72: =B15*('Plan de culture 104 '!$X$13/'Plan de culture 104 '!$B$3) -> #DIV/0! | C72: =C15*('Plan de culture 104 '!$X$13/'Plan de culture 104 '!$B$3) -> #DIV/0! | D72: =D15*('Plan de culture 104 '!$X$13/'Plan de culture 104 '!$B$3) -> #DIV/0!
A73: Insectes | B73: =B16*('Plan de culture 104 '!$X$13/'Plan de culture 104 '!$B$3) -> #DIV/0! | C73: =C16*('Plan de culture 104 '!$X$13/'Plan de culture 104 '!$B$3) -> #DIV/0! | D73: =D16*('Plan de culture 104 '!$X$13/'Plan de culture 104 '!$B$3) -> #DIV/0!
A74: Energie | B74: =B21*('Plan de culture 104 '!$X$13/'Plan de culture 104 '!$B$3) -> #DIV/0! | C74: =C21*('Plan de culture 104 '!$X$13/'Plan de culture 104 '!$B$3) -> #DIV/0! | D74: =D21*('Plan de culture 104 '!$X$13/'Plan de culture 104 '!$B$3) -> #DIV/0!
A75: Prestations & analyses | B75: =B22*('Plan de culture 104 '!$X$13/'Plan de culture 104 '!$B$3) -> #DIV/0! | C75: =C22*('Plan de culture 104 '!$X$13/'Plan de culture 104 '!$B$3) -> #DIV/0! | D75: =D22*('Plan de culture 104 '!$X$13/'Plan de culture 104 '!$B$3) -> #DIV/0!
A76: Loyers fermes | B76: =B23*('Plan de culture 104 '!$X$13/'Plan de culture 104 '!$B$3) -> #DIV/0! | C76: =C23*('Plan de culture 104 '!$X$13/'Plan de culture 104 '!$B$3) -> #DIV/0! | D76: =D23*('Plan de culture 104 '!$X$13/'Plan de culture 104 '!$B$3) -> #DIV/0!
A77: Entretien | B77: =B24*('Plan de culture 104 '!$X$13/'Plan de culture 104 '!$B$3) -> #DIV/0! | C77: =C24*('Plan de culture 104 '!$X$13/'Plan de culture 104 '!$B$3) -> #DIV/0! | D77: =D24*('Plan de culture 104 '!$X$13/'Plan de culture 104 '!$B$3) -> #DIV/0!
A78: Main d'œuvre Directe | B78: =B25*('Plan de culture 104 '!$X$13/'Plan de culture 104 '!$B$3) -> #DIV/0! | C78: =C25*('Plan de culture 104 '!$X$13/'Plan de culture 104 '!$B$3) -> #DIV/0! | D78: =D25*('Plan de culture 104 '!$X$13/'Plan de culture 104 '!$B$3) -> #DIV/0!
A79: Main d'œuvre Adm. | B79: =B26*('Plan de culture 104 '!$X$13/'Plan de culture 104 '!$B$3) -> #DIV/0! | C79: =C26*('Plan de culture 104 '!$X$13/'Plan de culture 104 '!$B$3) -> #DIV/0! | D79: =D26*('Plan de culture 104 '!$X$13/'Plan de culture 104 '!$B$3) -> #DIV/0!
A80: Refact. HIJOS DE FEDERICO LIS | B80: =B27*('Plan de culture 104 '!$X$13/'Plan de culture 104 '!$B$3) -> #DIV/0! | C80: =C27*('Plan de culture 104 '!$X$13/'Plan de culture 104 '!$B$3) -> #DIV/0! | D80: =D27*('Plan de culture 104 '!$X$13/'Plan de culture 104 '!$B$3) -> #DIV/0!
A81: Autres frais généraux | B81: =B29*('Plan de culture 104 '!$X$13/'Plan de culture 104 '!$B$3) -> #DIV/0! | C81: =C29*('Plan de culture 104 '!$X$13/'Plan de culture 104 '!$B$3) -> #DIV/0! | D81: =D29*('Plan de culture 104 '!$X$13/'Plan de culture 104 '!$B$3) -> #DIV/0!
A82: Amortissements | B82: =B32*('Plan de culture 104 '!$X$13/'Plan de culture 104 '!$B$3) -> #DIV/0! | C82: =C32*('Plan de culture 104 '!$X$13/'Plan de culture 104 '!$B$3) -> #DIV/0! | D82: =D32*('Plan de culture 104 '!$X$13/'Plan de culture 104 '!$B$3) -> #DIV/0!

Sheet 105_Synthèse
B1: BUD | C1: BUD | D1: BUD | E1: BUD | F1: BUD | G1: BUD | H1: BUD | I1: BUD | J1: BUD | K1: BUD | L1: BUD | M1: BUD | N1: BUD | O1: REEL | P1: VARIATION | Q1: VARIATION
A2: 105 - Analyse totale (MAD) | B2: 45839 | C2: =+B2+31 -> 45870 | D2: =+C2+31 -> 45901 | E2: =+D2+31 -> 45932 | F2: =+E2+31 -> 45963 | G2: =+F2+31 -> 45994 | H2: =+G2+31 -> 46025 | I2: =+H2+31 -> 46056 | J2: =+I2+31 -> 46087 | ... M2: =+L2+31 -> 46180 | N2: 25/26 | O2: 25/26 | P2: BUD-REEL | Q2: % | R2: source | S2: check
A3: Sup Tot (ha) | B3: =+'Plan de culture 105'!$B$3 -> 0 | C3: =+'Plan de culture 105'!$B$3 -> 0 | D3: =+'Plan de culture 105'!$B$3 -> 0 | E3: =+'Plan de culture 105'!$B$3 -> 0 | F3: =+'Plan de culture 105'!$B$3 -> 0 | G3: =+'Plan de culture 105'!$B$3 -> 0 | H3: =+'Plan de culture 105'!$B$3 -> 0 | I3: =+'Plan de culture 105'!$B$3 -> 0 | ... N3: =+'Plan de culture 105'!$B$3 -> 0 | O3: 7.9 | P3: =+N3-O3 -> -7.9 | Q3: =+P3/O3 -> -1 | R3: =+'Plan de culture 105'!B3 -> 0 | S3: =+N3-R3 -> 0
A4: Sup productive | B4: =+'Budget Volumes Export'!B29 -> 5.395 | C4: =+'Budget Volumes Export'!C29 -> 5.395 | D4: =+'Budget Volumes Export'!D29 -> 5.395 | E4: =+'Budget Volumes Export'!E29 -> 5.395 | F4: =+'Budget Volumes Export'!F29 -> 5.395 | G4: =+'Budget Volumes Export'!G29 -> 5.395 | H4: =+'Budget Volumes Export'!H29 -> 5.395 | I4: =+'Budget Volumes Export'!I29 -> 5.395 | ... N4: =+'Budget Volumes Export'!N29 -> 5.395 | O4: 7.9 | P4: =+N4-O4 -> -2.505 | Q4: =+P4/O4 -> -0.31708861 | R4: =+'Budget Volumes Export'!N32 -> 0 | S4: =+N4-R4 -> 5.395
A5: Vol (kg) | B5: =+'Budget Volumes Export'!B28 -> 0 | C5: =+'Budget Volumes Export'!C28 -> 0 | D5: =+'Budget Volumes Export'!D28 -> 0 | E5: =+'Budget Volumes Export'!E28 -> 107900 | F5: =+'Budget Volumes Export'!F28 -> 107900 | G5: =+'Budget Volumes Export'!G28 -> 80925 | H5: =+'Budget Volumes Export'!H28 -> 80925 | I5: =+'Budget Volumes Export'!I28 -> 107900 | ... M5: =+'Budget Volumes Export'!M28 -> 26975 | N5: =SUM(B5:M5) -> 728325 | O5: 744107.81 | P5: =+N5-O5 -> -15782.81 | Q5: =+P5/O5 -> -0.021210381 | R5: =+'Budget Volumes Export'!N28*1000 -> 728325000 | S5: =+N5-R5 -> -727596675
A6: rendement (t/ha) | B6: =+B5/B4/1000 -> 0 | C6: =+C5/C4/1000 -> 0 | D6: =+D5/D4/1000 -> 0 | E6: =+E5/E4/1000 -> 20 | F6: =+F5/F4/1000 -> 20 | G6: =+G5/G4/1000 -> 15 | H6: =+H5/H4/1000 -> 15 | I6: =+I5/I4/1000 -> 20 | ... O6: =+O5/O4/1000 -> 94.190862 | P6: =+N6-O6 -> 40.809138 | Q6: =+P6/O6 -> 0.43326005 | R6: =+'Budget Volumes Export'!N30 -> 135 | S6: =+N6-R6 -> 0
A7: CA EXPORT(MAD) | B7: =+'Budget Commercial Export'!B16 -> 0 | C7: =+'Budget Commercial Export'!C16 -> 0 | D7: =+'Budget Commercial Export'!D16 -> 0 | E7: =+'Budget Commercial Export'!E16 -> 0 | F7: =+'Budget Commercial Export'!F16 -> 0 | G7: =+'Budget Commercial Export'!G16 -> 0 | H7: =+'Budget Commercial Export'!H16 -> 0 | I7: =+'Budget Commercial Export'!I16 -> 0 | ... M7: =+'Budget Commercial Export'!M16 -> 0 | N7: =SUM(B7:M7) -> 0 | O7: 7792907.1 | P7: =+N7-O7 -> -7792907.1 | Q7: =+P7/O7 -> -1 | R7: =+'Budget Commercial Export'!N16 -> 0 | S7: =+N7-R7 -> 0
A8: CA MARCHE LOCAL | B8: =+'Budget Commercial ML'!B16 -> 0 | C8: =+'Budget Commercial ML'!C16 -> 0 | D8: =+'Budget Commercial ML'!D16 -> 0 | E8: =+'Budget Commercial ML'!E16 -> 0 | F8: =+'Budget Commercial ML'!F16 -> 0 | G8: =+'Budget Commercial ML'!G16 -> 0 | H8: =+'Budget Commercial ML'!H16 -> 0 | I8: =+'Budget Commercial ML'!I16 -> 0 | ... M8: =+'Budget Commercial ML'!M16 -> 0 | N8: =SUM(B8:M8) -> 0 | P8: =+N8-O8 -> 0 | Q8: =+P8/O8 -> #DIV/0!
A9: Autres revenus (MAD) | N9: =SUM(B9:M9) -> 0 | O9: 476521.56 | P9: =+N9-O9 -> -476521.56 | Q9: =+P9/O9 -> -1
A10: Production encours (MAD) | B10: =+B30+B32 -> #DIV/0! | C10: =+C30+C32 -> #DIV/0! | D10: =+D30+D32 -> #DIV/0! | E10: =+E66 -> #DIV/0! | F10: =+F66 -> #DIV/0! | G10: =+G66 -> #DIV/0! | H10: =+H66 -> #DIV/0! | I10: =+I66 -> #DIV/0! | J10: =+J66 -> #DIV/0! | K10: =+K66 -> #DIV/0! | L10: =+L66 -> #DIV/0! | M10: =+M66 -> #DIV/0! | N10: =SUM(B10:M10) -> #DIV/0! | O10: 0 | P10: =+N10-O10 -> #DIV/0! | Q10: =+P10/O10 -> #DIV/0! | R10: 0 | S10: =+N10-R10 -> #DIV/0!
A11: Production totale (MAD) | B11: =+B10+B7+B9 -> #DIV/0! | C11: =+C10+C7+C9 -> #DIV/0! | D11: =+D10+D7+D9 -> #DIV/0! | E11: =+E10+E7+E9 -> #DIV/0! | F11: =+F10+F7+F9 -> #DIV/0! | G11: =+G10+G7+G9 -> #DIV/0! | H11: =+H10+H7+H9 -> #DIV/0! | I11: =+I10+I7+I9 -> #DIV/0! | ... M11: =+M10+M7+M9 -> #DIV/0! | N11: =SUM(B11:M11) -> #DIV/0! | O11: =+O10+O7+O9 -> 8269428.6 | P11: =+N11-O11 -> #DIV/0! | Q11: =+P11/O11 -> #DIV/0! | U11: =+O11-O18-O21-O22-O27 -> 4250370.7
A12: Consommation Semences | B12: =+'Budget Semences'!B20 -> 0 | C12: =+'Budget Semences'!C20 -> 0 | D12: =+'Budget Semences'!D20 -> 0 | E12: =+'Budget Semences'!E20 -> 0 | F12: =+'Budget Semences'!F20 -> 0 | G12: =+'Budget Semences'!G20 -> 0 | H12: =+'Budget Semences'!H20 -> 0 | I12: =+'Budget Semences'!I20 -> 0 | ... M12: =+'Budget Semences'!M20 -> 0 | N12: =SUM(B12:M12) -> 0 | O12: 1236358.2 | P12: =+N12-O12 -> -1236358.2 | Q12: =+P12/O12 -> -1 | R12: =+'Budget Semences'!N20 -> 0 | S12: =+N12-R12 -> 0 | U12: 166967.16
A13: Consommation Engrais | B13: =+'Budget Engrais'!B16 -> 0 | C13: =+'Budget Engrais'!C16 -> 0 | D13: =+'Budget Engrais'!D16 -> 0 | E13: =+'Budget Engrais'!E16 -> 0 | F13: =+'Budget Engrais'!F16 -> 0 | G13: =+'Budget Engrais'!G16 -> 0 | H13: =+'Budget Engrais'!H16 -> 0 | I13: =+'Budget Engrais'!I16 -> 0 | ... M13: =+'Budget Engrais'!M16 -> 0 | N13: =SUM(B13:M13) -> 0 | O13: 1186252.2 | P13: =+N13-O13 -> -1186252.2 | Q13: =+P13/O13 -> -1 | R13: =+'Budget Engrais'!N16 -> 0 | S13: =+N13-R13 -> 0 | U13: =+U11-U12 -> 4083403.5
A14: Consommation Plants | B14: =+'Budget Plants'!B21 -> 0 | C14: =+'Budget Plants'!C21 -> 0 | D14: =+'Budget Plants'!D21 -> 0 | E14: =+'Budget Plants'!E21 -> 0 | F14: =+'Budget Plants'!F21 -> 0 | G14: =+'Budget Plants'!G21 -> 0 | H14: =+'Budget Plants'!H21 -> 0 | I14: =+'Budget Plants'!I21 -> 0 | ... M14: =+'Budget Plants'!M21 -> 0 | N14: =SUM(B14:M14) -> 0 | O14: 399668.6 | P14: =+N14-O14 -> -399668.6 | Q14: =+P14/O14 -> -1 | R14: =+'Budget Plants'!N21 -> 0 | S14: =+N14-R14 -> 0
A15: Consommation Phytos | B15: =+'Budget Phytos'!B16 -> 0 | C15: =+'Budget Phytos'!C16 -> 0 | D15: =+'Budget Phytos'!D16 -> 0 | E15: =+'Budget Phytos'!E16 -> 0 | F15: =+'Budget Phytos'!F16 -> 0 | G15: =+'Budget Phytos'!G16 -> 0 | H15: =+'Budget Phytos'!H16 -> 0 | I15: =+'Budget Phytos'!I16 -> 0 | ... M15: =+'Budget Phytos'!M16 -> 0 | N15: =SUM(B15:M15) -> 0 | O15: 622415.65 | P15: =+N15-O15 -> -622415.65 | Q15: =+P15/O15 -> -1 | R15: =+'Budget Phytos'!N16 -> 0 | S15: =+N15-R15 -> 0
A16: Consommation Insectes | B16: =+'Budget Ruches'!B20 -> 0 | C16: =+'Budget Ruches'!C20 -> 0 | D16: =+'Budget Ruches'!D20 -> 0 | E16: =+'Budget Ruches'!E20 -> 0 | F16: =+'Budget Ruches'!F20 -> 0 | G16: =+'Budget Ruches'!G20 -> 0 | H16: =+'Budget Ruches'!H20 -> 0 | I16: =+'Budget Ruches'!I20 -> 0 | ... M16: =+'Budget Ruches'!M20 -> 0 | N16: =SUM(B16:M16) -> 0 | O16: 200129.96 | P16: =+N16-O16 -> -200129.96 | Q16: =+P16/O16 -> -1 | R16: =+'Budget Ruches'!N20 -> 0 | S16: =+N16-R16 -> 0 | U16: =+O16/220 -> 909.68166
A17: Autres fournitures agricoles | B17: =+'Budget Fres Agri'!B24 -> 0 | C17: =+'Budget Fres Agri'!C24 -> 0 | D17: =+'Budget Fres Agri'!D24 -> 0 | E17: =+'Budget Fres Agri'!E24 -> 0 | F17: =+'Budget Fres Agri'!F24 -> 0 | G17: =+'Budget Fres Agri'!G24 -> 0 | H17: =+'Budget Fres Agri'!H24 -> 0 | I17: =+'Budget Fres Agri'!I24 -> 0 | ... M17: =+'Budget Fres Agri'!M24 -> 0 | N17: =SUM(B17:M17) -> 0 | O17: 31340 | P17: =+N17-O17 -> -31340 | Q17: =+P17/O17 -> -1 | R17: =+'Budget Fres Agri'!N24 -> 0 | S17: =+N17-R17 -> 0 | U17: =+U16/7.9 -> 115.14958
A18: Total consommation Intrants | B18: =SUM(B12:B17) -> 0 | C18: =SUM(C12:C17) -> 0 | D18: =SUM(D12:D17) -> 0 | E18: =SUM(E12:E17) -> 0 | F18: =SUM(F12:F17) -> 0 | G18: =SUM(G12:G17) -> 0 | H18: =SUM(H12:H17) -> 0 | I18: =SUM(I12:I17) -> 0 | ... M18: =SUM(M12:M17) -> 0 | N18: =SUM(B18:M18) -> 0 | O18: =SUM(O12:O17) -> 3676164.7 | P18: =+N18-O18 -> -3676164.7 | Q18: =+P18/O18 -> -1 | R18: =+'Budget Semences'!N20+'Budget Plants'!N21+'Budget Engrais'!N16+'Budget Phytos'!N16+'Budget Ruches'!N20+'Budget Fres Agri'!N24 -> 0 | S18: =+N18-R18 -> 0
A19: Electricité | B19: =+'Budget Energie'!B32 -> 0 | C19: =+'Budget Energie'!C32 -> 0 | D19: =+'Budget Energie'!D32 -> 0 | E19: =+'Budget Energie'!E32 -> 0 | F19: =+'Budget Energie'!F32 -> 0 | G19: =+'Budget Energie'!G32 -> 0 | H19: =+'Budget Energie'!H32 -> 0 | I19: =+'Budget Energie'!I32 -> 0 | ... M19: =+'Budget Energie'!M32 -> 0 | N19: =SUM(B19:M19) -> 0 | O19: 129328.37 | P19: =+N19-O19 -> -129328.37 | Q19: =+P19/O19 -> -1 | R19: =+'Budget Energie'!N32 -> 0 | S19: =+N19-R19 -> 0
A20: Eau | B20: =+'Budget Energie'!B30 -> #DIV/0! | C20: =+'Budget Energie'!C30 -> #DIV/0! | D20: =+'Budget Energie'!D30 -> #DIV/0! | E20: =+'Budget Energie'!E30 -> #DIV/0! | F20: =+'Budget Energie'!F30 -> #DIV/0! | G20: =+'Budget Energie'!G30 -> #DIV/0! | H20: =+'Budget Energie'!H30 -> #DIV/0! | I20: =+'Budget Energie'!I30 -> #DIV/0! | ... M20: =+'Budget Energie'!M30 -> #DIV/0! | N20: =SUM(B20:M20) -> #DIV/0! | O20: 21786.118 | P20: =+N20-O20 -> #DIV/0! | Q20: =+P20/O20 -> #DIV/0! | R20: =+'Budget Energie'!N30 -> #DIV/0! | S20: =+N20-R20 -> #DIV/0!
A21: Total consommation Energie | B21: =SUM(B19:B20) -> #DIV/0! | C21: =SUM(C19:C20) -> #DIV/0! | D21: =SUM(D19:D20) -> #DIV/0! | E21: =SUM(E19:E20) -> #DIV/0! | F21: =SUM(F19:F20) -> #DIV/0! | G21: =SUM(G19:G20) -> #DIV/0! | H21: =SUM(H19:H20) -> #DIV/0! | I21: =SUM(I19:I20) -> #DIV/0! | ... M21: =SUM(M19:M20) -> #DIV/0! | N21: =SUM(B21:M21) -> #DIV/0! | O21: =+O20+O19 -> 151114.49 | P21: =+N21-O21 -> #DIV/0! | Q21: =+P21/O21 -> #DIV/0! | R21: =+'Budget Energie'!N24 -> 0 | S21: =+N21-R21 -> #DIV/0!
A22: Prestations & analyses | B22: =+'Budget Ent & Analyses'!B33+'Budget Commun'!B20 -> 0 | C22: =+'Budget Ent & Analyses'!C33+'Budget Commun'!C20 -> 0 | D22: =+'Budget Ent & Analyses'!D33+'Budget Commun'!D20 -> 0 | E22: =+'Budget Ent & Analyses'!E33+'Budget Commun'!E20 -> 0 | F22: =+'Budget Ent & Analyses'!F33+'Budget Commun'!F20 -> 0 | G22: =+'Budget Ent & Analyses'!G33+'Budget Commun'!G20 -> 0 | H22: =+'Budget Ent & Analyses'!H33+'Budget Commun'!H20 -> 0 | I22: =+'Budget Ent & Analyses'!I33+'Budget Commun'!I20 -> 0 | ... M22: =+'Budget Ent & Analyses'!M33+'Budget Commun'!M20 -> 0 | N22: =SUM(B22:M22) -> 0 | O22: 11759.316 | P22: =+N22-O22 -> -11759.316 | Q22: =+P22/O22 -> -1 | R22: =+'Budget Ent & Analyses'!N33+'Budget Commun'!N20 -> #DIV/0! | S22: =+N22-R22 -> #DIV/0!
A23: Loyers fermes | B23: =+'Budget Loyers Fermes'!B16 -> 0 | C23: =+'Budget Loyers Fermes'!C16 -> 0 | D23: =+'Budget Loyers Fermes'!D16 -> 0 | E23: =+'Budget Loyers Fermes'!E16 -> 0 | F23: =+'Budget Loyers Fermes'!F16 -> 0 | G23: =+'Budget Loyers Fermes'!G16 -> 0 | H23: =+'Budget Loyers Fermes'!H16 -> 0 | I23: =+'Budget Loyers Fermes'!I16 -> 0 | ... M23: =+'Budget Loyers Fermes'!M16 -> 0 | N23: =SUM(B23:M23) -> 0 | O23: 250000 | P23: =+N23-O23 -> -250000 | Q23: =+P23/O23 -> -1 | R23: =+'Budget Loyers Fermes'!N16 -> 0 | S23: =+N23-R23 -> 0
A24: Entretien | B24: =+'Budget Ent & Analyses'!B35-'Budget Ent & Analyses'!B33+'Budget Commun'!B28 -> 1461.2717 | C24: =+'Budget Ent & Analyses'!C35-'Budget Ent & Analyses'!C33+'Budget Commun'!C28 -> 1461.2717 | D24: =+'Budget Ent & Analyses'!D35-'Budget Ent & Analyses'!D33+'Budget Commun'!D28 -> 1461.2717 | E24: =+'Budget Ent & Analyses'!E35-'Budget Ent & Analyses'!E33+'Budget Commun'!E28 -> 1461.2717 | F24: =+'Budget Ent & Analyses'!F35-'Budget Ent & Analyses'!F33+'Budget Commun'!F28 -> 1461.2717 | G24: =+'Budget Ent & Analyses'!G35-'Budget Ent & Analyses'!G33+'Budget Commun'!G28 -> 1461.2717 | H24: =+'Budget Ent & Analyses'!H35-'Budget Ent & Analyses'!H33+'Budget Commun'!H28 -> 1461.2717 | I24: =+'Budget Ent & Analyses'!I35-'Budget Ent & Analyses'!I33+'Budget Commun'!I28 -> 1461.2717 | ... M24: =+'Budget Ent & Analyses'!M35-'Budget Ent & Analyses'!M33+'Budget Commun'!M28 -> 1461.2717 | N24: =SUM(B24:M24) -> 17535.26 | O24: 171610.26 | P24: =+N24-O24 -> -154075 | Q24: =+P24/O24 -> -0.89781928 | R24: =+'Budget Ent & Analyses'!N35-'Budget Ent & Analyses'!N33+'Budget Commun'!N28 -> #DIV/0! | S24: =+N24-R24 -> #DIV/0!
A25: Main d'œuvre Directe | B25: =+'Budget MOD'!B26 -> 0 | C25: =+'Budget MOD'!C26 -> 0 | D25: =+'Budget MOD'!D26 -> 0 | E25: =+'Budget MOD'!E26 -> 0 | F25: =+'Budget MOD'!F26 -> 0 | G25: =+'Budget MOD'!G26 -> 0 | H25: =+'Budget MOD'!H26 -> 0 | I25: =+'Budget MOD'!I26 -> 0 | ... M25: =+'Budget MOD'!M26 -> 0 | N25: =SUM(B25:M25) -> 0 | O25: 2116946 | P25: =+N25-O25 -> -2116946 | Q25: =+P25/O25 -> -1 | R25: =+'Budget MOD'!N26 -> 0 | S25: =+N25-R25 -> 0
A26: Main d'œuvre Adm. | B26: =+'Budget Commun'!B55 -> 35317.11 | C26: =+'Budget Commun'!C55 -> 35317.11 | D26: =+'Budget Commun'!D55 -> 35317.11 | E26: =+'Budget Commun'!E55 -> 35317.11 | F26: =+'Budget Commun'!F55 -> 35317.11 | G26: =+'Budget Commun'!G55 -> 35317.11 | H26: =+'Budget Commun'!H55 -> 35317.11 | I26: =+'Budget Commun'!I55 -> 35317.11 | ... M26: =+'Budget Commun'!M55 -> 35317.11 | N26: =SUM(B26:M26) -> 423805.32 | O26: 377216.53 | P26: =+N26-O26 -> 46588.79 | Q26: =+P26/O26 -> 0.12350676 | R26: =+'Budget Commun'!N55 -> 423805.32 | S26: =+N26-R26 -> 0
A27: Refact. HIJOS DE FEDERICO LIS | B27: =+'Budget Commun'!B48 -> 0 | C27: =+'Budget Commun'!C48 -> 0 | D27: =+'Budget Commun'!D48 -> 0 | E27: =+'Budget Commun'!E48 -> 0 | F27: =+'Budget Commun'!F48 -> 0 | G27: =+'Budget Commun'!G48 -> 0 | H27: =+'Budget Commun'!H48 -> 0 | I27: =+'Budget Commun'!I48 -> 0 | ... M27: =+'Budget Commun'!M48 -> 0 | N27: =SUM(B27:M27) -> 0 | O27: 180019.49 | P27: =+N27-O27 -> -180019.49 | Q27: =+P27/O27 -> -1 | R27: =+'Budget Commun'!N48 -> 0 | S27: =+N27-R27 -> 0
A28: Transport | B28: =+'Budget Transp Ventes'!B16 -> 0 | C28: =+'Budget Transp Ventes'!C16 -> 0 | D28: =+'Budget Transp Ventes'!D16 -> 0 | E28: =+'Budget Transp Ventes'!E16 -> 0 | F28: =+'Budget Transp Ventes'!F16 -> 0 | G28: =+'Budget Transp Ventes'!G16 -> 0 | H28: =+'Budget Transp Ventes'!H16 -> 0 | I28: =+'Budget Transp Ventes'!I16 -> 0 | ... M28: =+'Budget Transp Ventes'!M16 -> 0 | N28: =SUM(B28:M28) -> 0 | O28: 51283.86 | P28: =+N28-O28 -> -51283.86 | Q28: =+P28/O28 -> -1 | R28: =+'Budget Transp Ventes'!N16 -> 0 | S28: =+N28-R28 -> 0
A29: Autres frais généraux | B29: =+'Budget Commun'!B44+'Budget Commun'!B35 -> 86831.503 | C29: =+'Budget Commun'!C44+'Budget Commun'!C35 -> 4360.9827 | D29: =+'Budget Commun'!D44+'Budget Commun'!D35 -> 4360.9827 | E29: =+'Budget Commun'!E44+'Budget Commun'!E35 -> 4360.9827 | F29: =+'Budget Commun'!F44+'Budget Commun'!F35 -> 4360.9827 | G29: =+'Budget Commun'!G44+'Budget Commun'!G35 -> 4360.9827 | H29: =+'Budget Commun'!H44+'Budget Commun'!H35 -> 6278.9017 | I29: =+'Budget Commun'!I44+'Budget Commun'!I35 -> 4360.9827 | ... M29: =+'Budget Commun'!M44+'Budget Commun'!M35 -> 4360.9827 | N29: =SUM(B29:M29) -> 143569.94 | O29: 90077.583 | P29: =+N29-O29 -> 53492.359 | Q29: =+P29/O29 -> 0.59384762 | R29: =+'Budget Commun'!N44+'Budget Commun'!N35 -> 143569.94 | S29: =+N29-R29 -> 0
A30: Coût de revient total | B30: =SUM(B22:B29)+B21+B18 -> #DIV/0! | C30: =SUM(C22:C29)+C21+C18 -> #DIV/0! | D30: =SUM(D22:D29)+D21+D18 -> #DIV/0! | E30: =SUM(E22:E29)+E21+E18 -> #DIV/0! | F30: =SUM(F22:F29)+F21+F18 -> #DIV/0! | G30: =SUM(G22:G29)+G21+G18 -> #DIV/0! | H30: =SUM(H22:H29)+H21+H18 -> #DIV/0! | I30: =SUM(I22:I29)+I21+I18 -> #DIV/0! | ... M30: =SUM(M22:M29)+M21+M18 -> #DIV/0! | N30: =SUM(B30:M30) -> #DIV/0! | O30: =SUM(O22:O29)+O21+O18 -> 7076192.2 | P30: =+N30-O30 -> #DIV/0! | Q30: =+P30/O30 -> #DIV/0!
A31: EBITDA | B31: =B11-B30 -> #DIV/0! | C31: =C11-C30 -> #DIV/0! | D31: =D11-D30 -> #DIV/0! | E31: =E11-E30 -> #DIV/0! | F31: =F11-F30 -> #DIV/0! | G31: =G11-G30 -> #DIV/0! | H31: =H11-H30 -> #DIV/0! | I31: =I11-I30 -> #DIV/0! | ... O31: =O11-O30 -> 1193236.4 | P31: =+N31-O31 -> #DIV/0! | Q31: =+P31/O31 -> #DIV/0!
A32: Amortissements | B32: =+'Budget Commun'!B15+'Budget Invest& Amort'!B10 -> 131703.29 | C32: =+'Budget Commun'!C15+'Budget Invest& Amort'!C10 -> 131703.29 | D32: =+'Budget Commun'!D15+'Budget Invest& Amort'!D10 -> 131703.29 | E32: =+'Budget Commun'!E15+'Budget Invest& Amort'!E10 -> 131703.29 | F32: =+'Budget Commun'!F15+'Budget Invest& Amort'!F10 -> 131703.29 | G32: =+'Budget Commun'!G15+'Budget Invest& Amort'!G10 -> 131703.29 | H32: =+'Budget Commun'!H15+'Budget Invest& Amort'!H10 -> 131703.29 | I32: =+'Budget Commun'!I15+'Budget Invest& Amort'!I10 -> 131703.29 | ... M32: =+'Budget Commun'!M15+'Budget Invest& Amort'!M10 -> 131703.29 | N32: =SUM(B32:M32) -> 1580439.4 | O32: 1727123.2 | P32: =+N32-O32 -> -146683.76 | Q32: =+P32/O32 -> -0.084929531 | R32: =+'Budget Commun'!N15+'Budget Invest& Amort'!N10 -> 1580439.4 | S32: =+N32-R32 -> 0
A33: Résultat d'exploitation | B33: =B31-B32 -> #DIV/0! | C33: =C31-C32 -> #DIV/0! | D33: =D31-D32 -> #DIV/0! | E33: =E31-E32 -> #DIV/0! | F33: =F31-F32 -> #DIV/0! | G33: =G31-G32 -> #DIV/0! | H33: =H31-H32 -> #DIV/0! | I33: =I31-I32 -> #DIV/0! | ... O33: =O31-O32 -> -533886.78 | P33: =+N33-O33 -> #DIV/0! | Q33: =+P33/O33 -> #DIV/0!
A34: EBITDA en % du CA | N34: =+N31/N7 -> #DIV/0! | O34: =+O31/O7 -> 0.15311827 | P34: =+N34-O34 -> #DIV/0!
A35: PMV au kg | B35: =+(B7)/B5 -> #DIV/0! | C35: =+(C7)/C5 -> #DIV/0! | D35: =+(D7)/D5 -> #DIV/0! | E35: =+(E7)/E5 -> 0 | F35: =+(F7)/F5 -> 0 | G35: =+(G7)/G5 -> 0 | H35: =+(H7)/H5 -> 0 | I35: =+(I7)/I5 -> 0 | ... O35: =+(O7)/O5 -> 10.47282 | P35: =+N35-O35 -> -10.47282 | Q35: =+P35/O35 -> -1
A36: CA à l'hectare prod | B36: =+B7/B4 -> 0 | C36: =+C7/C4 -> 0 | D36: =+D7/D4 -> 0 | E36: =+E7/E4 -> 0 | F36: =+F7/F4 -> 0 | G36: =+G7/G4 -> 0 | H36: =+H7/H4 -> 0 | I36: =+I7/I4 -> 0 | ... O36: =+O7/O4 -> 986443.94 | P36: =+N36-O36 -> -986443.94 | Q36: =+P36/O36 -> -1
A37: Coût à l'hectare prod (hors Amort) | B37: =+(B30-B10)/B4 -> #DIV/0! | C37: =+(C30-C10)/C4 -> #DIV/0! | D37: =+(D30-D10)/D4 -> #DIV/0! | E37: =+(E30-E10)/E4 -> #DIV/0! | F37: =+(F30-F10)/F4 -> #DIV/0! | G37: =+(G30-G10)/G4 -> #DIV/0! | H37: =+(H30-H10)/H4 -> #DIV/0! | I37: =+(I30-I10)/I4 -> #DIV/0! | ... O37: =+(O30-O10)/O4 -> 895720.53 | P37: =+N37-O37 -> #DIV/0! | Q37: =+P37/O37 -> #DIV/0!
A38: EBITDA à l'hectare prod | B38: =+B31/B4 -> #DIV/0! | C38: =+C31/C4 -> #DIV/0! | D38: =+D31/D4 -> #DIV/0! | E38: =+E31/E4 -> #DIV/0! | F38: =+F31/F4 -> #DIV/0! | G38: =+G31/G4 -> #DIV/0! | H38: =+H31/H4 -> #DIV/0! | I38: =+I31/I4 -> #DIV/0! | ... O38: =+O31/O4 -> 151042.59 | P38: =+N38-O38 -> #DIV/0! | Q38: =+P38/O38 -> #DIV/0!
A39: Coût total à l'hectare prod | B39: =+(B30+B32-B10)/B4 -> #DIV/0! | C39: =+(C30+C32-C10)/C4 -> #DIV/0! | D39: =+(D30+D32-D10)/D4 -> #DIV/0! | E39: =+(E30+E32-E10)/E4 -> #DIV/0! | F39: =+(F30+F32-F10)/F4 -> #DIV/0! | G39: =+(G30+G32-G10)/G4 -> #DIV/0! | H39: =+(H30+H32-H10)/H4 -> #DIV/0! | I39: =+(I30+I32-I10)/I4 -> #DIV/0! | ... O39: =+(O30+O32-O10)/O4 -> 1114343.7 | P39: =+N39-O39 -> #DIV/0! | Q39: =+P39/O39 -> #DIV/0!
A40: REX à l'hectare prod | B40: =B33/B4 -> #DIV/0! | C40: =C33/C4 -> #DIV/0! | D40: =D33/D4 -> #DIV/0! | E40: =E33/E4 -> #DIV/0! | F40: =F33/F4 -> #DIV/0! | G40: =G33/G4 -> #DIV/0! | H40: =H33/H4 -> #DIV/0! | I40: =I33/I4 -> #DIV/0! | ... O40: =O33/O4 -> -67580.605 | P40: =+N40-O40 -> #DIV/0! | Q40: =+P40/O40 -> #DIV/0!
A41: Détail des coûts à l'hectare
A42: Coût total à l'hectare | B42: =+(B30+B32)/B3 -> #DIV/0! | C42: =+(C30+C32)/C3 -> #DIV/0! | D42: =+(D30+D32)/D3 -> #DIV/0! | E42: =+(E30+E32)/E3 -> #DIV/0! | F42: =+(F30+F32)/F3 -> #DIV/0! | G42: =+(G30+G32)/G3 -> #DIV/0! | H42: =+(H30+H32)/H3 -> #DIV/0! | I42: =+(I30+I32)/I3 -> #DIV/0! | ... M42: =+(M30+M32)/M3 -> #DIV/0! | N42: =+(N30+N32-N10)/N3 -> #DIV/0! | O42: =+(O30+O32-O10)/O3 -> 1114343.7 | P42: =+N42-O42 -> #DIV/0! | Q42: =+P42/O42 -> #DIV/0!
A43: Coût à l'hectare (hors Amort) | B43: =+B30/B3 -> #DIV/0! | C43: =+C30/C3 -> #DIV/0! | D43: =+D30/D3 -> #DIV/0! | E43: =+E30/E3 -> #DIV/0! | F43: =+F30/F3 -> #DIV/0! | G43: =+G30/G3 -> #DIV/0! | H43: =+H30/H3 -> #DIV/0! | I43: =+I30/I3 -> #DIV/0! | ... M43: =+M30/M3 -> #DIV/0! | N43: =+(N30-N10)/N3 -> #DIV/0! | O43: =+(O30-O10)/O3 -> 895720.53 | P43: =+N43-O43 -> #DIV/0! | Q43: =+P43/O43 -> #DIV/0!
A44: Semences | B44: =+B12/B3 -> #DIV/0! | C44: =+C12/C3 -> #DIV/0! | D44: =+D12/D3 -> #DIV/0! | E44: =+E12/E3 -> #DIV/0! | F44: =+F12/F3 -> #DIV/0! | G44: =+G12/G3 -> #DIV/0! | H44: =+H12/H3 -> #DIV/0! | I44: =+I12/I3 -> #DIV/0! | ... O44: =+O12/O3 -> 156501.04 | P44: =+N44-O44 -> #DIV/0! | Q44: =+P44/O44 -> #DIV/0! | R44: Tech
A45: Engrais | B45: =+B13/B3 -> #DIV/0! | C45: =+C13/C3 -> #DIV/0! | D45: =+D13/D3 -> #DIV/0! | E45: =+E13/E3 -> #DIV/0! | F45: =+F13/F3 -> #DIV/0! | G45: =+G13/G3 -> #DIV/0! | H45: =+H13/H3 -> #DIV/0! | I45: =+I13/I3 -> #DIV/0! | ... O45: =+O13/O3 -> 150158.51 | P45: =+N45-O45 -> #DIV/0! | Q45: =+P45/O45 -> #DIV/0! | R45: Coco 16/17
A46: Plants | B46: =+B14/B3 -> #DIV/0! | C46: =+C14/C3 -> #DIV/0! | D46: =+D14/D3 -> #DIV/0! | E46: =+E14/E3 -> #DIV/0! | F46: =+F14/F3 -> #DIV/0! | G46: =+G14/G3 -> #DIV/0! | H46: =+H14/H3 -> #DIV/0! | I46: =+I14/I3 -> #DIV/0! | ... O46: =+O14/O3 -> 50590.962 | P46: =+N46-O46 -> #DIV/0! | Q46: =+P46/O46 -> #DIV/0! | R46: Tech | T46: =+N44+N46 -> #DIV/0!
A47: Phytos | B47: =+B15/B3 -> #DIV/0! | C47: =+C15/C3 -> #DIV/0! | D47: =+D15/D3 -> #DIV/0! | E47: =+E15/E3 -> #DIV/0! | F47: =+F15/F3 -> #DIV/0! | G47: =+G15/G3 -> #DIV/0! | H47: =+H15/H3 -> #DIV/0! | I47: =+I15/I3 -> #DIV/0! | ... O47: =+O15/O3 -> 78786.791 | P47: =+N47-O47 -> #DIV/0! | Q47: =+P47/O47 -> #DIV/0! | R47: NS
A48: Insectes | B48: =+B16/B3 -> #DIV/0! | C48: =+C16/C3 -> #DIV/0! | D48: =+D16/D3 -> #DIV/0! | E48: =+E16/E3 -> #DIV/0! | F48: =+F16/F3 -> #DIV/0! | G48: =+G16/G3 -> #DIV/0! | H48: =+H16/H3 -> #DIV/0! | I48: =+I16/I3 -> #DIV/0! | ... O48: =+O16/O3 -> 25332.907 | P48: =+N48-O48 -> #DIV/0! | Q48: =+P48/O48 -> #DIV/0! | R48: Tech
A49: Autres fournitures agricoles | B49: =+B17/B3 -> #DIV/0! | C49: =+C17/C3 -> #DIV/0! | D49: =+D17/D3 -> #DIV/0! | E49: =+E17/E3 -> #DIV/0! | F49: =+F17/F3 -> #DIV/0! | G49: =+G17/G3 -> #DIV/0! | H49: =+H17/H3 -> #DIV/0! | I49: =+I17/I3 -> #DIV/0! | ... O49: =+O17/O3 -> 3967.0886 | P49: =+N49-O49 -> #DIV/0! | Q49: =+P49/O49 -> #DIV/0! | R49: Tech
A50: Electricité | B50: =+B19/B3 -> #DIV/0! | C50: =+C19/C3 -> #DIV/0! | D50: =+D19/D3 -> #DIV/0! | E50: =+E19/E3 -> #DIV/0! | F50: =+F19/F3 -> #DIV/0! | G50: =+G19/G3 -> #DIV/0! | H50: =+H19/H3 -> #DIV/0! | I50: =+I19/I3 -> #DIV/0! | ... O50: =+O19/O3 -> 16370.68 | P50: =+N50-O50 -> #DIV/0! | Q50: =+P50/O50 -> #DIV/0! | R50: Tech
A51: Eau | B51: =+B20/B3 -> #DIV/0! | C51: =+C20/C3 -> #DIV/0! | D51: =+D20/D3 -> #DIV/0! | E51: =+E20/E3 -> #DIV/0! | F51: =+F20/F3 -> #DIV/0! | G51: =+G20/G3 -> #DIV/0! | H51: =+H20/H3 -> #DIV/0! | I51: =+I20/I3 -> #DIV/0! | ... O51: =+O20/O3 -> 2757.7365 | P51: =+N51-O51 -> #DIV/0! | Q51: =+P51/O51 -> #DIV/0! | R51: NS
A52: Prestations & analyses | B52: =+B22/B3 -> #DIV/0! | C52: =+C22/C3 -> #DIV/0! | D52: =+D22/D3 -> #DIV/0! | E52: =+E22/E3 -> #DIV/0! | F52: =+F22/F3 -> #DIV/0! | G52: =+G22/G3 -> #DIV/0! | H52: =+H22/H3 -> #DIV/0! | I52: =+I22/I3 -> #DIV/0! | ... O52: =+O22/O3 -> 1488.521 | P52: =+N52-O52 -> #DIV/0! | Q52: =+P52/O52 -> #DIV/0! | R52: NS
A53: Loyers fermes | B53: =+B23/B3 -> #DIV/0! | C53: =+C23/C3 -> #DIV/0! | D53: =+D23/D3 -> #DIV/0! | E53: =+E23/E3 -> #DIV/0! | F53: =+F23/F3 -> #DIV/0! | G53: =+G23/G3 -> #DIV/0! | H53: =+H23/H3 -> #DIV/0! | I53: =+I23/I3 -> #DIV/0! | ... O53: =+O23/O3 -> 31645.57 | P53: =+N53-O53 -> #DIV/0! | Q53: =+P53/O53 -> #DIV/0! | R53: OK
A54: Entretien | B54: =+B24/B3 -> #DIV/0! | C54: =+C24/C3 -> #DIV/0! | D54: =+D24/D3 -> #DIV/0! | E54: =+E24/E3 -> #DIV/0! | F54: =+F24/F3 -> #DIV/0! | G54: =+G24/G3 -> #DIV/0! | H54: =+H24/H3 -> #DIV/0! | I54: =+I24/I3 -> #DIV/0! | ... O54: =+O24/O3 -> 21722.817 | P54: =+N54-O54 -> #DIV/0! | Q54: =+P54/O54 -> #DIV/0! | R54: NS
A55: Main d'œuvre Directe | B55: =+B25/B3 -> #DIV/0! | C55: =+C25/C3 -> #DIV/0! | D55: =+D25/D3 -> #DIV/0! | E55: =+E25/E3 -> #DIV/0! | F55: =+F25/F3 -> #DIV/0! | G55: =+G25/G3 -> #DIV/0! | H55: =+H25/H3 -> #DIV/0! | I55: =+I25/I3 -> #DIV/0! | ... O55: =+O25/O3 -> 267967.85 | P55: =+N55-O55 -> #DIV/0! | Q55: =+P55/O55 -> #DIV/0! | R55: Hause de 2%
A56: Main d'œuvre Adm. | B56: =+B26/B3 -> #DIV/0! | C56: =+C26/C3 -> #DIV/0! | D56: =+D26/D3 -> #DIV/0! | E56: =+E26/E3 -> #DIV/0! | F56: =+F26/F3 -> #DIV/0! | G56: =+G26/G3 -> #DIV/0! | H56: =+H26/H3 -> #DIV/0! | I56: =+I26/I3 -> #DIV/0! | ... O56: =+O26/O3 -> 47748.928 | P56: =+N56-O56 -> #DIV/0! | Q56: =+P56/O56 -> #DIV/0! | R56: OK
A57: Refact. HIJOS DE FEDERICO LIS | B57: =+B27/B3 -> #DIV/0! | C57: =+C27/C3 -> #DIV/0! | D57: =+D27/D3 -> #DIV/0! | E57: =+E27/E3 -> #DIV/0! | F57: =+F27/F3 -> #DIV/0! | G57: =+G27/G3 -> #DIV/0! | H57: =+H27/H3 -> #DIV/0! | I57: =+I27/I3 -> #DIV/0! | ... O57: =+O27/O3 -> 22787.278 | P57: =+N57-O57 -> #DIV/0! | Q57: =+P57/O57 -> #DIV/0! | R57: OK
A58: Transport | B58: =+B28/B3 -> #DIV/0! | C58: =+C28/C3 -> #DIV/0! | D58: =+D28/D3 -> #DIV/0! | E58: =+E28/E3 -> #DIV/0! | F58: =+F28/F3 -> #DIV/0! | G58: =+G28/G3 -> #DIV/0! | H58: =+H28/H3 -> #DIV/0! | I58: =+I28/I3 -> #DIV/0! | ... O58: =+O28/O3 -> 6491.6279 | P58: =+N58-O58 -> #DIV/0! | Q58: =+P58/O58 -> #DIV/0! | R58: OK
A59: Autres frais généraux | B59: =+B29/B3 -> #DIV/0! | C59: =+C29/C3 -> #DIV/0! | D59: =+D29/D3 -> #DIV/0! | E59: =+E29/E3 -> #DIV/0! | F59: =+F29/F3 -> #DIV/0! | G59: =+G29/G3 -> #DIV/0! | H59: =+H29/H3 -> #DIV/0! | I59: =+I29/I3 -> #DIV/0! | ... O59: =+O29/O3 -> 11402.226 | P59: =+N59-O59 -> #DIV/0! | Q59: =+P59/O59 -> #DIV/0! | R59: Hon 16/17
A60: Amortissements | B60: =+B32/B3 -> #DIV/0! | C60: =+C32/C3 -> #DIV/0! | D60: =+D32/D3 -> #DIV/0! | E60: =+E32/E3 -> #DIV/0! | F60: =+F32/F3 -> #DIV/0! | G60: =+G32/G3 -> #DIV/0! | H60: =+H32/H3 -> #DIV/0! | I60: =+I32/I3 -> #DIV/0! | ... O60: =+O32/O3 -> 218623.19 | P60: =+N60-O60 -> #DIV/0! | Q60: =+P60/O60 -> #DIV/0! | R60: Amort acq 16/17
A61: Calcul des encours
A62: Encours initial | D62: =+B10+C10+D10 -> #DIV/0!
A63: Coût des encours | D63: =+D62/N5 -> #DIV/0! | E63: =+D63 -> #DIV/0! | F63: =+E63 -> #DIV/0! | G63: =+F63 -> #DIV/0! | H63: =+G63 -> #DIV/0! | I63: =+H63 -> #DIV/0! | J63: =+I63 -> #DIV/0! | K63: =+J63 -> #DIV/0! | L63: =+K63 -> #DIV/0! | M63: =+L63 -> #DIV/0!
A64: Coût des ventes | E64: =+E63*E5 -> #DIV/0! | F64: =+F63*F5 -> #DIV/0! | G64: =+G63*G5 -> #DIV/0! | H64: =+H63*H5 -> #DIV/0! | I64: =+I63*I5 -> #DIV/0! | J64: =+J63*J5 -> #DIV/0! | K64: =+K63*K5 -> #DIV/0! | L64: =+L63*L5 -> #DIV/0! | M64: =+M63*M5 -> #DIV/0!
A65: Encours fin de période | E65: =+D62-E64 -> #DIV/0! | F65: =+E65-F64 -> #DIV/0! | G65: =+F65-G64 -> #DIV/0! | H65: =+G65-H64 -> #DIV/0! | I65: =+H65-I64 -> #DIV/0! | J65: =+I65-J64 -> #DIV/0! | K65: =+J65-K64 -> #DIV/0! | L65: =+K65-L64 -> #DIV/0! | M65: =+L65-M64 -> #DIV/0!
A66: Variation encours | E66: =+E65-D62 -> #DIV/0! | F66: =+F65-E65 -> #DIV/0! | G66: =+G65-F65 -> #DIV/0! | H66: =+H65-G65 -> #DIV/0! | I66: =+I65-H65 -> #DIV/0! | J66: =+J65-I65 -> #DIV/0! | K66: =+K65-J65 -> #DIV/0! | L66: =+L65-K65 -> #DIV/0! | M66: =+M65-L65 -> #DIV/0!

Sheet 106_Synthèse
B1: BUD | C1: BUD | D1: BUD | E1: BUD | F1: BUD | G1: BUD | H1: BUD | I1: BUD | J1: BUD | K1: BUD | L1: BUD | M1: BUD | N1: BUD | O1: REEL | P1: VARIATION | Q1: VARIATION
A2: 106 - Analyse totale (MAD) | B2: 43647 | C2: =+B2+31 -> 43678 | D2: =+C2+31 -> 43709 | E2: =+D2+31 -> 43740 | F2: =+E2+31 -> 43771 | G2: =+F2+31 -> 43802 | H2: =+G2+31 -> 43833 | I2: =+H2+31 -> 43864 | J2: =+I2+31 -> 43895 | ... M2: =+L2+31 -> 43988 | N2: 19/20 | O2: 18/19 | P2: BUD-REEL | Q2: % | R2: source | S2: check
A3: Sup Tot (ha) | B3: =+'Plan de culture 106'!$C$3 -> 5.575 | C3: =+'Plan de culture 106'!$C$3 -> 5.575 | D3: =+'Plan de culture 106'!$C$3 -> 5.575 | E3: =+'Plan de culture 106'!$C$3 -> 5.575 | F3: =+'Plan de culture 106'!$C$3 -> 5.575 | G3: =+'Plan de culture 106'!$C$3 -> 5.575 | H3: =+'Plan de culture 106'!$C$3 -> 5.575 | I3: =+'Plan de culture 106'!$C$3 -> 5.575 | ... N3: =+'Plan de culture 106'!$C$3 -> 5.575 | O3: 2.6 | P3: =+N3-O3 -> 2.975 | Q3: =+P3/O3 -> 1.1442308 | R3: =+'Plan de culture 106'!C3 -> 5.575 | S3: =+N3-R3 -> 0
A4: Sup productive | B4: =+'Budget Volumes Export'!B35 -> 5.395 | C4: =+'Budget Volumes Export'!C35 -> 5.395 | D4: =+'Budget Volumes Export'!D35 -> 5.395 | E4: =+'Budget Volumes Export'!E35 -> 5.395 | F4: =+'Budget Volumes Export'!F35 -> 5.395 | G4: =+'Budget Volumes Export'!G35 -> 5.395 | H4: =+'Budget Volumes Export'!H35 -> 5.395 | I4: =+'Budget Volumes Export'!I35 -> 5.395 | ... N4: =+'Budget Volumes Export'!N35 -> 5.395 | O4: 2.6 | P4: =+N4-O4 -> 2.795 | Q4: =+P4/O4 -> 1.075 | R4: =+'Budget Volumes Export'!N35 -> 5.395 | S4: =+N4-R4 -> 0
A5: Vol (kg) | B5: =+'Budget Volumes Export'!B34*1000 -> 0 | C5: =+'Budget Volumes Export'!C34*1000 -> 0 | D5: =+'Budget Volumes Export'!D34*1000 -> 0 | E5: =+'Budget Volumes Export'!E34*1000 -> 1.079e+08 | F5: =+'Budget Volumes Export'!F34*1000 -> 1.079e+08 | G5: =+'Budget Volumes Export'!G34*1000 -> 80925000 | H5: =+'Budget Volumes Export'!H34*1000 -> 80925000 | I5: =+'Budget Volumes Export'!I34*1000 -> 1.079e+08 | ... M5: =+'Budget Volumes Export'!M34*1000 -> 26975000 | N5: =SUM(B5:M5) -> 728325000 | O5: 130622.01 | P5: =+N5-O5 -> 7.2819438e+08 | Q5: =+P5/O5 -> 5574.8214 | R5: =+'Budget Volumes Export'!N34*1000 -> 728325000 | S5: =+N5-R5 -> 0
A6: rendement (t/ha) | B6: =+B5/B4/1000 -> 0 | C6: =+C5/C4/1000 -> 0 | D6: =+D5/D4/1000 -> 0 | E6: =+E5/E4/1000 -> 20000 | F6: =+F5/F4/1000 -> 20000 | G6: =+G5/G4/1000 -> 15000 | H6: =+H5/H4/1000 -> 15000 | I6: =+I5/I4/1000 -> 20000 | ... O6: =+O5/O4/1000 -> 50.239235 | P6: =+N6-O6 -> 134949.76 | Q6: =+P6/O6 -> 2686.1428 | R6: =+'Budget Volumes Export'!N36 -> 135000 | S6: =+N6-R6 -> 0
A7: CA EXPORT(MAD) | B7: =+'Budget Commercial Export'!B22 -> 0 | C7: =+'Budget Commercial Export'!C22 -> 0 | D7: =+'Budget Commercial Export'!D22 -> 0 | E7: =+'Budget Commercial Export'!E22 -> 0 | F7: =+'Budget Commercial Export'!F22 -> 0 | G7: =+'Budget Commercial Export'!G22 -> 0 | H7: =+'Budget Commercial Export'!H22 -> 0 | I7: =+'Budget Commercial Export'!I22 -> 0 | ... M7: =+'Budget Commercial Export'!M22 -> 0 | N7: =SUM(B7:M7) -> 0 | O7: 932510.13 | P7: =+N7-O7 -> -932510.13 | Q7: =+P7/O7 -> -1 | R7: =+'Budget Commercial Export'!N22 -> 0 | S7: =+N7-R7 -> 0
A8: CA MARCHE LOCAL
A9: Autres revenus (MAD) | N9: =SUM(B9:M9) -> 0 | O9: 39491.96 | P9: =+N9-O9 -> -39491.96 | Q9: =+P9/O9 -> -1
A10: Production encours (MAD) | B10: =+B30+B32 -> 65093.987 | C10: =+C30+C32 -> 37951.79 | D10: =+D30+D32 -> 38128.261 | E10: =+E66 -> -20914.672 | F10: =+F66 -> -20914.672 | G10: =+G66 -> -15686.004 | H10: =+H66 -> -15686.004 | I10: =+I66 -> -20914.672 | J10: =+J66 -> -15686.004 | K10: =+K66 -> -15686.004 | L10: =+L66 -> -10457.336 | M10: =+M66 -> -5228.6681 | N10: =SUM(B10:M10) -> 1.4551915e-11 | O10: 0 | P10: =+N10-O10 -> 1.4551915e-11 | Q10: =+P10/O10 -> #DIV/0! | R10: 0 | S10: =+N10-R10 -> 1.4551915e-11
A11: Production totale (MAD) | B11: =+B10+B7+B9 -> 65093.987 | C11: =+C10+C7+C9 -> 37951.79 | D11: =+D10+D7+D9 -> 38128.261 | E11: =+E10+E7+E9 -> -20914.672 | F11: =+F10+F7+F9 -> -20914.672 | G11: =+G10+G7+G9 -> -15686.004 | H11: =+H10+H7+H9 -> -15686.004 | I11: =+I10+I7+I9 -> -20914.672 | ... M11: =+M10+M7+M9 -> -5228.6681 | N11: =SUM(B11:M11) -> 1.4551915e-11 | O11: =+O10+O7+O9 -> 972002.09 | P11: =+N11-O11 -> -972002.09 | Q11: =+P11/O11 -> -1 | U11: =+O11-O18-O21-O22-O27 -> 535341.69
A12: Consommation Semences | B12: =+'Budget Semences'!B28 -> 3.2 | C12: =+'Budget Semences'!C28 -> 3.2 | D12: =+'Budget Semences'!D28 -> 3.2 | E12: =+'Budget Semences'!E28 -> 3.2 | F12: =+'Budget Semences'!F28 -> 3.2 | G12: =+'Budget Semences'!G28 -> 3.2 | H12: =+'Budget Semences'!H28 -> 3.2 | I12: =+'Budget Semences'!I28 -> 3.2 | ... M12: =+'Budget Semences'!M28 -> 3.2 | N12: =SUM(B12:M12) -> 38.4 | O12: 48450 | P12: =+N12-O12 -> -48411.6 | Q12: =+P12/O12 -> -0.99920743 | R12: =+'Budget Semences'!N28 -> 0 | S12: =+N12-R12 -> 38.4
A13: Consommation Engrais | B13: =+'Budget Engrais'!B22 -> 0 | C13: =+'Budget Engrais'!C22 -> 0 | D13: =+'Budget Engrais'!D22 -> 0 | E13: =+'Budget Engrais'!E22 -> 0 | F13: =+'Budget Engrais'!F22 -> 0 | G13: =+'Budget Engrais'!G22 -> 0 | H13: =+'Budget Engrais'!H22 -> 0 | I13: =+'Budget Engrais'!I22 -> 0 | ... M13: =+'Budget Engrais'!M22 -> 0 | N13: =SUM(B13:M13) -> 0 | O13: 170119.82 | P13: =+N13-O13 -> -170119.82 | Q13: =+P13/O13 -> -1 | R13: =+'Budget Engrais'!N22 -> 0 | S13: =+N13-R13 -> 0
A14: Consommation Plants | B14: =+'Budget Plants'!B29 -> 0 | C14: =+'Budget Plants'!C29 -> 0 | D14: =+'Budget Plants'!D29 -> 0 | E14: =+'Budget Plants'!E29 -> 0 | F14: =+'Budget Plants'!F29 -> 0 | G14: =+'Budget Plants'!G29 -> 0 | H14: =+'Budget Plants'!H29 -> 0 | I14: =+'Budget Plants'!I29 -> 0 | ... M14: =+'Budget Plants'!M29 -> 0 | N14: =SUM(B14:M14) -> 0 | O14: 15603.6 | P14: =+N14-O14 -> -15603.6 | Q14: =+P14/O14 -> -1 | R14: =+'Budget Plants'!N29 -> 0 | S14: =+N14-R14 -> 0
A15: Consommation Phytos | B15: =+'Budget Phytos'!B22 -> 0 | C15: =+'Budget Phytos'!C22 -> 0 | D15: =+'Budget Phytos'!D22 -> 0 | E15: =+'Budget Phytos'!E22 -> 0 | F15: =+'Budget Phytos'!F22 -> 0 | G15: =+'Budget Phytos'!G22 -> 0 | H15: =+'Budget Phytos'!H22 -> 0 | I15: =+'Budget Phytos'!I22 -> 0 | ... M15: =+'Budget Phytos'!M22 -> 0 | N15: =SUM(B15:M15) -> 0 | O15: 67641.418 | P15: =+N15-O15 -> -67641.418 | Q15: =+P15/O15 -> -1 | R15: =+'Budget Phytos'!N22 -> 0 | S15: =+N15-R15 -> 0
A16: Consommation Insectes | B16: =+'Budget Ruches'!B28 -> 4.7 | C16: =+'Budget Ruches'!C28 -> 4.7 | D16: =+'Budget Ruches'!D28 -> 4.7 | E16: =+'Budget Ruches'!E28 -> 4.7 | F16: =+'Budget Ruches'!F28 -> 4.7 | G16: =+'Budget Ruches'!G28 -> 4.7 | H16: =+'Budget Ruches'!H28 -> 4.7 | I16: =+'Budget Ruches'!I28 -> 4.7 | ... M16: =+'Budget Ruches'!M28 -> 4.7 | N16: =SUM(B16:M16) -> 56.4 | O16: 0 | P16: =+N16-O16 -> 56.4 | Q16: =+P16/O16 -> #DIV/0! | R16: =+'Budget Ruches'!N28 -> 0 | S16: =+N16-R16 -> 56.4
A17: Autres fournitures agricoles | B17: =+'Budget Fres Agri'!B34 -> 0 | C17: =+'Budget Fres Agri'!C34 -> 0 | D17: =+'Budget Fres Agri'!D34 -> 0 | E17: =+'Budget Fres Agri'!E34 -> 0 | F17: =+'Budget Fres Agri'!F34 -> 0 | G17: =+'Budget Fres Agri'!G34 -> 0 | H17: =+'Budget Fres Agri'!H34 -> 0 | I17: =+'Budget Fres Agri'!I34 -> 0 | ... M17: =+'Budget Fres Agri'!M34 -> 0 | N17: =SUM(B17:M17) -> 0 | O17: 37041.037 | P17: =+N17-O17 -> -37041.037 | Q17: =+P17/O17 -> -1 | R17: =+'Budget Fres Agri'!N34 -> 0 | S17: =+N17-R17 -> 0
A18: Total consommation Intrants | B18: =SUM(B12:B17) -> 7.9 | C18: =SUM(C12:C17) -> 7.9 | D18: =SUM(D12:D17) -> 7.9 | E18: =SUM(E12:E17) -> 7.9 | F18: =SUM(F12:F17) -> 7.9 | G18: =SUM(G12:G17) -> 7.9 | H18: =SUM(H12:H17) -> 7.9 | I18: =SUM(I12:I17) -> 7.9 | ... M18: =SUM(M12:M17) -> 7.9 | N18: =SUM(B18:M18) -> 94.8 | O18: =SUM(O12:O17) -> 338855.88 | P18: =+N18-O18 -> -338761.08 | Q18: =+P18/O18 -> -0.99972024 | R18: =+'Budget Semences'!N28+'Budget Plants'!N29+'Budget Engrais'!N22+'Budget Phytos'!N22+'Budget Ruches'!N28+'Budget Fres Agri'!N34 -> 0 | S18: =+N18-R18 -> 94.8
A19: Electricité | B19: =+'Budget Energie'!B42 -> 0 | C19: =+'Budget Energie'!C42 -> 0 | D19: =+'Budget Energie'!D42 -> 0 | E19: =+'Budget Energie'!E42 -> 0 | F19: =+'Budget Energie'!F42 -> 0 | G19: =+'Budget Energie'!G42 -> 0 | H19: =+'Budget Energie'!H42 -> 0 | I19: =+'Budget Energie'!I42 -> 0 | ... M19: =+'Budget Energie'!M42 -> 0 | N19: =SUM(B19:M19) -> 0 | O19: 29559.099 | P19: =+N19-O19 -> -29559.099 | Q19: =+P19/O19 -> -1 | R19: =+'Budget Energie'!N42 -> #DIV/0! | S19: =+N19-R19 -> #DIV/0!
A20: Eau | B20: =+'Budget Energie'!B40 -> 0 | C20: =+'Budget Energie'!C40 -> 0 | D20: =+'Budget Energie'!D40 -> 0 | E20: =+'Budget Energie'!E40 -> 0 | F20: =+'Budget Energie'!F40 -> 0 | G20: =+'Budget Energie'!G40 -> 0 | H20: =+'Budget Energie'!H40 -> 0 | I20: =+'Budget Energie'!I40 -> 0 | ... M20: =+'Budget Energie'!M40 -> 0 | N20: =SUM(B20:M20) -> 0 | O20: 5094.618 | P20: =+N20-O20 -> -5094.618 | Q20: =+P20/O20 -> -1 | R20: =+'Budget Energie'!N40 -> #DIV/0! | S20: =+N20-R20 -> #DIV/0!
A21: Total consommation Energie | B21: =SUM(B19:B20) -> 0 | C21: =SUM(C19:C20) -> 0 | D21: =SUM(D19:D20) -> 0 | E21: =SUM(E19:E20) -> 0 | F21: =SUM(F19:F20) -> 0 | G21: =SUM(G19:G20) -> 0 | H21: =SUM(H19:H20) -> 0 | I21: =SUM(I19:I20) -> 0 | ... M21: =SUM(M19:M20) -> 0 | N21: =SUM(B21:M21) -> 0 | O21: =+O20+O19 -> 34653.717 | P21: =+N21-O21 -> -34653.717 | Q21: =+P21/O21 -> -1 | R21: =+'Budget Energie'!N34 -> 0 | S21: =+N21-R21 -> 0
A22: Prestations & analyses | B22: ='Budget Ent & Analyses'!B44+'Budget Commun'!B21 -> 0 | C22: ='Budget Ent & Analyses'!C44+'Budget Commun'!C21 -> 0 | D22: ='Budget Ent & Analyses'!D44+'Budget Commun'!D21 -> 0 | E22: ='Budget Ent & Analyses'!E44+'Budget Commun'!E21 -> 0 | F22: ='Budget Ent & Analyses'!F44+'Budget Commun'!F21 -> 0 | G22: ='Budget Ent & Analyses'!G44+'Budget Commun'!G21 -> 0 | H22: ='Budget Ent & Analyses'!H44+'Budget Commun'!H21 -> 0 | I22: ='Budget Ent & Analyses'!I44+'Budget Commun'!I21 -> 0 | ... M22: ='Budget Ent & Analyses'!M44+'Budget Commun'!M21 -> 0 | N22: =SUM(B22:M22) -> 0 | O22: 3144.307 | P22: =+N22-O22 -> -3144.307 | Q22: =+P22/O22 -> -1 | R22: ='Budget Ent & Analyses'!N44+'Budget Commun'!N21 -> 0 | S22: =+N22-R22 -> 0
A23: Loyers fermes | B23: =+'Budget Loyers Fermes'!B22 -> 0 | C23: =+'Budget Loyers Fermes'!C22 -> 0 | D23: =+'Budget Loyers Fermes'!D22 -> 0 | E23: =+'Budget Loyers Fermes'!E22 -> 0 | F23: =+'Budget Loyers Fermes'!F22 -> 0 | G23: =+'Budget Loyers Fermes'!G22 -> 0 | H23: =+'Budget Loyers Fermes'!H22 -> 0 | I23: =+'Budget Loyers Fermes'!I22 -> 0 | ... M23: =+'Budget Loyers Fermes'!M22 -> 0 | N23: =SUM(B23:M23) -> 0 | O23: 183333.33 | P23: =+N23-O23 -> -183333.33 | Q23: =+P23/O23 -> -1 | R23: =+'Budget Loyers Fermes'!N22 -> 0 | S23: =+N23-R23 -> 0
A24: Entretien | B24: =+'Budget Commun'!B29+'Budget Ent & Analyses'!B37-'Budget Ent & Analyses'!B44 -> 480.92486 | C24: =+'Budget Commun'!C29+'Budget Ent & Analyses'!C37-'Budget Ent & Analyses'!C44 -> 480.92486 | D24: =+'Budget Commun'!D29+'Budget Ent & Analyses'!D37-'Budget Ent & Analyses'!D44 -> 480.92486 | E24: =+'Budget Commun'!E29+'Budget Ent & Analyses'!E37-'Budget Ent & Analyses'!E44 -> 480.92486 | F24: =+'Budget Commun'!F29+'Budget Ent & Analyses'!F37-'Budget Ent & Analyses'!F44 -> 480.92486 | G24: =+'Budget Commun'!G29+'Budget Ent & Analyses'!G37-'Budget Ent & Analyses'!G44 -> 480.92486 | H24: =+'Budget Commun'!H29+'Budget Ent & Analyses'!H37-'Budget Ent & Analyses'!H44 -> 480.92486 | I24: =+'Budget Commun'!I29+'Budget Ent & Analyses'!I37-'Budget Ent & Analyses'!I44 -> 480.92486 | ... M24: =+'Budget Commun'!M29+'Budget Ent & Analyses'!M37-'Budget Ent & Analyses'!M44 -> 480.92486 | N24: =SUM(B24:M24) -> 5771.0983 | O24: 31800.513 | P24: =+N24-O24 -> -26029.414 | Q24: =+P24/O24 -> -0.81852185 | R24: =+'Budget Ent & Analyses'!N37-'Budget Ent & Analyses'!N44+'Budget Commun'!N29 -> 5771.0983 | S24: =+N24-R24 -> 0
A25: Main d'œuvre Directe | B25: =+'Budget MOD'!B37 -> 0 | C25: =+'Budget MOD'!C37 -> 0 | D25: =+'Budget MOD'!D37 -> 176.47059 | E25: =+'Budget MOD'!E37 -> 0 | F25: =+'Budget MOD'!F37 -> 0 | G25: =+'Budget MOD'!G37 -> 176.47059 | H25: =+'Budget MOD'!H37 -> 0 | I25: =+'Budget MOD'!I37 -> 0 | ... M25: =+'Budget MOD'!M37 -> 176.47059 | N25: =SUM(B25:M25) -> 705.88235 | O25: 459592.51 | P25: =+N25-O25 -> -458886.63 | Q25: =+P25/O25 -> -0.99846411 | R25: =+'Budget MOD'!N37 -> 705.88235 | S25: =+N25-R25 -> 0
A26: Main d'œuvre Adm. | B26: =+'Budget Commun'!B56 -> 11623.353 | C26: =+'Budget Commun'!C56 -> 11623.353 | D26: =+'Budget Commun'!D56 -> 11623.353 | E26: =+'Budget Commun'!E56 -> 11623.353 | F26: =+'Budget Commun'!F56 -> 11623.353 | G26: =+'Budget Commun'!G56 -> 11623.353 | H26: =+'Budget Commun'!H56 -> 11623.353 | I26: =+'Budget Commun'!I56 -> 11623.353 | ... M26: =+'Budget Commun'!M56 -> 11623.353 | N26: =SUM(B26:M26) -> 139480.23 | O26: 118588.59 | P26: =+N26-O26 -> 20891.636 | Q26: =+P26/O26 -> 0.17616902 | R26: =+'Budget Commun'!N56 -> 139480.23 | S26: =+N26-R26 -> 0
A27: Refact. HIJOS DE FEDERICO LIS | B27: =+'Budget Commun'!B49 -> 0 | C27: =+'Budget Commun'!C49 -> 0 | D27: =+'Budget Commun'!D49 -> 0 | E27: =+'Budget Commun'!E49 -> 0 | F27: =+'Budget Commun'!F49 -> 0 | G27: =+'Budget Commun'!G49 -> 0 | H27: =+'Budget Commun'!H49 -> 0 | I27: =+'Budget Commun'!I49 -> 0 | ... M27: =+'Budget Commun'!M49 -> 0 | N27: =SUM(B27:M27) -> 0 | O27: 60006.497 | P27: =+N27-O27 -> -60006.497 | Q27: =+P27/O27 -> -1 | R27: =+'Budget Commun'!N49 -> 0 | S27: =+N27-R27 -> 0
A28: Transport | B28: =+'Budget Transp Ventes'!B22 -> 0 | C28: =+'Budget Transp Ventes'!C22 -> 0 | D28: =+'Budget Transp Ventes'!D22 -> 0 | E28: =+'Budget Transp Ventes'!E22 -> 0 | F28: =+'Budget Transp Ventes'!F22 -> 0 | G28: =+'Budget Transp Ventes'!G22 -> 0 | H28: =+'Budget Transp Ventes'!H22 -> 0 | I28: =+'Budget Transp Ventes'!I22 -> 0 | ... M28: =+'Budget Transp Ventes'!M22 -> 0 | N28: =SUM(B28:M28) -> 0 | O28: 21108.953 | P28: =+N28-O28 -> -21108.953 | Q28: =+P28/O28 -> -1 | R28: =+'Budget Transp Ventes'!N22 -> 0 | S28: =+N28-R28 -> 0
A29: Autres frais généraux | B29: =+'Budget Commun'!B45+'Budget Commun'!B36 -> 28577.457 | C29: =+'Budget Commun'!C45+'Budget Commun'!C36 -> 1435.2601 | D29: =+'Budget Commun'!D45+'Budget Commun'!D36 -> 1435.2601 | E29: =+'Budget Commun'!E45+'Budget Commun'!E36 -> 1435.2601 | F29: =+'Budget Commun'!F45+'Budget Commun'!F36 -> 1435.2601 | G29: =+'Budget Commun'!G45+'Budget Commun'!G36 -> 1435.2601 | H29: =+'Budget Commun'!H45+'Budget Commun'!H36 -> 2066.474 | I29: =+'Budget Commun'!I45+'Budget Commun'!I36 -> 1435.2601 | ... M29: =+'Budget Commun'!M45+'Budget Commun'!M36 -> 1435.2601 | N29: =SUM(B29:M29) -> 47250.867 | O29: 25918.321 | P29: =+N29-O29 -> 21332.546 | Q29: =+P29/O29 -> 0.82306823 | R29: =+'Budget Commun'!N45+'Budget Commun'!N36 -> 47250.867 | S29: =+N29-R29 -> 0
A30: Coût de revient total | B30: =SUM(B22:B29)+B21+B18 -> 40689.634 | C30: =SUM(C22:C29)+C21+C18 -> 13547.438 | D30: =SUM(D22:D29)+D21+D18 -> 13723.908 | E30: =SUM(E22:E29)+E21+E18 -> 13547.438 | F30: =SUM(F22:F29)+F21+F18 -> 13547.438 | G30: =SUM(G22:G29)+G21+G18 -> 13723.908 | H30: =SUM(H22:H29)+H21+H18 -> 14178.651 | I30: =SUM(I22:I29)+I21+I18 -> 13547.438 | ... M30: =SUM(M22:M29)+M21+M18 -> 13723.908 | N30: =SUM(B30:M30) -> 193302.88 | O30: =SUM(O22:O29)+O21+O18 -> 1277002.6 | P30: =+N30-O30 -> -1083699.7 | Q30: =+P30/O30 -> -0.84862766
A31: EBITDA | B31: =B11-B30 -> 24404.353 | C31: =C11-C30 -> 24404.353 | D31: =D11-D30 -> 24404.353 | E31: =E11-E30 -> -34462.11 | F31: =F11-F30 -> -34462.11 | G31: =G11-G30 -> -29409.912 | H31: =H11-H30 -> -29864.656 | I31: =I11-I30 -> -34462.11 | ... O31: =O11-O30 -> -305000.54 | P31: =+N31-O31 -> 111697.66 | Q31: =+P31/O31 -> -0.36622118
A32: Amortissements | B32: =+'Budget Commun'!B16+'Budget Invest& Amort'!B11 -> 24404.353 | C32: =+'Budget Commun'!C16+'Budget Invest& Amort'!C11 -> 24404.353 | D32: =+'Budget Commun'!D16+'Budget Invest& Amort'!D11 -> 24404.353 | E32: =+'Budget Commun'!E16+'Budget Invest& Amort'!E11 -> 24404.353 | F32: =+'Budget Commun'!F16+'Budget Invest& Amort'!F11 -> 24404.353 | G32: =+'Budget Commun'!G16+'Budget Invest& Amort'!G11 -> 24404.353 | H32: =+'Budget Commun'!H16+'Budget Invest& Amort'!H11 -> 24404.353 | I32: =+'Budget Commun'!I16+'Budget Invest& Amort'!I11 -> 24404.353 | ... M32: =+'Budget Commun'!M16+'Budget Invest& Amort'!M11 -> 24404.353 | N32: =SUM(B32:M32) -> 292852.23 | O32: 174084.99 | P32: =+N32-O32 -> 118767.25 | Q32: =+P32/O32 -> 0.68223716 | R32: =+'Budget Commun'!N16+'Budget Invest& Amort'!N11 -> 292852.23 | S32: =+N32-R32 -> 0
A33: Résultat d'exploitation | B33: =B31-B32 -> 0 | C33: =C31-C32 -> 0 | D33: =D31-D32 -> 0 | E33: =E31-E32 -> -58866.463 | F33: =F31-F32 -> -58866.463 | G33: =G31-G32 -> -53814.265 | H33: =H31-H32 -> -54269.009 | I33: =I31-I32 -> -58866.463 | ... O33: =O31-O32 -> -479085.52 | P33: =+N33-O33 -> -7069.5912 | Q33: =+-P33/O33 -> -0.014756428
A34: EBITDA en % du CA | N34: =+N31/N7 -> #DIV/0! | O34: =+O31/O7 -> -0.32707477 | P34: =+N34-O34 -> #DIV/0!
A35: PMV au kg | B35: =+(B7)/B5 -> #DIV/0! | C35: =+(C7)/C5 -> #DIV/0! | D35: =+(D7)/D5 -> #DIV/0! | E35: =+(E7)/E5 -> 0 | F35: =+(F7)/F5 -> 0 | G35: =+(G7)/G5 -> 0 | H35: =+(H7)/H5 -> 0 | I35: =+(I7)/I5 -> 0 | ... O35: =+(O7)/O5 -> 7.138997 | P35: =+N35-O35 -> -7.138997 | Q35: =+P35/O35 -> -1
A36: CA à l'hectare prod | B36: =+B7/B4 -> 0 | C36: =+C7/C4 -> 0 | D36: =+D7/D4 -> 0 | E36: =+E7/E4 -> 0 | F36: =+F7/F4 -> 0 | G36: =+G7/G4 -> 0 | H36: =+H7/H4 -> 0 | I36: =+I7/I4 -> 0 | ... O36: =+O7/O4 -> 358657.74 | P36: =+N36-O36 -> -358657.74 | Q36: =+P36/O36 -> -1
A37: Coût à l'hectare prod (hors Amort) | B37: =+(B30-B10)/B4 -> -4523.513 | C37: =+(C30-C10)/C4 -> -4523.513 | D37: =+(D30-D10)/D4 -> -4523.513 | E37: =+(E30-E10)/E4 -> 6387.7868 | F37: =+(F30-F10)/F4 -> 6387.7868 | G37: =+(G30-G10)/G4 -> 5451.3276 | H37: =+(H30-H10)/H4 -> 5535.6174 | I37: =+(I30-I10)/I4 -> 6387.7868 | ... O37: =+(O30-O10)/O4 -> 491154.86 | P37: =+N37-O37 -> -455324.85 | Q37: =+P37/O37 -> -0.92704947
A38: EBITDA à l'hectare prod | B38: =+B31/B4 -> 4523.513 | C38: =+C31/C4 -> 4523.513 | D38: =+D31/D4 -> 4523.513 | E38: =+E31/E4 -> -6387.7868 | F38: =+F31/F4 -> -6387.7868 | G38: =+G31/G4 -> -5451.3276 | H38: =+H31/H4 -> -5535.6174 | I38: =+I31/I4 -> -6387.7868 | ... O38: =+O31/O4 -> -117307.9 | P38: =+N38-O38 -> 81477.893 | Q38: =+P38/O38 -> -0.69456442
A39: Coût total à l'hectare prod | B39: =+(B30+B32-B10)/B4 -> 0 | C39: =+(C30+C32-C10)/C4 -> 0 | D39: =+(D30+D32-D10)/D4 -> 0 | E39: =+(E30+E32-E10)/E4 -> 10911.3 | F39: =+(F30+F32-F10)/F4 -> 10911.3 | G39: =+(G30+G32-G10)/G4 -> 9974.8406 | H39: =+(H30+H32-H10)/H4 -> 10059.13 | I39: =+(I30+I32-I10)/I4 -> 10911.3 | ... O39: =+(O30+O32-O10)/O4 -> 558110.62 | P39: =+N39-O39 -> -467998.46 | Q39: =+P39/O39 -> -0.83854068
A40: REX à l'hectare prod | B40: =B33/B4 -> 0 | C40: =C33/C4 -> 0 | D40: =D33/D4 -> 0 | E40: =E33/E4 -> -10911.3 | F40: =F33/F4 -> -10911.3 | G40: =G33/G4 -> -9974.8406 | H40: =H33/H4 -> -10059.13 | I40: =I33/I4 -> -10911.3 | ... O40: =O33/O4 -> -184263.66 | P40: =+N40-O40 -> 94151.5 | Q40: =+P40/O40 -> -0.51096076
A41: Détail des coûts à l'hectare
A42: Coût total à l'hectare | B42: =+(B30+B32)/B3 -> 11676.051 | C42: =+(C30+C32)/C3 -> 6807.496 | D42: =+(D30+D32)/D3 -> 6839.15 | E42: =+(E30+E32)/E3 -> 6807.496 | F42: =+(F30+F32)/F3 -> 6807.496 | G42: =+(G30+G32)/G3 -> 6839.15 | H42: =+(H30+H32)/H3 -> 6920.7183 | I42: =+(I30+I32)/I3 -> 6807.496 | ... M42: =+(M30+M32)/M3 -> 6839.15 | N42: =+(N30+N32-N10)/N3 -> 87202.711 | O42: =+(O30+O32-O10)/O3 -> 558110.62 | P42: =+N42-O42 -> -470907.91 | Q42: =+P42/O42 -> -0.84375372
A43: Coût à l'hectare (hors Amort) | B43: =+B30/B3 -> 7298.5891 | C43: =+C30/C3 -> 2430.0336 | D43: =+D30/D3 -> 2461.6876 | E43: =+E30/E3 -> 2430.0336 | F43: =+F30/F3 -> 2430.0336 | G43: =+G30/G3 -> 2461.6876 | H43: =+H30/H3 -> 2543.2559 | I43: =+I30/I3 -> 2430.0336 | ... M43: =+M30/M3 -> 2461.6876 | N43: =+(N30-N10)/N3 -> 34673.162 | O43: =+(O30-O10)/O3 -> 491154.86 | P43: =+N43-O43 -> -456481.69 | Q43: =+P43/O43 -> -0.92940483
A44: Semences | B44: =+B12/B3 -> 0.57399103 | C44: =+C12/C3 -> 0.57399103 | D44: =+D12/D3 -> 0.57399103 | E44: =+E12/E3 -> 0.57399103 | F44: =+F12/F3 -> 0.57399103 | G44: =+G12/G3 -> 0.57399103 | H44: =+H12/H3 -> 0.57399103 | I44: =+I12/I3 -> 0.57399103 | ... O44: =+O12/O3 -> 18634.615 | P44: =+N44-O44 -> -18627.727 | Q44: =+P44/O44 -> -0.99963037
A45: Engrais | B45: =+B13/B3 -> 0 | C45: =+C13/C3 -> 0 | D45: =+D13/D3 -> 0 | E45: =+E13/E3 -> 0 | F45: =+F13/F3 -> 0 | G45: =+G13/G3 -> 0 | H45: =+H13/H3 -> 0 | I45: =+I13/I3 -> 0 | ... O45: =+O13/O3 -> 65430.7 | P45: =+N45-O45 -> -65430.7 | Q45: =+P45/O45 -> -1
A46: Plants | B46: =+B14/B3 -> 0 | C46: =+C14/C3 -> 0 | D46: =+D14/D3 -> 0 | E46: =+E14/E3 -> 0 | F46: =+F14/F3 -> 0 | G46: =+G14/G3 -> 0 | H46: =+H14/H3 -> 0 | I46: =+I14/I3 -> 0 | ... O46: =+O14/O3 -> 6001.3846 | P46: =+N46-O46 -> -6001.3846 | Q46: =+P46/O46 -> -1
A47: Phytos | B47: =+B15/B3 -> 0 | C47: =+C15/C3 -> 0 | D47: =+D15/D3 -> 0 | E47: =+E15/E3 -> 0 | F47: =+F15/F3 -> 0 | G47: =+G15/G3 -> 0 | H47: =+H15/H3 -> 0 | I47: =+I15/I3 -> 0 | ... O47: =+O15/O3 -> 26015.93 | P47: =+N47-O47 -> -26015.93 | Q47: =+P47/O47 -> -1
A48: Insectes | B48: =+B16/B3 -> 0.84304933 | C48: =+C16/C3 -> 0.84304933 | D48: =+D16/D3 -> 0.84304933 | E48: =+E16/E3 -> 0.84304933 | F48: =+F16/F3 -> 0.84304933 | G48: =+G16/G3 -> 0.84304933 | H48: =+H16/H3 -> 0.84304933 | I48: =+I16/I3 -> 0.84304933 | ... O48: =+O16/O3 -> 0 | P48: =+N48-O48 -> 10.116592 | Q48: =+P48/O48 -> #DIV/0!
A49: Autres fournitures agricoles | B49: =+B17/B3 -> 0 | C49: =+C17/C3 -> 0 | D49: =+D17/D3 -> 0 | E49: =+E17/E3 -> 0 | F49: =+F17/F3 -> 0 | G49: =+G17/G3 -> 0 | H49: =+H17/H3 -> 0 | I49: =+I17/I3 -> 0 | ... O49: =+O17/O3 -> 14246.553 | P49: =+N49-O49 -> -14246.553 | Q49: =+P49/O49 -> -1
A50: Electricité | B50: =+B19/B3 -> 0 | C50: =+C19/C3 -> 0 | D50: =+D19/D3 -> 0 | E50: =+E19/E3 -> 0 | F50: =+F19/F3 -> 0 | G50: =+G19/G3 -> 0 | H50: =+H19/H3 -> 0 | I50: =+I19/I3 -> 0 | ... O50: =+O19/O3 -> 11368.884 | P50: =+N50-O50 -> -11368.884 | Q50: =+P50/O50 -> -1
A51: Eau | B51: =+B20/B3 -> 0 | C51: =+C20/C3 -> 0 | D51: =+D20/D3 -> 0 | E51: =+E20/E3 -> 0 | F51: =+F20/F3 -> 0 | G51: =+G20/G3 -> 0 | H51: =+H20/H3 -> 0 | I51: =+I20/I3 -> 0 | ... O51: =+O20/O3 -> 1959.4685 | P51: =+N51-O51 -> -1959.4685 | Q51: =+P51/O51 -> -1
A52: Prestations & analyses | B52: =+B22/B3 -> 0 | C52: =+C22/C3 -> 0 | D52: =+D22/D3 -> 0 | E52: =+E22/E3 -> 0 | F52: =+F22/F3 -> 0 | G52: =+G22/G3 -> 0 | H52: =+H22/H3 -> 0 | I52: =+I22/I3 -> 0 | ... O52: =+O22/O3 -> 1209.3488 | P52: =+N52-O52 -> -1209.3488 | Q52: =+P52/O52 -> -1
A53: Loyers fermes | B53: =+B23/B3 -> 0 | C53: =+C23/C3 -> 0 | D53: =+D23/D3 -> 0 | E53: =+E23/E3 -> 0 | F53: =+F23/F3 -> 0 | G53: =+G23/G3 -> 0 | H53: =+H23/H3 -> 0 | I53: =+I23/I3 -> 0 | ... O53: =+O23/O3 -> 70512.821 | P53: =+N53-O53 -> -70512.821 | Q53: =+P53/O53 -> -1
A54: Entretien | B54: =+B24/B3 -> 86.264548 | C54: =+C24/C3 -> 86.264548 | D54: =+D24/D3 -> 86.264548 | E54: =+E24/E3 -> 86.264548 | F54: =+F24/F3 -> 86.264548 | G54: =+G24/G3 -> 86.264548 | H54: =+H24/H3 -> 86.264548 | I54: =+I24/I3 -> 86.264548 | ... O54: =+O24/O3 -> 12230.966 | P54: =+N54-O54 -> -11195.792 | Q54: =+P54/O54 -> -0.91536445
A55: Main d'œuvre Directe | B55: =+B25/B3 -> 0 | C55: =+C25/C3 -> 0 | D55: =+D25/D3 -> 31.653917 | E55: =+E25/E3 -> 0 | F55: =+F25/F3 -> 0 | G55: =+G25/G3 -> 31.653917 | H55: =+H25/H3 -> 0 | I55: =+I25/I3 -> 0 | ... O55: =+O25/O3 -> 176766.35 | P55: =+N55-O55 -> -176639.74 | Q55: =+P55/O55 -> -0.99928371
A56: Main d'œuvre Adm. | B56: =+B26/B3 -> 2084.9063 | C56: =+C26/C3 -> 2084.9063 | D56: =+D26/D3 -> 2084.9063 | E56: =+E26/E3 -> 2084.9063 | F56: =+F26/F3 -> 2084.9063 | G56: =+G26/G3 -> 2084.9063 | H56: =+H26/H3 -> 2084.9063 | I56: =+I26/I3 -> 2084.9063 | ... O56: =+O26/O3 -> 45610.998 | P56: =+N56-O56 -> -20592.122 | Q56: =+P56/O56 -> -0.45147274
A57: Refact. HIJOS DE FEDERICO LIS | B57: =+B27/B3 -> 0 | C57: =+C27/C3 -> 0 | D57: =+D27/D3 -> 0 | E57: =+E27/E3 -> 0 | F57: =+F27/F3 -> 0 | G57: =+G27/G3 -> 0 | H57: =+H27/H3 -> 0 | I57: =+I27/I3 -> 0 | ... O57: =+O27/O3 -> 23079.422 | P57: =+N57-O57 -> -23079.422 | Q57: =+P57/O57 -> -1
A58: Transport | B58: =+B28/B3 -> 0 | C58: =+C28/C3 -> 0 | D58: =+D28/D3 -> 0 | E58: =+E28/E3 -> 0 | F58: =+F28/F3 -> 0 | G58: =+G28/G3 -> 0 | H58: =+H28/H3 -> 0 | I58: =+I28/I3 -> 0 | ... O58: =+O28/O3 -> 8118.8283 | P58: =+N58-O58 -> -8118.8283 | Q58: =+P58/O58 -> -1
A59: Autres frais généraux | B59: =+B29/B3 -> 5126.0012 | C59: =+C29/C3 -> 257.44576 | D59: =+D29/D3 -> 257.44576 | E59: =+E29/E3 -> 257.44576 | F59: =+F29/F3 -> 257.44576 | G59: =+G29/G3 -> 257.44576 | H59: =+H29/H3 -> 370.66798 | I59: =+I29/I3 -> 257.44576 | ... O59: =+O29/O3 -> 9968.5849 | P59: =+N59-O59 -> -1493.093 | Q59: =+P59/O59 -> -0.14977984
A60: Amortissements | B60: =+B32/B3 -> 4377.4624 | C60: =+C32/C3 -> 4377.4624 | D60: =+D32/D3 -> 4377.4624 | E60: =+E32/E3 -> 4377.4624 | F60: =+F32/F3 -> 4377.4624 | G60: =+G32/G3 -> 4377.4624 | H60: =+H32/H3 -> 4377.4624 | I60: =+I32/I3 -> 4377.4624 | ... O60: =+O32/O3 -> 66955.764 | P60: =+N60-O60 -> -14426.215 | Q60: =+P60/O60 -> -0.2154589
A61: Calcul des encours
A62: Encours initial | D62: =+B10+C10+D10 -> 141174.04
A63: Coût des encours | D63: =+D62/N5 -> 0.00019383385 | E63: =+D63 -> 0.00019383385 | F63: =+E63 -> 0.00019383385 | G63: =+F63 -> 0.00019383385 | H63: =+G63 -> 0.00019383385 | I63: =+H63 -> 0.00019383385 | J63: =+I63 -> 0.00019383385 | K63: =+J63 -> 0.00019383385 | L63: =+K63 -> 0.00019383385 | M63: =+L63 -> 0.00019383385
A64: Coût des ventes | E64: =+E63*E5 -> 20914.672 | F64: =+F63*F5 -> 20914.672 | G64: =+G63*G5 -> 15686.004 | H64: =+H63*H5 -> 15686.004 | I64: =+I63*I5 -> 20914.672 | J64: =+J63*J5 -> 15686.004 | K64: =+K63*K5 -> 15686.004 | L64: =+L63*L5 -> 10457.336 | M64: =+M63*M5 -> 5228.6681
A65: Encours fin de période | E65: =+D62-E64 -> 120259.37 | F65: =+E65-F64 -> 99344.694 | G65: =+F65-G64 -> 83658.689 | H65: =+G65-H64 -> 67972.685 | I65: =+H65-I64 -> 47058.013 | J65: =+I65-J64 -> 31372.009 | K65: =+J65-K64 -> 15686.004 | L65: =+K65-L64 -> 5228.6681 | M65: =+L65-M64 -> 1.4551915e-11
A66: Variation encours | E66: =+E65-D62 -> -20914.672 | F66: =+F65-E65 -> -20914.672 | G66: =+G65-F65 -> -15686.004 | H66: =+H65-G65 -> -15686.004 | I66: =+I65-H65 -> -20914.672 | J66: =+J65-I65 -> -15686.004 | K66: =+K65-J65 -> -15686.004 | L66: =+L65-K65 -> -10457.336 | M66: =+M65-L65 -> -5228.6681

Sheet 107_Synthèse
B1: BUD | C1: BUD | D1: BUD | E1: BUD | F1: BUD | G1: BUD | H1: BUD | I1: BUD | J1: BUD | K1: BUD | L1: BUD | M1: BUD | N1: BUD | O1: REEL | P1: VARIATION | Q1: VARIATION
A2: 107 - Analyse totale (MAD) | B2: 43647 | C2: =+B2+31 -> 43678 | D2: =+C2+31 -> 43709 | E2: =+D2+31 -> 43740 | F2: =+E2+31 -> 43771 | G2: =+F2+31 -> 43802 | H2: =+G2+31 -> 43833 | I2: =+H2+31 -> 43864 | J2: =+I2+31 -> 43895 | ... M2: =+L2+31 -> 43988 | N2: 19/20 | O2: 18/19 | P2: BUD-REEL | Q2: % | R2: source | S2: check
A3: Sup Tot (ha) | B3: =+'Plan de culture 107'!$C$3 -> 16.558 | C3: =+'Plan de culture 107'!$C$3 -> 16.558 | D3: =+'Plan de culture 107'!$C$3 -> 16.558 | E3: =+'Plan de culture 107'!$C$3 -> 16.558 | F3: =+'Plan de culture 107'!$C$3 -> 16.558 | G3: =+'Plan de culture 107'!$C$3 -> 16.558 | H3: =+'Plan de culture 107'!$C$3 -> 16.558 | I3: =+'Plan de culture 107'!$C$3 -> 16.558 | ... N3: =+'Plan de culture 107'!$C$3 -> 16.558 | O3: 6.8 | P3: =+N3-O3 -> 9.758 | Q3: =+P3/O3 -> 1.435 | R3: =+'Plan de culture 104 '!$B$3 -> 0 | S3: =+N3-R3 -> 16.558
A4: Sup productive | B4: =+'Budget Volumes Export'!B8 -> 15.35 | C4: =+'Budget Volumes Export'!C8 -> 15.35 | D4: =+'Budget Volumes Export'!D8 -> 15.35 | E4: =+'Budget Volumes Export'!E8 -> 15.35 | F4: =+'Budget Volumes Export'!F8 -> 15.35 | G4: =+'Budget Volumes Export'!G8 -> 15.35 | H4: =+'Budget Volumes Export'!H8 -> 15.35 | I4: =+'Budget Volumes Export'!I8 -> 15.35 | ... N4: =+'Budget Volumes Export'!N8 -> 15.35 | O4: 6.8 | P4: =+N4-O4 -> 8.55 | Q4: =+P4/O4 -> 1.2573529 | R4: =+'Budget Volumes Export'!N8 -> 15.35 | S4: =+N4-R4 -> 0
A5: Vol (kg) | B5: =+'Budget Volumes Export'!B7*1000 -> 0 | C5: =+'Budget Volumes Export'!C7*1000 -> 0 | D5: =+'Budget Volumes Export'!D7*1000 -> 0 | E5: =+'Budget Volumes Export'!E7*1000 -> 0 | F5: =+'Budget Volumes Export'!F7*1000 -> 3.07e+08 | G5: =+'Budget Volumes Export'!G7*1000 -> 2.3025e+08 | H5: =+'Budget Volumes Export'!H7*1000 -> 2.3025e+08 | I5: =+'Budget Volumes Export'!I7*1000 -> 3.07e+08 | ... M5: =+'Budget Volumes Export'!M7*1000 -> 76750000 | N5: =SUM(B5:M5) -> 1.76525e+09 | O5: 1108263.7 | P5: =+N5-O5 -> 1.7641417e+09 | Q5: =+P5/O5 -> 1591.8069 | R5: =+'Budget Volumes Export'!N7*1000 -> 1.76525e+09 | S5: =+N5-R5 -> 0
A6: rendement (t/ha) | B6: =+B5/B4/1000 -> 0 | C6: =+C5/C4/1000 -> 0 | D6: =+D5/D4/1000 -> 0 | E6: =+E5/E4/1000 -> 0 | F6: =+F5/F4/1000 -> 20000 | G6: =+G5/G4/1000 -> 15000 | H6: =+H5/H4/1000 -> 15000 | I6: =+I5/I4/1000 -> 20000 | ... O6: =+O5/O4/1000 -> 162.97995 | P6: =+N6-O6 -> 114837.02 | Q6: =+P6/O6 -> 704.60825 | R6: =+R5/R4/1000 -> 115000 | S6: =+N6-R6 -> 0
A7: CA EXPORT(MAD) | B7: =+'Budget Commercial Export'!B7 -> 0 | C7: =+'Budget Commercial Export'!C7 -> 0 | D7: =+'Budget Commercial Export'!D7 -> 0 | E7: =+'Budget Commercial Export'!E7 -> 0 | F7: =+'Budget Commercial Export'!F7 -> 3070000 | G7: =+'Budget Commercial Export'!G7 -> 2302500 | H7: =+'Budget Commercial Export'!H7 -> 2302500 | I7: =+'Budget Commercial Export'!I7 -> 3070000 | ... M7: =+'Budget Commercial Export'!M7 -> 767500 | N7: =SUM(B7:M7) -> 17652500 | O7: 2538893.7 | P7: =+N7-O7 -> 15113606 | Q7: =+P7/O7 -> 5.9528315 | R7: =+'Budget Commercial Export'!N7 -> 17652500 | S7: =+N7-R7 -> 0
A8: CA MARCHE LOCAL
A9: Autres revenus (MAD) | N9: =SUM(B9:M9) -> 0 | O9: 1023632.5 | P9: =+N9-O9 -> -1023632.5 | Q9: =+P9/O9 -> -1
A10: Production encours (MAD) | B10: =SUM(B68:B82) -> #DIV/0! | C10: =SUM(C68:C82) -> #DIV/0! | D10: =SUM(D68:D82) -> #DIV/0! | E10: =+E66 -> #DIV/0! | F10: =+F66 -> #DIV/0! | G10: =+G66 -> #DIV/0! | H10: =+H66 -> #DIV/0! | I10: =+I66 -> #DIV/0! | J10: =+J66 -> #DIV/0! | K10: =+K66 -> #DIV/0! | L10: =+L66 -> #DIV/0! | M10: =+M66 -> #DIV/0! | N10: =SUM(B10:M10) -> #DIV/0! | O10: 0 | P10: =+N10-O10 -> #DIV/0! | Q10: =+P10/O10 -> #DIV/0! | R10: 0 | S10: =+N10-R10 -> #DIV/0!
A11: Production totale (MAD) | B11: =+B10+B7+B9 -> #DIV/0! | C11: =+C10+C7+C9 -> #DIV/0! | D11: =+D10+D7+D9 -> #DIV/0! | E11: =+E10+E7+E9 -> #DIV/0! | F11: =+F10+F7+F9 -> #DIV/0! | G11: =+G10+G7+G9 -> #DIV/0! | H11: =+H10+H7+H9 -> #DIV/0! | I11: =+I10+I7+I9 -> #DIV/0! | ... M11: =+M10+M7+M9 -> #DIV/0! | N11: =SUM(B11:M11) -> #DIV/0! | O11: =+O10+O7+O9 -> 3562526.2 | P11: =+N11-O11 -> #DIV/0! | Q11: =+P11/O11 -> #DIV/0!
A12: Consommation Semences | B12: =+'Budget Semences'!B7 -> 0 | C12: =+'Budget Semences'!C10 -> 1494600 | D12: =+'Budget Semences'!D10 -> 0 | E12: =+'Budget Semences'!E10 -> 0 | F12: =+'Budget Semences'!F10 -> 0 | G12: =+'Budget Semences'!G10 -> 0 | H12: =+'Budget Semences'!H10 -> 0 | I12: =+'Budget Semences'!I10 -> 0 | J12: =+'Budget Semences'!J10 -> 0 | ... M12: =+'Budget Semences'!M10 -> 0 | N12: =SUM(B12:M12) -> 1494600 | O12: 202400 | P12: =+N12-O12 -> 1292200 | Q12: =+P12/O12 -> 6.3843874 | R12: =+'Budget Semences'!N7 -> 1494600 | S12: =+N12-R12 -> 0
A13: Consommation Engrais | B13: =+'Budget Engrais'!B7 -> 0 | C13: =+'Budget Engrais'!C7 -> 0 | D13: =+'Budget Engrais'!D7 -> 0 | E13: =+'Budget Engrais'!E7 -> 0 | F13: =+'Budget Engrais'!F7 -> 0 | G13: =+'Budget Engrais'!G7 -> 0 | H13: =+'Budget Engrais'!H7 -> 0 | I13: =+'Budget Engrais'!I7 -> 0 | ... M13: =+'Budget Engrais'!M7 -> 0 | N13: =SUM(B13:M13) -> 0 | O13: 537520.18 | P13: =+N13-O13 -> -537520.18 | Q13: =+P13/O13 -> -1 | R13: =+'Budget Engrais'!N7 -> 0 | S13: =+N13-R13 -> 0
A14: Consommation Plants | B14: =+'Budget Plants'!B7 -> 0 | C14: =+'Budget Plants'!C7 -> 1113000 | D14: =+'Budget Plants'!D7 -> 0 | E14: =+'Budget Plants'!E7 -> 0 | F14: =+'Budget Plants'!F7 -> 0 | G14: =+'Budget Plants'!G7 -> 0 | H14: =+'Budget Plants'!H7 -> 0 | I14: =+'Budget Plants'!I7 -> 0 | ... M14: =+'Budget Plants'!M7 -> 0 | N14: =SUM(B14:M14) -> 1113000 | O14: 254887 | P14: =+N14-O14 -> 858113 | Q14: =+P14/O14 -> 3.3666409 | R14: =+'Budget Plants'!N7 -> 1113000 | S14: =+N14-R14 -> 0
A15: Consommation Phytos | B15: =+'Budget Phytos'!B7 -> 0 | C15: =+'Budget Phytos'!C7 -> 0 | D15: =+'Budget Phytos'!D7 -> 0 | E15: =+'Budget Phytos'!E7 -> 0 | F15: =+'Budget Phytos'!F7 -> 0 | G15: =+'Budget Phytos'!G7 -> 0 | H15: =+'Budget Phytos'!H7 -> 0 | I15: =+'Budget Phytos'!I7 -> 0 | ... M15: =+'Budget Phytos'!M7 -> 0 | N15: =SUM(B15:M15) -> 0 | O15: 582668.22 | P15: =+N15-O15 -> -582668.22 | Q15: =+P15/O15 -> -1 | R15: =+'Budget Phytos'!N7 -> 0 | S15: =+N15-R15 -> 0
A16: Consommation Insectes | B16: =+'Budget Ruches'!B7 -> 0 | C16: =+'Budget Ruches'!C7 -> 0 | D16: =+'Budget Ruches'!D7 -> 0 | E16: =+'Budget Ruches'!E7 -> 0 | F16: =+'Budget Ruches'!F7 -> 0 | G16: =+'Budget Ruches'!G7 -> 0 | H16: =+'Budget Ruches'!H7 -> 0 | I16: =+'Budget Ruches'!I7 -> 0 | ... M16: =+'Budget Ruches'!M7 -> 0 | N16: =SUM(B16:M16) -> 0 | O16: 107635.05 | P16: =+N16-O16 -> -107635.05 | Q16: =+P16/O16 -> -1 | R16: =+'Budget Ruches'!N7 -> 0 | S16: =+N16-R16 -> 0
A17: Autres fournitures agricoles | B17: =+'Budget Fres Agri'!B7 -> 479534 | C17: =+'Budget Fres Agri'!C7 -> 15350 | D17: =+'Budget Fres Agri'!D7 -> 15350 | E17: =+'Budget Fres Agri'!E7 -> 15350 | F17: =+'Budget Fres Agri'!F7 -> 15350 | G17: =+'Budget Fres Agri'!G7 -> 15350 | H17: =+'Budget Fres Agri'!H7 -> 15350 | I17: =+'Budget Fres Agri'!I7 -> 15350 | ... M17: =+'Budget Fres Agri'!M7 -> 15350 | N17: =SUM(B17:M17) -> 648384 | O17: 73551.904 | P17: =+N17-O17 -> 574832.1 | Q17: =+P17/O17 -> 7.8153258 | R17: =+'Budget Fres Agri'!N7 -> 648384 | S17: =+N17-R17 -> 0
A18: Total consommation Intrants | B18: =SUM(B12:B17) -> 479534 | C18: =SUM(C12:C17) -> 2622950 | D18: =SUM(D12:D17) -> 15350 | E18: =SUM(E12:E17) -> 15350 | F18: =SUM(F12:F17) -> 15350 | G18: =SUM(G12:G17) -> 15350 | H18: =SUM(H12:H17) -> 15350 | I18: =SUM(I12:I17) -> 15350 | ... M18: =SUM(M12:M17) -> 15350 | N18: =SUM(B18:M18) -> 3255984 | O18: =SUM(O12:O17) -> 1758662.4 | P18: =+N18-O18 -> 1497321.6 | Q18: =+P18/O18 -> 0.85139802 | R18: =+'Budget Semences'!N7+'Budget Plants'!N7+'Budget Engrais'!N7+'Budget Phytos'!N7+'Budget Ruches'!N7+'Budget Fres Agri'!N7 -> 3255984 | S18: =+N18-R18 -> 0
A19: Electricité | B19: =+'Budget Energie'!B15+'Budget Energie'!B22 -> 0 | C19: =+'Budget Energie'!C15+'Budget Energie'!C22 -> 0 | D19: =+'Budget Energie'!D15+'Budget Energie'!D22 -> 0 | E19: =+'Budget Energie'!E15+'Budget Energie'!E22 -> 0 | F19: =+'Budget Energie'!F15+'Budget Energie'!F22 -> 0 | G19: =+'Budget Energie'!G15+'Budget Energie'!G22 -> 0 | H19: =+'Budget Energie'!H15+'Budget Energie'!H22 -> 0 | I19: =+'Budget Energie'!I15+'Budget Energie'!I22 -> 0 | ... M19: =+'Budget Energie'!M15+'Budget Energie'!M22 -> 0 | N19: =SUM(B19:M19) -> 0 | O19: 91727.417 | P19: =+N19-O19 -> -91727.417 | Q19: =+P19/O19 -> -1 | R19: =+'Budget Energie'!N15+'Budget Energie'!N22 -> 0 | S19: =+N19-R19 -> 0
A20: Eau | B20: =+'Budget Energie'!B13+'Budget Energie'!B20 -> 0 | C20: =+'Budget Energie'!C13+'Budget Energie'!C20 -> 0 | D20: =+'Budget Energie'!D13+'Budget Energie'!D20 -> 0 | E20: =+'Budget Energie'!E13+'Budget Energie'!E20 -> 0 | F20: =+'Budget Energie'!F13+'Budget Energie'!F20 -> 0 | G20: =+'Budget Energie'!G13+'Budget Energie'!G20 -> 0 | H20: =+'Budget Energie'!H13+'Budget Energie'!H20 -> 0 | I20: =+'Budget Energie'!I13+'Budget Energie'!I20 -> 0 | ... M20: =+'Budget Energie'!M13+'Budget Energie'!M20 -> 0 | N20: =SUM(B20:M20) -> 0 | O20: 20637.641 | P20: =+N20-O20 -> -20637.641 | Q20: =+P20/O20 -> -1 | R20: =+'Budget Energie'!N13+'Budget Energie'!N20 -> 0 | S20: =+N20-R20 -> 0
A21: Total consommation Energie | B21: =SUM(B19:B20) -> 0 | C21: =SUM(C19:C20) -> 0 | D21: =SUM(D19:D20) -> 0 | E21: =SUM(E19:E20) -> 0 | F21: =SUM(F19:F20) -> 0 | G21: =SUM(G19:G20) -> 0 | H21: =SUM(H19:H20) -> 0 | I21: =SUM(I19:I20) -> 0 | ... M21: =SUM(M19:M20) -> 0 | N21: =SUM(B21:M21) -> 0 | O21: =+O20+O19 -> 112365.06 | P21: =+N21-O21 -> -112365.06 | Q21: =+P21/O21 -> -1 | R21: =+'Budget Energie'!N7 -> 0 | S21: =+N21-R21 -> 0
A22: Prestations & analyses | B22: =+'Budget Ent & Analyses'!B14+'Budget Commun'!B19+'Budget Ent & Analyses'!B22 -> 0 | C22: =+'Budget Ent & Analyses'!C14+'Budget Commun'!C19+'Budget Ent & Analyses'!C22 -> 61400 | D22: =+'Budget Ent & Analyses'!D14+'Budget Commun'!D19+'Budget Ent & Analyses'!D22 -> 0 | E22: =+'Budget Ent & Analyses'!E14+'Budget Commun'!E19+'Budget Ent & Analyses'!E22 -> 0 | F22: =+'Budget Ent & Analyses'!F14+'Budget Commun'!F19+'Budget Ent & Analyses'!F22 -> 0 | G22: =+'Budget Ent & Analyses'!G14+'Budget Commun'!G19+'Budget Ent & Analyses'!G22 -> 0 | H22: =+'Budget Ent & Analyses'!H14+'Budget Commun'!H19+'Budget Ent & Analyses'!H22 -> 0 | I22: =+'Budget Ent & Analyses'!I14+'Budget Commun'!I19+'Budget Ent & Analyses'!I22 -> 0 | ... M22: =+'Budget Ent & Analyses'!M14+'Budget Commun'!M19+'Budget Ent & Analyses'!M22 -> 0 | N22: =SUM(B22:M22) -> 61400 | O22: 43594.909 | P22: =+N22-O22 -> 17805.091 | Q22: =+P22/O22 -> 0.40842133 | R22: =+'Budget Ent & Analyses'!N14+'Budget Commun'!N19+'Budget Ent & Analyses'!N22 -> 61400 | S22: =+N22-R22 -> 0
A23: Loyers fermes | B23: =+'Budget Loyers Fermes'!B7 -> 37622.549 | C23: =+'Budget Loyers Fermes'!C7 -> 37622.549 | D23: =+'Budget Loyers Fermes'!D7 -> 37622.549 | E23: =+'Budget Loyers Fermes'!E7 -> 37622.549 | F23: =+'Budget Loyers Fermes'!F7 -> 37622.549 | G23: =+'Budget Loyers Fermes'!G7 -> 37622.549 | H23: =+'Budget Loyers Fermes'!H7 -> 37622.549 | I23: =+'Budget Loyers Fermes'!I7 -> 37622.549 | ... M23: =+'Budget Loyers Fermes'!M7 -> 37622.549 | N23: =SUM(B23:M23) -> 451470.59 | O23: 191666.67 | P23: =+N23-O23 -> 259803.92 | Q23: =+P23/O23 -> 1.3554987 | R23: =+'Budget Loyers Fermes'!N7 -> 451470.59 | S23: =+N23-R23 -> 0
A24: Entretien | B24: =+'Budget Ent & Analyses'!B7-'Budget Ent & Analyses'!B14-'Budget Ent & Analyses'!B22+'Budget Commun'!B27 -> 10295.303 | C24: =+'Budget Ent & Analyses'!C7-'Budget Ent & Analyses'!C14-'Budget Ent & Analyses'!C22+'Budget Commun'!C27 -> 14132.803 | D24: =+'Budget Ent & Analyses'!D7-'Budget Ent & Analyses'!D14-'Budget Ent & Analyses'!D22+'Budget Commun'!D27 -> 14132.803 | E24: =+'Budget Ent & Analyses'!E7-'Budget Ent & Analyses'!E14-'Budget Ent & Analyses'!E22+'Budget Commun'!E27 -> 10295.303 | F24: =+'Budget Ent & Analyses'!F7-'Budget Ent & Analyses'!F14-'Budget Ent & Analyses'!F22+'Budget Commun'!F27 -> 10295.303 | G24: =+'Budget Ent & Analyses'!G7-'Budget Ent & Analyses'!G14-'Budget Ent & Analyses'!G22+'Budget Commun'!G27 -> 14132.803 | H24: =+'Budget Ent & Analyses'!H7-'Budget Ent & Analyses'!H14-'Budget Ent & Analyses'!H22+'Budget Commun'!H27 -> 14132.803 | I24: =+'Budget Ent & Analyses'!I7-'Budget Ent & Analyses'!I14-'Budget Ent & Analyses'!I22+'Budget Commun'!I27 -> 10295.303 | ... M24: =+'Budget Ent & Analyses'!M7-'Budget Ent & Analyses'!M14-'Budget Ent & Analyses'!M22+'Budget Commun'!M27 -> 1257.8035 | N24: =SUM(B24:M24) -> 125618.64 | O24: 105442.18 | P24: =+N24-O24 -> 20176.466 | Q24: =+P24/O24 -> 0.19135101 | R24: ='Budget Ent & Analyses'!N7-'Budget Ent & Analyses'!N14-'Budget Ent & Analyses'!N22+'Budget Commun'!N27 -> 125618.64 | S24: =+N24-R24 -> 0
A25: Main d'œuvre Directe | B25: =+'Budget MOD'!B7 -> 354391.69 | C25: =+'Budget MOD'!C7 -> 309277.47 | D25: =+'Budget MOD'!D7 -> 277874.46 | E25: =+'Budget MOD'!E7 -> 277413.75 | F25: =+'Budget MOD'!F7 -> 271051.42 | G25: =+'Budget MOD'!G7 -> 261194.88 | H25: =+'Budget MOD'!H7 -> 259638.92 | I25: =+'Budget MOD'!I7 -> 259783.08 | ... M25: =+'Budget MOD'!M7 -> 6140 | N25: =SUM(B25:M25) -> 2548032.9 | O25: 1390695.8 | P25: =+N25-O25 -> 1157337.1 | Q25: =+P25/O25 -> 0.83220007 | R25: =+'Budget MOD'!N7 -> 2548032.9 | S25: =+N25-R25 -> 0
A26: Main d'œuvre Adm. | B26: =+'Budget Commun'!B54 -> 30399.538 | C26: =+'Budget Commun'!C54 -> 30399.538 | D26: =+'Budget Commun'!D54 -> 30399.538 | E26: =+'Budget Commun'!E54 -> 30399.538 | F26: =+'Budget Commun'!F54 -> 30399.538 | G26: =+'Budget Commun'!G54 -> 30399.538 | H26: =+'Budget Commun'!H54 -> 30399.538 | I26: =+'Budget Commun'!I54 -> 30399.538 | ... M26: =+'Budget Commun'!M54 -> 30399.538 | N26: =SUM(B26:M26) -> 364794.45 | O26: 319900.43 | P26: =+N26-O26 -> 44894.019 | Q26: =+P26/O26 -> 0.14033748 | R26: =+'Budget Commun'!N54 -> 364794.45 | S26: =+N26-R26 -> 0
A27: Refact. HIJOS DE FEDERICO LIS | B27: =+'Budget Commun'!B47 -> 0 | C27: =+'Budget Commun'!C47 -> 0 | D27: =+'Budget Commun'!D47 -> 0 | E27: =+'Budget Commun'!E47 -> 0 | F27: =+'Budget Commun'!F47 -> 0 | G27: =+'Budget Commun'!G47 -> 0 | H27: =+'Budget Commun'!H47 -> 0 | I27: =+'Budget Commun'!I47 -> 0 | ... M27: =+'Budget Commun'!M47 -> 0 | N27: =SUM(B27:M27) -> 0 | O27: 156940.07 | P27: =+N27-O27 -> -156940.07 | Q27: =+P27/O27 -> -1 | R27: =+'Budget Commun'!N47 -> 0 | S27: =+N27-R27 -> 0
A28: Transport | B28: =+'Budget Transp Ventes'!B7 -> 0 | C28: =+'Budget Transp Ventes'!C7 -> 0 | D28: =+'Budget Transp Ventes'!D7 -> 0 | E28: =+'Budget Transp Ventes'!E7 -> 0 | F28: =+'Budget Transp Ventes'!F7 -> 23025000 | G28: =+'Budget Transp Ventes'!G7 -> 17268750 | H28: =+'Budget Transp Ventes'!H7 -> 17268750 | I28: =+'Budget Transp Ventes'!I7 -> 23025000 | ... M28: =+'Budget Transp Ventes'!M7 -> 5756250 | N28: =SUM(B28:M28) -> 1.3239375e+08 | O28: 70540.186 | P28: =+N28-O28 -> 1.3232321e+08 | Q28: =+P28/O28 -> 1875.8557 | R28: =+'Budget Transp Ventes'!N7 -> 1.3239375e+08 | S28: =+N28-R28 -> 0
A29: Autres frais généraux | B29: =+'Budget Commun'!B43+'Budget Commun'!B34 -> 74741.04 | C29: =+'Budget Commun'!C43+'Budget Commun'!C34 -> 3753.7572 | D29: =+'Budget Commun'!D43+'Budget Commun'!D34 -> 3753.7572 | E29: =+'Budget Commun'!E43+'Budget Commun'!E34 -> 3753.7572 | F29: =+'Budget Commun'!F43+'Budget Commun'!F34 -> 3753.7572 | G29: =+'Budget Commun'!G43+'Budget Commun'!G34 -> 3753.7572 | H29: =+'Budget Commun'!H43+'Budget Commun'!H34 -> 5404.6243 | I29: =+'Budget Commun'!I43+'Budget Commun'!I34 -> 3753.7572 | ... M29: =+'Budget Commun'!M43+'Budget Commun'!M34 -> 3753.7572 | N29: =SUM(B29:M29) -> 123579.19 | O29: 79354.347 | P29: =+N29-O29 -> 44224.844 | Q29: =+P29/O29 -> 0.5573084 | R29: =+'Budget Commun'!N34+'Budget Commun'!N43 -> 123579.19 | S29: =+N29-R29 -> 0
A30: Coût de revient total | B30: =SUM(B22:B29)+B21+B18 -> 986984.12 | C30: =SUM(C22:C29)+C21+C18 -> 3079536.1 | D30: =SUM(D22:D29)+D21+D18 -> 379133.11 | E30: =SUM(E22:E29)+E21+E18 -> 374834.89 | F30: =SUM(F22:F29)+F21+F18 -> 23393473 | G30: =SUM(G22:G29)+G21+G18 -> 17631204 | H30: =SUM(H22:H29)+H21+H18 -> 17631298 | I30: =SUM(I22:I29)+I21+I18 -> 23382204 | ... M30: =SUM(M22:M29)+M21+M18 -> 5850773.6 | N30: =SUM(B30:M30) -> 1.3932463e+08 | O30: =SUM(O22:O29)+O21+O18 -> 4229162 | P30: =+N30-O30 -> 1.3509547e+08 | Q30: =+P30/O30 -> 31.943791
A31: EBITDA | B31: =B11-B30 -> #DIV/0! | C31: =C11-C30 -> #DIV/0! | D31: =D11-D30 -> #DIV/0! | E31: =E11-E30 -> #DIV/0! | F31: =F11-F30 -> #DIV/0! | G31: =G11-G30 -> #DIV/0! | H31: =H11-H30 -> #DIV/0! | I31: =I11-I30 -> #DIV/0! | ... O31: =O11-O30 -> -666635.78 | P31: =+N31-O31 -> #DIV/0! | Q31: =+P31/O31 -> #DIV/0!
A32: Amortissements | B32: =+'Budget Commun'!B14+'Budget Invest& Amort'!B9 -> 84231.686 | C32: =+'Budget Commun'!C14+'Budget Invest& Amort'!C9 -> 84231.686 | D32: =+'Budget Commun'!D14+'Budget Invest& Amort'!D9 -> 84231.686 | E32: =+'Budget Commun'!E14+'Budget Invest& Amort'!E9 -> 84231.686 | F32: =+'Budget Commun'!F14+'Budget Invest& Amort'!F9 -> 84231.686 | G32: =+'Budget Commun'!G14+'Budget Invest& Amort'!G9 -> 84231.686 | H32: =+'Budget Commun'!H14+'Budget Invest& Amort'!H9 -> 84231.686 | I32: =+'Budget Commun'!I14+'Budget Invest& Amort'!I9 -> 84231.686 | ... M32: =+'Budget Commun'!M14+'Budget Invest& Amort'!M9 -> 87247.519 | N32: =SUM(B32:M32) -> 1019827.7 | O32: 823053.01 | P32: =+N32-O32 -> 196774.71 | Q32: =+P32/O32 -> 0.23907903 | R32: =+'Budget Commun'!N14+'Budget Invest& Amort'!N9 -> 1019827.7 | S32: =+N32-R32 -> 0
A33: Résultat d'exploitation | B33: =B31-B32 -> #DIV/0! | C33: =C31-C32 -> #DIV/0! | D33: =D31-D32 -> #DIV/0! | E33: =E31-E32 -> #DIV/0! | F33: =F31-F32 -> #DIV/0! | G33: =G31-G32 -> #DIV/0! | H33: =H31-H32 -> #DIV/0! | I33: =I31-I32 -> #DIV/0! | ... O33: =O31-O32 -> -1489688.8 | P33: =+N33-O33 -> #DIV/0! | Q33: =+P33/O33 -> #DIV/0!
A34: EBITDA en % du CA | N34: =+N31/N7 -> #DIV/0! | O34: =+O31/O7 -> -0.26256939 | P34: =+N34-O34 -> #DIV/0!
A35: PMV au kg | B35: =+(B7)/B5 -> #DIV/0! | C35: =+(C7)/C5 -> #DIV/0! | D35: =+(D7)/D5 -> #DIV/0! | E35: =+(E7)/E5 -> #DIV/0! | F35: =+(F7)/F5 -> 0.01 | G35: =+(G7)/G5 -> 0.01 | H35: =+(H7)/H5 -> 0.01 | I35: =+(I7)/I5 -> 0.01 | ... O35: =+(O7)/O5 -> 2.2908751 | P35: =+N35-O35 -> -2.2808751 | Q35: =+P35/O35 -> -0.99563486
A36: CA à l'hectare prod | B36: =+B7/B4 -> 0 | C36: =+C7/C4 -> 0 | D36: =+D7/D4 -> 0 | E36: =+E7/E4 -> 0 | F36: =+F7/F4 -> 200000 | G36: =+G7/G4 -> 150000 | H36: =+H7/H4 -> 150000 | I36: =+I7/I4 -> 200000 | ... O36: =+O7/O4 -> 373366.72 | P36: =+N36-O36 -> 776633.28 | Q36: =+P36/O36 -> 2.0800817
A37: Coût à l'hectare prod (hors Amort) | B37: =+(B30-B10)/B4 -> #DIV/0! | C37: =+(C30-C10)/C4 -> #DIV/0! | D37: =+(D30-D10)/D4 -> #DIV/0! | E37: =+(E30-E10)/E4 -> #DIV/0! | F37: =+(F30-F10)/F4 -> #DIV/0! | G37: =+(G30-G10)/G4 -> #DIV/0! | H37: =+(H30-H10)/H4 -> #DIV/0! | I37: =+(I30-I10)/I4 -> #DIV/0! | ... O37: =+(O30-O10)/O4 -> 621935.58 | P37: =+N37-O37 -> #DIV/0! | Q37: =+P37/O37 -> #DIV/0!
A38: EBITDA à l'hectare prod | B38: =+B31/B4 -> #DIV/0! | C38: =+C31/C4 -> #DIV/0! | D38: =+D31/D4 -> #DIV/0! | E38: =+E31/E4 -> #DIV/0! | F38: =+F31/F4 -> #DIV/0! | G38: =+G31/G4 -> #DIV/0! | H38: =+H31/H4 -> #DIV/0! | I38: =+I31/I4 -> #DIV/0! | ... O38: =+O31/O4 -> -98034.674 | P38: =+N38-O38 -> #DIV/0! | Q38: =+P38/O38 -> #DIV/0!
A39: Coût total à l'hectare prod | B39: =+(B30+B32-B10)/B4 -> #DIV/0! | C39: =+(C30+C32-C10)/C4 -> #DIV/0! | D39: =+(D30+D32-D10)/D4 -> #DIV/0! | E39: =+(E30+E32-E10)/E4 -> #DIV/0! | F39: =+(F30+F32-F10)/F4 -> #DIV/0! | G39: =+(G30+G32-G10)/G4 -> #DIV/0! | H39: =+(H30+H32-H10)/H4 -> #DIV/0! | I39: =+(I30+I32-I10)/I4 -> #DIV/0! | ... O39: =+(O30+O32-O10)/O4 -> 742972.79 | P39: =+N39-O39 -> #DIV/0! | Q39: =+P39/O39 -> #DIV/0!
A40: REX à l'hectare prod | B40: =B33/B4 -> #DIV/0! | C40: =C33/C4 -> #DIV/0! | D40: =D33/D4 -> #DIV/0! | E40: =E33/E4 -> #DIV/0! | F40: =F33/F4 -> #DIV/0! | G40: =G33/G4 -> #DIV/0! | H40: =H33/H4 -> #DIV/0! | I40: =I33/I4 -> #DIV/0! | ... O40: =O33/O4 -> -219071.88 | P40: =+N40-O40 -> #DIV/0! | Q40: =+P40/O40 -> #DIV/0!
A41: Détail des coûts à l'hectare
A42: Coût total à l'hectare | B42: =+(B30+B32)/B3 -> 64694.758 | C42: =+(C30+C32)/C3 -> 191071.86 | D42: =+(D30+D32)/D3 -> 27984.345 | E42: =+(E30+E32)/E3 -> 27724.76 | F42: =+(F30+F32)/F3 -> 1417907 | G42: =+(G30+G32)/G3 -> 1069901.9 | H42: =+(H30+H32)/H3 -> 1069907.6 | I42: =+(I30+I32)/I3 -> 1417226.5 | ... M42: =+(M30+M32)/M3 -> 358619.47 | N42: =+(N30+N32-N10)/N3 -> #DIV/0! | O42: =+(O30+O32-O10)/O3 -> 742972.79 | P42: =+N42-O42 -> #DIV/0! | Q42: =+P42/O42 -> #DIV/0!
A43: Coût à l'hectare (hors Amort) | B43: =+B30/B3 -> 59607.689 | C43: =+C30/C3 -> 185984.79 | D43: =+D30/D3 -> 22897.277 | E43: =+E30/E3 -> 22637.691 | F43: =+F30/F3 -> 1412819.9 | G43: =+G30/G3 -> 1064814.8 | H43: =+H30/H3 -> 1064820.5 | I43: =+I30/I3 -> 1412139.4 | ... M43: =+M30/M3 -> 353350.26 | N43: =+(N30-N10)/N3 -> #DIV/0! | O43: =+(O30-O10)/O3 -> 621935.58 | P43: =+N43-O43 -> #DIV/0! | Q43: =+P43/O43 -> #DIV/0!
A44: Semences | B44: =+B12/B3 -> 0 | C44: =+C12/C3 -> 90264.525 | D44: =+D12/D3 -> 0 | E44: =+E12/E3 -> 0 | F44: =+F12/F3 -> 0 | G44: =+G12/G3 -> 0 | H44: =+H12/H3 -> 0 | I44: =+I12/I3 -> 0 | ... O44: =+O12/O3 -> 29764.706 | P44: =+N44-O44 -> 60499.819 | Q44: =+P44/O44 -> 2.0326026
A45: Engrais | B45: =+B13/B3 -> 0 | C45: =+C13/C3 -> 0 | D45: =+D13/D3 -> 0 | E45: =+E13/E3 -> 0 | F45: =+F13/F3 -> 0 | G45: =+G13/G3 -> 0 | H45: =+H13/H3 -> 0 | I45: =+I13/I3 -> 0 | ... O45: =+O13/O3 -> 79047.086 | P45: =+N45-O45 -> -79047.086 | Q45: =+P45/O45 -> -1
A46: Plants | B46: =+B14/B3 -> 0 | C46: =+C14/C3 -> 67218.263 | D46: =+D14/D3 -> 0 | E46: =+E14/E3 -> 0 | F46: =+F14/F3 -> 0 | G46: =+G14/G3 -> 0 | H46: =+H14/H3 -> 0 | I46: =+I14/I3 -> 0 | ... O46: =+O14/O3 -> 37483.382 | P46: =+N46-O46 -> 29734.881 | Q46: =+P46/O46 -> 0.79328169
A47: Phytos | B47: =+B15/B3 -> 0 | C47: =+C15/C3 -> 0 | D47: =+D15/D3 -> 0 | E47: =+E15/E3 -> 0 | F47: =+F15/F3 -> 0 | G47: =+G15/G3 -> 0 | H47: =+H15/H3 -> 0 | I47: =+I15/I3 -> 0 | ... O47: =+O15/O3 -> 85686.503 | P47: =+N47-O47 -> -85686.503 | Q47: =+P47/O47 -> -1
A48: Insectes | B48: =+B16/B3 -> 0 | C48: =+C16/C3 -> 0 | D48: =+D16/D3 -> 0 | E48: =+E16/E3 -> 0 | F48: =+F16/F3 -> 0 | G48: =+G16/G3 -> 0 | H48: =+H16/H3 -> 0 | I48: =+I16/I3 -> 0 | ... O48: =+O16/O3 -> 15828.683 | P48: =+N48-O48 -> -15828.683 | Q48: =+P48/O48 -> -1
A49: Autres fournitures agricoles | B49: =+B17/B3 -> 28960.865 | C49: =+C17/C3 -> 927.04433 | D49: =+D17/D3 -> 927.04433 | E49: =+E17/E3 -> 927.04433 | F49: =+F17/F3 -> 927.04433 | G49: =+G17/G3 -> 927.04433 | H49: =+H17/H3 -> 927.04433 | I49: =+I17/I3 -> 927.04433 | ... O49: =+O17/O3 -> 10816.456 | P49: =+N49-O49 -> 28341.896 | Q49: =+P49/O49 -> 2.620257
A50: Electricité | B50: =+B19/B3 -> 0 | C50: =+C19/C3 -> 0 | D50: =+D19/D3 -> 0 | E50: =+E19/E3 -> 0 | F50: =+F19/F3 -> 0 | G50: =+G19/G3 -> 0 | H50: =+H19/H3 -> 0 | I50: =+I19/I3 -> 0 | ... O50: =+O19/O3 -> 13489.326 | P50: =+N50-O50 -> -13489.326 | Q50: =+P50/O50 -> -1
A51: Eau | B51: =+B20/B3 -> 0 | C51: =+C20/C3 -> 0 | D51: =+D20/D3 -> 0 | E51: =+E20/E3 -> 0 | F51: =+F20/F3 -> 0 | G51: =+G20/G3 -> 0 | H51: =+H20/H3 -> 0 | I51: =+I20/I3 -> 0 | ... O51: =+O20/O3 -> 3034.9473 | P51: =+N51-O51 -> -3034.9473 | Q51: =+P51/O51 -> -1
A52: Prestations & analyses | B52: =+B22/B3 -> 0 | C52: =+C22/C3 -> 3708.1773 | D52: =+D22/D3 -> 0 | E52: =+E22/E3 -> 0 | F52: =+F22/F3 -> 0 | G52: =+G22/G3 -> 0 | H52: =+H22/H3 -> 0 | I52: =+I22/I3 -> 0 | ... O52: =+O22/O3 -> 6411.0161 | P52: =+N52-O52 -> -2702.8388 | Q52: =+P52/O52 -> -0.42159288
A53: Loyers fermes | B53: =+B23/B3 -> 2272.1675 | C53: =+C23/C3 -> 2272.1675 | D53: =+D23/D3 -> 2272.1675 | E53: =+E23/E3 -> 2272.1675 | F53: =+F23/F3 -> 2272.1675 | G53: =+G23/G3 -> 2272.1675 | H53: =+H23/H3 -> 2272.1675 | I53: =+I23/I3 -> 2272.1675 | ... O53: =+O23/O3 -> 28186.275 | P53: =+N53-O53 -> -920.26483 | Q53: =+P53/O53 -> -0.032649396
A54: Entretien | B54: =+B24/B3 -> 621.77216 | C54: =+C24/C3 -> 853.53324 | D54: =+D24/D3 -> 853.53324 | E54: =+E24/E3 -> 621.77216 | F54: =+F24/F3 -> 621.77216 | G54: =+G24/G3 -> 853.53324 | H54: =+H24/H3 -> 853.53324 | I54: =+I24/I3 -> 621.77216 | ... O54: =+O24/O3 -> 15506.202 | P54: =+N54-O54 -> -7919.6192 | Q54: =+P54/O54 -> -0.51073881
A55: Main d'œuvre Directe | B55: =+B25/B3 -> 21403.049 | C55: =+C25/C3 -> 18678.432 | D55: =+D25/D3 -> 16781.885 | E55: =+E25/E3 -> 16754.061 | F55: =+F25/F3 -> 16369.816 | G55: =+G25/G3 -> 15774.543 | H55: =+H25/H3 -> 15680.573 | I55: =+I25/I3 -> 15689.279 | ... O55: =+O25/O3 -> 204514.08 | P55: =+N55-O55 -> -50628.778 | Q55: =+P55/O55 -> -0.24755644
A56: Main d'œuvre Adm. | B56: =+B26/B3 -> 1835.9426 | C56: =+C26/C3 -> 1835.9426 | D56: =+D26/D3 -> 1835.9426 | E56: =+E26/E3 -> 1835.9426 | F56: =+F26/F3 -> 1835.9426 | G56: =+G26/G3 -> 1835.9426 | H56: =+H26/H3 -> 1835.9426 | I56: =+I26/I3 -> 1835.9426 | ... O56: =+O26/O3 -> 47044.181 | P56: =+N56-O56 -> -25012.87 | Q56: =+P56/O56 -> -0.53168892
A57: Refact. HIJOS DE FEDERICO LIS | B57: =+B27/B3 -> 0 | C57: =+C27/C3 -> 0 | D57: =+D27/D3 -> 0 | E57: =+E27/E3 -> 0 | F57: =+F27/F3 -> 0 | G57: =+G27/G3 -> 0 | H57: =+H27/H3 -> 0 | I57: =+I27/I3 -> 0 | ... O57: =+O27/O3 -> 23079.422 | P57: =+N57-O57 -> -23079.422 | Q57: =+P57/O57 -> -1
A58: Transport | B58: =+B28/B3 -> 0 | C58: =+C28/C3 -> 0 | D58: =+D28/D3 -> 0 | E58: =+E28/E3 -> 0 | F58: =+F28/F3 -> 1390566.5 | G58: =+G28/G3 -> 1042924.9 | H58: =+H28/H3 -> 1042924.9 | I58: =+I28/I3 -> 1390566.5 | ... O58: =+O28/O3 -> 10373.557 | P58: =+N58-O58 -> 7985383.8 | Q58: =+P58/O58 -> 769.78263
A59: Autres frais généraux | B59: =+B29/B3 -> 4513.893 | C59: =+C29/C3 -> 226.70354 | D59: =+D29/D3 -> 226.70354 | E59: =+E29/E3 -> 226.70354 | F59: =+F29/F3 -> 226.70354 | G59: =+G29/G3 -> 226.70354 | H59: =+H29/H3 -> 326.40562 | I59: =+I29/I3 -> 226.70354 | ... O59: =+O29/O3 -> 11669.757 | P59: =+N59-O59 -> -4206.3439 | Q59: =+P59/O59 -> -0.36044829
A60: Amortissements | B60: =+B32/B3 -> 5087.0688 | C60: =+C32/C3 -> 5087.0688 | D60: =+D32/D3 -> 5087.0688 | E60: =+E32/E3 -> 5087.0688 | F60: =+F32/F3 -> 5087.0688 | G60: =+G32/G3 -> 5087.0688 | H60: =+H32/H3 -> 5087.0688 | I60: =+I32/I3 -> 5087.0688 | ... O60: =+O32/O3 -> 121037.21 | P60: =+N60-O60 -> -59445.97 | Q60: =+P60/O60 -> -0.49113798
A61: Calcul des encours
A62: Encours initial | D62: =SUM(B68:D84) -> #DIV/0!
A63: Coût des encours | D63: =+D62/('Budget Volumes Export'!N16*1000) -> #DIV/0! | E63: =+D63 -> #DIV/0! | F63: =+E63 -> #DIV/0! | G63: =+F63 -> #DIV/0! | H63: =+G63 -> #DIV/0! | I63: =+H63 -> #DIV/0! | J63: =+I63 -> #DIV/0! | K63: =+J63 -> #DIV/0! | L63: =+K63 -> #DIV/0! | M63: =+L63 -> #DIV/0!
A64: Coût des ventes | E64: =+E63*'Budget Volumes Export'!E16*1000 -> #DIV/0! | F64: =+F63*'Budget Volumes Export'!F16*1000 -> #DIV/0! | G64: =+G63*'Budget Volumes Export'!G16*1000 -> #DIV/0! | H64: =+H63*'Budget Volumes Export'!H16*1000 -> #DIV/0! | I64: =+I63*'Budget Volumes Export'!I16*1000 -> #DIV/0! | J64: =+J63*'Budget Volumes Export'!J16*1000 -> #DIV/0! | K64: =+K63*'Budget Volumes Export'!K16*1000 -> #DIV/0! | L64: =+L63*'Budget Volumes Export'!L16*1000 -> #DIV/0! | M64: =+M63*'Budget Volumes Export'!M16*1000 -> #DIV/0!
A65: Encours fin de période | E65: =+D62-E64 -> #DIV/0! | F65: =+E65-F64 -> #DIV/0! | G65: =+F65-G64 -> #DIV/0! | H65: =+G65-H64 -> #DIV/0! | I65: =+H65-I64 -> #DIV/0! | J65: =+I65-J64 -> #DIV/0! | K65: =+J65-K64 -> #DIV/0! | L65: =+K65-L64 -> #DIV/0! | M65: =+L65-M64 -> #DIV/0!
A66: Variation encours | E66: =+E65-D62 -> #DIV/0! | F66: =+F65-E65 -> #DIV/0! | G66: =+G65-F65 -> #DIV/0! | H66: =+H65-G65 -> #DIV/0! | I66: =+I65-H65 -> #DIV/0! | J66: =+J65-I65 -> #DIV/0! | K66: =+K65-J65 -> #DIV/0! | L66: =+L65-K65 -> #DIV/0! | M66: =+M65-L65 -> #DIV/0!
A67: Calcul encours initial culture hiver
A68: Semences | B68: =B12 -> 0 | C68: =C12 -> 1494600 | D68: =D12 -> 0
A69: Plants | B69: =B14 -> 0 | C69: =C14 -> 1113000 | D69: =D14 -> 0
A70: Fournitures agricoles | B70: =B17 -> 479534 | C70: =C17 -> 15350 | D70: =D17 -> 15350
A71: Engrais | B71: =B13*('Plan de culture 104 '!$X$13/'Plan de culture 104 '!$B$3) -> #DIV/0! | C71: =C13*('Plan de culture 104 '!$X$13/'Plan de culture 104 '!$B$3) -> #DIV/0! | D71: =D13*('Plan de culture 104 '!$X$13/'Plan de culture 104 '!$B$3) -> #DIV/0!
A72: Phytos | B72: =B15*('Plan de culture 104 '!$X$13/'Plan de culture 104 '!$B$3) -> #DIV/0! | C72: =C15*('Plan de culture 104 '!$X$13/'Plan de culture 104 '!$B$3) -> #DIV/0! | D72: =D15*('Plan de culture 104 '!$X$13/'Plan de culture 104 '!$B$3) -> #DIV/0!
A73: Insectes | B73: =B16*('Plan de culture 104 '!$X$13/'Plan de culture 104 '!$B$3) -> #DIV/0! | C73: =C16*('Plan de culture 104 '!$X$13/'Plan de culture 104 '!$B$3) -> #DIV/0! | D73: =D16*('Plan de culture 104 '!$X$13/'Plan de culture 104 '!$B$3) -> #DIV/0!
A74: Energie | B74: =B21*('Plan de culture 104 '!$X$13/'Plan de culture 104 '!$B$3) -> #DIV/0! | C74: =C21*('Plan de culture 104 '!$X$13/'Plan de culture 104 '!$B$3) -> #DIV/0! | D74: =D21*('Plan de culture 104 '!$X$13/'Plan de culture 104 '!$B$3) -> #DIV/0!
A75: Prestations & analyses | B75: =B22*('Plan de culture 104 '!$X$13/'Plan de culture 104 '!$B$3) -> #DIV/0! | C75: =C22*('Plan de culture 104 '!$X$13/'Plan de culture 104 '!$B$3) -> #DIV/0! | D75: =D22*('Plan de culture 104 '!$X$13/'Plan de culture 104 '!$B$3) -> #DIV/0!
A76: Loyers fermes | B76: =B23*('Plan de culture 104 '!$X$13/'Plan de culture 104 '!$B$3) -> #DIV/0! | C76: =C23*('Plan de culture 104 '!$X$13/'Plan de culture 104 '!$B$3) -> #DIV/0! | D76: =D23*('Plan de culture 104 '!$X$13/'Plan de culture 104 '!$B$3) -> #DIV/0!
A77: Entretien | B77: =B24*('Plan de culture 104 '!$X$13/'Plan de culture 104 '!$B$3) -> #DIV/0! | C77: =C24*('Plan de culture 104 '!$X$13/'Plan de culture 104 '!$B$3) -> #DIV/0! | D77: =D24*('Plan de culture 104 '!$X$13/'Plan de culture 104 '!$B$3) -> #DIV/0!
A78: Main d'œuvre Directe | B78: =B25*('Plan de culture 104 '!$X$13/'Plan de culture 104 '!$B$3) -> #DIV/0! | C78: =C25*('Plan de culture 104 '!$X$13/'Plan de culture 104 '!$B$3) -> #DIV/0! | D78: =D25*('Plan de culture 104 '!$X$13/'Plan de culture 104 '!$B$3) -> #DIV/0!
A79: Main d'œuvre Adm. | B79: =B26*('Plan de culture 104 '!$X$13/'Plan de culture 104 '!$B$3) -> #DIV/0! | C79: =C26*('Plan de culture 104 '!$X$13/'Plan de culture 104 '!$B$3) -> #DIV/0! | D79: =D26*('Plan de culture 104 '!$X$13/'Plan de culture 104 '!$B$3) -> #DIV/0!
A80: Refact. HIJOS DE FEDERICO LIS | B80: =B27*('Plan de culture 104 '!$X$13/'Plan de culture 104 '!$B$3) -> #DIV/0! | C80: =C27*('Plan de culture 104 '!$X$13/'Plan de culture 104 '!$B$3) -> #DIV/0! | D80: =D27*('Plan de culture 104 '!$X$13/'Plan de culture 104 '!$B$3) -> #DIV/0!
A81: Autres frais généraux | B81: =B29*('Plan de culture 104 '!$X$13/'Plan de culture 104 '!$B$3) -> #DIV/0! | C81: =C29*('Plan de culture 104 '!$X$13/'Plan de culture 104 '!$B$3) -> #DIV/0! | D81: =D29*('Plan de culture 104 '!$X$13/'Plan de culture 104 '!$B$3) -> #DIV/0!
A82: Amortissements | B82: =B32*('Plan de culture 104 '!$X$13/'Plan de culture 104 '!$B$3) -> #DIV/0! | C82: =C32*('Plan de culture 104 '!$X$13/'Plan de culture 104 '!$B$3) -> #DIV/0! | D82: =D32*('Plan de culture 104 '!$X$13/'Plan de culture 104 '!$B$3) -> #DIV/0!

Sheet 114_Synthèse
B1: BUD | C1: BUD | D1: BUD | E1: BUD | F1: BUD | G1: BUD | H1: BUD | I1: BUD | J1: BUD | K1: BUD | L1: BUD | M1: BUD | N1: BUD | O1: REEL | P1: VARIATION | Q1: VARIATION
A2: 114 - Analyse totale (MAD) | B2: 43647 | C2: =+B2+31 -> 43678 | D2: =+C2+31 -> 43709 | E2: =+D2+31 -> 43740 | F2: =+E2+31 -> 43771 | G2: =+F2+31 -> 43802 | H2: =+G2+31 -> 43833 | I2: =+H2+31 -> 43864 | J2: =+I2+31 -> 43895 | ... M2: =+L2+31 -> 43988 | N2: 19/20 | O2: 18/19 | P2: BUD-REEL | Q2: % | R2: source | S2: check
A3: Sup Tot (ha) | B3: =+'Plan de culture 104 '!$B$3 -> 0 | C3: =+'Plan de culture 104 '!$B$3 -> 0 | D3: =+'Plan de culture 104 '!$B$3 -> 0 | E3: =+'Plan de culture 104 '!$B$3 -> 0 | F3: =+'Plan de culture 104 '!$B$3 -> 0 | G3: =+'Plan de culture 104 '!$B$3 -> 0 | H3: =+'Plan de culture 104 '!$B$3 -> 0 | I3: =+'Plan de culture 104 '!$B$3 -> 0 | ... N3: =+'Plan de culture 104 '!$B$3 -> 0 | O3: 6.8 | P3: =+N3-O3 -> -6.8 | Q3: =+P3/O3 -> -1 | R3: =+'Plan de culture 104 '!$B$3 -> 0 | S3: =+N3-R3 -> 0
A4: Sup productive | B4: =+'Budget Volumes Export'!B8 -> 15.35 | C4: =+'Budget Volumes Export'!C8 -> 15.35 | D4: =+'Budget Volumes Export'!D8 -> 15.35 | E4: =+'Budget Volumes Export'!E8 -> 15.35 | F4: =+'Budget Volumes Export'!F8 -> 15.35 | G4: =+'Budget Volumes Export'!G8 -> 15.35 | H4: =+'Budget Volumes Export'!H8 -> 15.35 | I4: =+'Budget Volumes Export'!I8 -> 15.35 | ... N4: =+'Budget Volumes Export'!N8 -> 15.35 | O4: 6.8 | P4: =+N4-O4 -> 8.55 | Q4: =+P4/O4 -> 1.2573529 | R4: =+'Budget Volumes Export'!N8 -> 15.35 | S4: =+N4-R4 -> 0
A5: Vol (kg) | B5: =+'Budget Volumes Export'!B7*1000 -> 0 | C5: =+'Budget Volumes Export'!C7*1000 -> 0 | D5: =+'Budget Volumes Export'!D7*1000 -> 0 | E5: =+'Budget Volumes Export'!E7*1000 -> 0 | F5: =+'Budget Volumes Export'!F7*1000 -> 3.07e+08 | G5: =+'Budget Volumes Export'!G7*1000 -> 2.3025e+08 | H5: =+'Budget Volumes Export'!H7*1000 -> 2.3025e+08 | I5: =+'Budget Volumes Export'!I7*1000 -> 3.07e+08 | ... M5: =+'Budget Volumes Export'!M7*1000 -> 76750000 | N5: =SUM(B5:M5) -> 1.76525e+09 | O5: 1108263.7 | P5: =+N5-O5 -> 1.7641417e+09 | Q5: =+P5/O5 -> 1591.8069 | R5: =+'Budget Volumes Export'!N7*1000 -> 1.76525e+09 | S5: =+N5-R5 -> 0
A6: rendement (t/ha) | B6: =+B5/B4/1000 -> 0 | C6: =+C5/C4/1000 -> 0 | D6: =+D5/D4/1000 -> 0 | E6: =+E5/E4/1000 -> 0 | F6: =+F5/F4/1000 -> 20000 | G6: =+G5/G4/1000 -> 15000 | H6: =+H5/H4/1000 -> 15000 | I6: =+I5/I4/1000 -> 20000 | ... O6: =+O5/O4/1000 -> 162.97995 | P6: =+N6-O6 -> 114837.02 | Q6: =+P6/O6 -> 704.60825 | R6: =+R5/R4/1000 -> 115000 | S6: =+N6-R6 -> 0
A7: CA EXPORT(MAD) | B7: =+'Budget Commercial Export'!B7 -> 0 | C7: =+'Budget Commercial Export'!C7 -> 0 | D7: =+'Budget Commercial Export'!D7 -> 0 | E7: =+'Budget Commercial Export'!E7 -> 0 | F7: =+'Budget Commercial Export'!F7 -> 3070000 | G7: =+'Budget Commercial Export'!G7 -> 2302500 | H7: =+'Budget Commercial Export'!H7 -> 2302500 | I7: =+'Budget Commercial Export'!I7 -> 3070000 | ... M7: =+'Budget Commercial Export'!M7 -> 767500 | N7: =SUM(B7:M7) -> 17652500 | O7: 2538893.7 | P7: =+N7-O7 -> 15113606 | Q7: =+P7/O7 -> 5.9528315 | R7: =+'Budget Commercial Export'!N7 -> 17652500 | S7: =+N7-R7 -> 0
A8: CA MARCHE LOCAL
A9: Autres revenus (MAD) | N9: =SUM(B9:M9) -> 0 | O9: 1023632.5 | P9: =+N9-O9 -> -1023632.5 | Q9: =+P9/O9 -> -1
A10: Production encours (MAD) | B10: =SUM(B67:B81) -> #DIV/0! | C10: =SUM(C67:C81) -> #DIV/0! | D10: =SUM(D67:D81) -> #DIV/0! | E10: =+E65 -> #DIV/0! | F10: =+F65 -> #DIV/0! | G10: =+G65 -> #DIV/0! | H10: =+H65 -> #DIV/0! | I10: =+I65 -> #DIV/0! | J10: =+J65 -> #DIV/0! | K10: =+K65 -> #DIV/0! | L10: =+L65 -> #DIV/0! | M10: =+M65 -> #DIV/0! | N10: =SUM(B10:M10) -> #DIV/0! | O10: 0 | P10: =+N10-O10 -> #DIV/0! | Q10: =+P10/O10 -> #DIV/0! | R10: 0 | S10: =+N10-R10 -> #DIV/0!
A11: Production totale (MAD) | B11: =+B10+B7+B9 -> #DIV/0! | C11: =+C10+C7+C9 -> #DIV/0! | D11: =+D10+D7+D9 -> #DIV/0! | E11: =+E10+E7+E9 -> #DIV/0! | F11: =+F10+F7+F9 -> #DIV/0! | G11: =+G10+G7+G9 -> #DIV/0! | H11: =+H10+H7+H9 -> #DIV/0! | I11: =+I10+I7+I9 -> #DIV/0! | ... M11: =+M10+M7+M9 -> #DIV/0! | N11: =SUM(B11:M11) -> #DIV/0! | O11: =+O10+O7+O9 -> 3562526.2 | P11: =+N11-O11 -> #DIV/0! | Q11: =+P11/O11 -> #DIV/0!
A12: Consommation Semences | B12: =+'Budget Semences'!B7 -> 0 | C12: =+'Budget Semences'!C10 -> 1494600 | D12: =+'Budget Semences'!D10 -> 0 | E12: =+'Budget Semences'!E10 -> 0 | F12: =+'Budget Semences'!F10 -> 0 | G12: =+'Budget Semences'!G10 -> 0 | H12: =+'Budget Semences'!H10 -> 0 | I12: =+'Budget Semences'!I10 -> 0 | J12: =+'Budget Semences'!J10 -> 0 | ... M12: =+'Budget Semences'!M10 -> 0 | N12: =SUM(B12:M12) -> 1494600 | O12: 202400 | P12: =+N12-O12 -> 1292200 | Q12: =+P12/O12 -> 6.3843874 | R12: =+'Budget Semences'!N7 -> 1494600 | S12: =+N12-R12 -> 0
A13: Consommation Engrais | B13: =+'Budget Engrais'!B7 -> 0 | C13: =+'Budget Engrais'!C7 -> 0 | D13: =+'Budget Engrais'!D7 -> 0 | E13: =+'Budget Engrais'!E7 -> 0 | F13: =+'Budget Engrais'!F7 -> 0 | G13: =+'Budget Engrais'!G7 -> 0 | H13: =+'Budget Engrais'!H7 -> 0 | I13: =+'Budget Engrais'!I7 -> 0 | ... M13: =+'Budget Engrais'!M7 -> 0 | N13: =SUM(B13:M13) -> 0 | O13: 537520.18 | P13: =+N13-O13 -> -537520.18 | Q13: =+P13/O13 -> -1 | R13: =+'Budget Engrais'!N7 -> 0 | S13: =+N13-R13 -> 0
A14: Consommation Plants | B14: =+'Budget Plants'!B7 -> 0 | C14: =+'Budget Plants'!C7 -> 1113000 | D14: =+'Budget Plants'!D7 -> 0 | E14: =+'Budget Plants'!E7 -> 0 | F14: =+'Budget Plants'!F7 -> 0 | G14: =+'Budget Plants'!G7 -> 0 | H14: =+'Budget Plants'!H7 -> 0 | I14: =+'Budget Plants'!I7 -> 0 | ... M14: =+'Budget Plants'!M7 -> 0 | N14: =SUM(B14:M14) -> 1113000 | O14: 254887 | P14: =+N14-O14 -> 858113 | Q14: =+P14/O14 -> 3.3666409 | R14: =+'Budget Plants'!N7 -> 1113000 | S14: =+N14-R14 -> 0
A15: Consommation Phytos | B15: =+'Budget Phytos'!B7 -> 0 | C15: =+'Budget Phytos'!C7 -> 0 | D15: =+'Budget Phytos'!D7 -> 0 | E15: =+'Budget Phytos'!E7 -> 0 | F15: =+'Budget Phytos'!F7 -> 0 | G15: =+'Budget Phytos'!G7 -> 0 | H15: =+'Budget Phytos'!H7 -> 0 | I15: =+'Budget Phytos'!I7 -> 0 | ... M15: =+'Budget Phytos'!M7 -> 0 | N15: =SUM(B15:M15) -> 0 | O15: 582668.22 | P15: =+N15-O15 -> -582668.22 | Q15: =+P15/O15 -> -1 | R15: =+'Budget Phytos'!N7 -> 0 | S15: =+N15-R15 -> 0
A16: Consommation Insectes | B16: =+'Budget Ruches'!B7 -> 0 | C16: =+'Budget Ruches'!C7 -> 0 | D16: =+'Budget Ruches'!D7 -> 0 | E16: =+'Budget Ruches'!E7 -> 0 | F16: =+'Budget Ruches'!F7 -> 0 | G16: =+'Budget Ruches'!G7 -> 0 | H16: =+'Budget Ruches'!H7 -> 0 | I16: =+'Budget Ruches'!I7 -> 0 | ... M16: =+'Budget Ruches'!M7 -> 0 | N16: =SUM(B16:M16) -> 0 | O16: 107635.05 | P16: =+N16-O16 -> -107635.05 | Q16: =+P16/O16 -> -1 | R16: =+'Budget Ruches'!N7 -> 0 | S16: =+N16-R16 -> 0
A17: Autres fournitures agricoles | B17: =+'Budget Fres Agri'!B7 -> 479534 | C17: =+'Budget Fres Agri'!C7 -> 15350 | D17: =+'Budget Fres Agri'!D7 -> 15350 | E17: =+'Budget Fres Agri'!E7 -> 15350 | F17: =+'Budget Fres Agri'!F7 -> 15350 | G17: =+'Budget Fres Agri'!G7 -> 15350 | H17: =+'Budget Fres Agri'!H7 -> 15350 | I17: =+'Budget Fres Agri'!I7 -> 15350 | ... M17: =+'Budget Fres Agri'!M7 -> 15350 | N17: =SUM(B17:M17) -> 648384 | O17: 73551.904 | P17: =+N17-O17 -> 574832.1 | Q17: =+P17/O17 -> 7.8153258 | R17: =+'Budget Fres Agri'!N7 -> 648384 | S17: =+N17-R17 -> 0
A18: Total consommation Intrants | B18: =SUM(B12:B17) -> 479534 | C18: =SUM(C12:C17) -> 2622950 | D18: =SUM(D12:D17) -> 15350 | E18: =SUM(E12:E17) -> 15350 | F18: =SUM(F12:F17) -> 15350 | G18: =SUM(G12:G17) -> 15350 | H18: =SUM(H12:H17) -> 15350 | I18: =SUM(I12:I17) -> 15350 | ... M18: =SUM(M12:M17) -> 15350 | N18: =SUM(B18:M18) -> 3255984 | O18: =SUM(O12:O17) -> 1758662.4 | P18: =+N18-O18 -> 1497321.6 | Q18: =+P18/O18 -> 0.85139802 | R18: =+'Budget Semences'!N7+'Budget Plants'!N7+'Budget Engrais'!N7+'Budget Phytos'!N7+'Budget Ruches'!N7+'Budget Fres Agri'!N7 -> 3255984 | S18: =+N18-R18 -> 0
A19: Electricité | B19: =+'Budget Energie'!B15+'Budget Energie'!B22 -> 0 | C19: =+'Budget Energie'!C15+'Budget Energie'!C22 -> 0 | D19: =+'Budget Energie'!D15+'Budget Energie'!D22 -> 0 | E19: =+'Budget Energie'!E15+'Budget Energie'!E22 -> 0 | F19: =+'Budget Energie'!F15+'Budget Energie'!F22 -> 0 | G19: =+'Budget Energie'!G15+'Budget Energie'!G22 -> 0 | H19: =+'Budget Energie'!H15+'Budget Energie'!H22 -> 0 | I19: =+'Budget Energie'!I15+'Budget Energie'!I22 -> 0 | ... M19: =+'Budget Energie'!M15+'Budget Energie'!M22 -> 0 | N19: =SUM(B19:M19) -> 0 | O19: 91727.417 | P19: =+N19-O19 -> -91727.417 | Q19: =+P19/O19 -> -1 | R19: =+'Budget Energie'!N15+'Budget Energie'!N22 -> 0 | S19: =+N19-R19 -> 0
A20: Eau | B20: =+'Budget Energie'!B13+'Budget Energie'!B20 -> 0 | C20: =+'Budget Energie'!C13+'Budget Energie'!C20 -> 0 | D20: =+'Budget Energie'!D13+'Budget Energie'!D20 -> 0 | E20: =+'Budget Energie'!E13+'Budget Energie'!E20 -> 0 | F20: =+'Budget Energie'!F13+'Budget Energie'!F20 -> 0 | G20: =+'Budget Energie'!G13+'Budget Energie'!G20 -> 0 | H20: =+'Budget Energie'!H13+'Budget Energie'!H20 -> 0 | I20: =+'Budget Energie'!I13+'Budget Energie'!I20 -> 0 | ... M20: =+'Budget Energie'!M13+'Budget Energie'!M20 -> 0 | N20: =SUM(B20:M20) -> 0 | O20: 20637.641 | P20: =+N20-O20 -> -20637.641 | Q20: =+P20/O20 -> -1 | R20: =+'Budget Energie'!N13+'Budget Energie'!N20 -> 0 | S20: =+N20-R20 -> 0
A21: Total consommation Energie | B21: =SUM(B19:B20) -> 0 | C21: =SUM(C19:C20) -> 0 | D21: =SUM(D19:D20) -> 0 | E21: =SUM(E19:E20) -> 0 | F21: =SUM(F19:F20) -> 0 | G21: =SUM(G19:G20) -> 0 | H21: =SUM(H19:H20) -> 0 | I21: =SUM(I19:I20) -> 0 | ... M21: =SUM(M19:M20) -> 0 | N21: =SUM(B21:M21) -> 0 | O21: =+O20+O19 -> 112365.06 | P21: =+N21-O21 -> -112365.06 | Q21: =+P21/O21 -> -1 | R21: =+'Budget Energie'!N7 -> 0 | S21: =+N21-R21 -> 0
A22: Prestations & analyses | B22: =+'Budget Ent & Analyses'!B14+'Budget Commun'!B19+'Budget Ent & Analyses'!B22 -> 0 | C22: =+'Budget Ent & Analyses'!C14+'Budget Commun'!C19+'Budget Ent & Analyses'!C22 -> 61400 | D22: =+'Budget Ent & Analyses'!D14+'Budget Commun'!D19+'Budget Ent & Analyses'!D22 -> 0 | E22: =+'Budget Ent & Analyses'!E14+'Budget Commun'!E19+'Budget Ent & Analyses'!E22 -> 0 | F22: =+'Budget Ent & Analyses'!F14+'Budget Commun'!F19+'Budget Ent & Analyses'!F22 -> 0 | G22: =+'Budget Ent & Analyses'!G14+'Budget Commun'!G19+'Budget Ent & Analyses'!G22 -> 0 | H22: =+'Budget Ent & Analyses'!H14+'Budget Commun'!H19+'Budget Ent & Analyses'!H22 -> 0 | I22: =+'Budget Ent & Analyses'!I14+'Budget Commun'!I19+'Budget Ent & Analyses'!I22 -> 0 | ... M22: =+'Budget Ent & Analyses'!M14+'Budget Commun'!M19+'Budget Ent & Analyses'!M22 -> 0 | N22: =SUM(B22:M22) -> 61400 | O22: 43594.909 | P22: =+N22-O22 -> 17805.091 | Q22: =+P22/O22 -> 0.40842133 | R22: =+'Budget Ent & Analyses'!N14+'Budget Commun'!N19+'Budget Ent & Analyses'!N22 -> 61400 | S22: =+N22-R22 -> 0
A23: Loyers fermes | B23: =+'Budget Loyers Fermes'!B7 -> 37622.549 | C23: =+'Budget Loyers Fermes'!C7 -> 37622.549 | D23: =+'Budget Loyers Fermes'!D7 -> 37622.549 | E23: =+'Budget Loyers Fermes'!E7 -> 37622.549 | F23: =+'Budget Loyers Fermes'!F7 -> 37622.549 | G23: =+'Budget Loyers Fermes'!G7 -> 37622.549 | H23: =+'Budget Loyers Fermes'!H7 -> 37622.549 | I23: =+'Budget Loyers Fermes'!I7 -> 37622.549 | ... M23: =+'Budget Loyers Fermes'!M7 -> 37622.549 | N23: =SUM(B23:M23) -> 451470.59 | O23: 191666.67 | P23: =+N23-O23 -> 259803.92 | Q23: =+P23/O23 -> 1.3554987 | R23: =+'Budget Loyers Fermes'!N7 -> 451470.59 | S23: =+N23-R23 -> 0
A24: Entretien | B24: =+'Budget Ent & Analyses'!B7-'Budget Ent & Analyses'!B14-'Budget Ent & Analyses'!B22+'Budget Commun'!B27 -> 10295.303 | C24: =+'Budget Ent & Analyses'!C7-'Budget Ent & Analyses'!C14-'Budget Ent & Analyses'!C22+'Budget Commun'!C27 -> 14132.803 | D24: =+'Budget Ent & Analyses'!D7-'Budget Ent & Analyses'!D14-'Budget Ent & Analyses'!D22+'Budget Commun'!D27 -> 14132.803 | E24: =+'Budget Ent & Analyses'!E7-'Budget Ent & Analyses'!E14-'Budget Ent & Analyses'!E22+'Budget Commun'!E27 -> 10295.303 | F24: =+'Budget Ent & Analyses'!F7-'Budget Ent & Analyses'!F14-'Budget Ent & Analyses'!F22+'Budget Commun'!F27 -> 10295.303 | G24: =+'Budget Ent & Analyses'!G7-'Budget Ent & Analyses'!G14-'Budget Ent & Analyses'!G22+'Budget Commun'!G27 -> 14132.803 | H24: =+'Budget Ent & Analyses'!H7-'Budget Ent & Analyses'!H14-'Budget Ent & Analyses'!H22+'Budget Commun'!H27 -> 14132.803 | I24: =+'Budget Ent & Analyses'!I7-'Budget Ent & Analyses'!I14-'Budget Ent & Analyses'!I22+'Budget Commun'!I27 -> 10295.303 | ... M24: =+'Budget Ent & Analyses'!M7-'Budget Ent & Analyses'!M14-'Budget Ent & Analyses'!M22+'Budget Commun'!M27 -> 1257.8035 | N24: =SUM(B24:M24) -> 125618.64 | O24: 105442.18 | P24: =+N24-O24 -> 20176.466 | Q24: =+P24/O24 -> 0.19135101 | R24: ='Budget Ent & Analyses'!N7-'Budget Ent & Analyses'!N14-'Budget Ent & Analyses'!N22+'Budget Commun'!N27 -> 125618.64 | S24: =+N24-R24 -> 0
A25: Main d'œuvre Directe | B25: =+'Budget MOD'!B7 -> 354391.69 | C25: =+'Budget MOD'!C7 -> 309277.47 | D25: =+'Budget MOD'!D7 -> 277874.46 | E25: =+'Budget MOD'!E7 -> 277413.75 | F25: =+'Budget MOD'!F7 -> 271051.42 | G25: =+'Budget MOD'!G7 -> 261194.88 | H25: =+'Budget MOD'!H7 -> 259638.92 | I25: =+'Budget MOD'!I7 -> 259783.08 | ... M25: =+'Budget MOD'!M7 -> 6140 | N25: =SUM(B25:M25) -> 2548032.9 | O25: 1390695.8 | P25: =+N25-O25 -> 1157337.1 | Q25: =+P25/O25 -> 0.83220007 | R25: =+'Budget MOD'!N7 -> 2548032.9 | S25: =+N25-R25 -> 0
A26: Main d'œuvre Adm. | B26: =+'Budget Commun'!B54 -> 30399.538 | C26: =+'Budget Commun'!C54 -> 30399.538 | D26: =+'Budget Commun'!D54 -> 30399.538 | E26: =+'Budget Commun'!E54 -> 30399.538 | F26: =+'Budget Commun'!F54 -> 30399.538 | G26: =+'Budget Commun'!G54 -> 30399.538 | H26: =+'Budget Commun'!H54 -> 30399.538 | I26: =+'Budget Commun'!I54 -> 30399.538 | ... M26: =+'Budget Commun'!M54 -> 30399.538 | N26: =SUM(B26:M26) -> 364794.45 | O26: 319900.43 | P26: =+N26-O26 -> 44894.019 | Q26: =+P26/O26 -> 0.14033748 | R26: =+'Budget Commun'!N54 -> 364794.45 | S26: =+N26-R26 -> 0
A27: Transport | B27: =+'Budget Transp Ventes'!B7 -> 0 | C27: =+'Budget Transp Ventes'!C7 -> 0 | D27: =+'Budget Transp Ventes'!D7 -> 0 | E27: =+'Budget Transp Ventes'!E7 -> 0 | F27: =+'Budget Transp Ventes'!F7 -> 23025000 | G27: =+'Budget Transp Ventes'!G7 -> 17268750 | H27: =+'Budget Transp Ventes'!H7 -> 17268750 | I27: =+'Budget Transp Ventes'!I7 -> 23025000 | ... M27: =+'Budget Transp Ventes'!M7 -> 5756250 | N27: =SUM(B27:M27) -> 1.3239375e+08 | O27: 70540.186 | P27: =+N27-O27 -> 1.3232321e+08 | Q27: =+P27/O27 -> 1875.8557 | R27: =+'Budget Transp Ventes'!N7 -> 1.3239375e+08 | S27: =+N27-R27 -> 0
A28: Autres frais généraux | B28: =+'Budget Commun'!B43+'Budget Commun'!B34 -> 74741.04 | C28: =+'Budget Commun'!C43+'Budget Commun'!C34 -> 3753.7572 | D28: =+'Budget Commun'!D43+'Budget Commun'!D34 -> 3753.7572 | E28: =+'Budget Commun'!E43+'Budget Commun'!E34 -> 3753.7572 | F28: =+'Budget Commun'!F43+'Budget Commun'!F34 -> 3753.7572 | G28: =+'Budget Commun'!G43+'Budget Commun'!G34 -> 3753.7572 | H28: =+'Budget Commun'!H43+'Budget Commun'!H34 -> 5404.6243 | I28: =+'Budget Commun'!I43+'Budget Commun'!I34 -> 3753.7572 | ... M28: =+'Budget Commun'!M43+'Budget Commun'!M34 -> 3753.7572 | N28: =SUM(B28:M28) -> 123579.19 | O28: 79354.347 | P28: =+N28-O28 -> 44224.844 | Q28: =+P28/O28 -> 0.5573084 | R28: =+'Budget Commun'!N34+'Budget Commun'!N43 -> 123579.19 | S28: =+N28-R28 -> 0
A29: Coût de revient total | B29: =SUM(B22:B28)+B21+B18 -> 986984.12 | C29: =SUM(C22:C28)+C21+C18 -> 3079536.1 | D29: =SUM(D22:D28)+D21+D18 -> 379133.11 | E29: =SUM(E22:E28)+E21+E18 -> 374834.89 | F29: =SUM(F22:F28)+F21+F18 -> 23393473 | G29: =SUM(G22:G28)+G21+G18 -> 17631204 | H29: =SUM(H22:H28)+H21+H18 -> 17631298 | I29: =SUM(I22:I28)+I21+I18 -> 23382204 | ... M29: =SUM(M22:M28)+M21+M18 -> 5850773.6 | N29: =SUM(B29:M29) -> 1.3932463e+08 | O29: =SUM(O22:O28)+O21+O18 -> 4072221.9 | P29: =+N29-O29 -> 1.3525241e+08 | Q29: =+P29/O29 -> 33.213418
A30: EBITDA | B30: =B11-B29 -> #DIV/0! | C30: =C11-C29 -> #DIV/0! | D30: =D11-D29 -> #DIV/0! | E30: =E11-E29 -> #DIV/0! | F30: =F11-F29 -> #DIV/0! | G30: =G11-G29 -> #DIV/0! | H30: =H11-H29 -> #DIV/0! | I30: =I11-I29 -> #DIV/0! | ... O30: =O11-O29 -> -509695.71 | P30: =+N30-O30 -> #DIV/0! | Q30: =+P30/O30 -> #DIV/0!
A31: Amortissements | B31: =+'Budget Commun'!B14+'Budget Invest& Amort'!B9 -> 84231.686 | C31: =+'Budget Commun'!C14+'Budget Invest& Amort'!C9 -> 84231.686 | D31: =+'Budget Commun'!D14+'Budget Invest& Amort'!D9 -> 84231.686 | E31: =+'Budget Commun'!E14+'Budget Invest& Amort'!E9 -> 84231.686 | F31: =+'Budget Commun'!F14+'Budget Invest& Amort'!F9 -> 84231.686 | G31: =+'Budget Commun'!G14+'Budget Invest& Amort'!G9 -> 84231.686 | H31: =+'Budget Commun'!H14+'Budget Invest& Amort'!H9 -> 84231.686 | I31: =+'Budget Commun'!I14+'Budget Invest& Amort'!I9 -> 84231.686 | ... M31: =+'Budget Commun'!M14+'Budget Invest& Amort'!M9 -> 87247.519 | N31: =SUM(B31:M31) -> 1019827.7 | O31: 823053.01 | P31: =+N31-O31 -> 196774.71 | Q31: =+P31/O31 -> 0.23907903 | R31: =+'Budget Commun'!N14+'Budget Invest& Amort'!N9 -> 1019827.7 | S31: =+N31-R31 -> 0
A32: Résultat d'exploitation | B32: =B30-B31 -> #DIV/0! | C32: =C30-C31 -> #DIV/0! | D32: =D30-D31 -> #DIV/0! | E32: =E30-E31 -> #DIV/0! | F32: =F30-F31 -> #DIV/0! | G32: =G30-G31 -> #DIV/0! | H32: =H30-H31 -> #DIV/0! | I32: =I30-I31 -> #DIV/0! | ... O32: =O30-O31 -> -1332748.7 | P32: =+N32-O32 -> #DIV/0! | Q32: =+P32/O32 -> #DIV/0!
A33: EBITDA en % du CA | N33: =+N30/N7 -> #DIV/0! | O33: =+O30/O7 -> -0.20075504 | P33: =+N33-O33 -> #DIV/0!
A34: PMV au kg | B34: =+(B7)/B5 -> #DIV/0! | C34: =+(C7)/C5 -> #DIV/0! | D34: =+(D7)/D5 -> #DIV/0! | E34: =+(E7)/E5 -> #DIV/0! | F34: =+(F7)/F5 -> 0.01 | G34: =+(G7)/G5 -> 0.01 | H34: =+(H7)/H5 -> 0.01 | I34: =+(I7)/I5 -> 0.01 | ... O34: =+(O7)/O5 -> 2.2908751 | P34: =+N34-O34 -> -2.2808751 | Q34: =+P34/O34 -> -0.99563486
A35: CA à l'hectare prod | B35: =+B7/B4 -> 0 | C35: =+C7/C4 -> 0 | D35: =+D7/D4 -> 0 | E35: =+E7/E4 -> 0 | F35: =+F7/F4 -> 200000 | G35: =+G7/G4 -> 150000 | H35: =+H7/H4 -> 150000 | I35: =+I7/I4 -> 200000 | ... O35: =+O7/O4 -> 373366.72 | P35: =+N35-O35 -> 776633.28 | Q35: =+P35/O35 -> 2.0800817
A36: Coût à l'hectare prod (hors Amort) | B36: =+(B29-B10)/B4 -> #DIV/0! | C36: =+(C29-C10)/C4 -> #DIV/0! | D36: =+(D29-D10)/D4 -> #DIV/0! | E36: =+(E29-E10)/E4 -> #DIV/0! | F36: =+(F29-F10)/F4 -> #DIV/0! | G36: =+(G29-G10)/G4 -> #DIV/0! | H36: =+(H29-H10)/H4 -> #DIV/0! | I36: =+(I29-I10)/I4 -> #DIV/0! | ... O36: =+(O29-O10)/O4 -> 598856.16 | P36: =+N36-O36 -> #DIV/0! | Q36: =+P36/O36 -> #DIV/0!
A37: EBITDA à l'hectare prod | B37: =+B30/B4 -> #DIV/0! | C37: =+C30/C4 -> #DIV/0! | D37: =+D30/D4 -> #DIV/0! | E37: =+E30/E4 -> #DIV/0! | F37: =+F30/F4 -> #DIV/0! | G37: =+G30/G4 -> #DIV/0! | H37: =+H30/H4 -> #DIV/0! | I37: =+I30/I4 -> #DIV/0! | ... O37: =+O30/O4 -> -74955.251 | P37: =+N37-O37 -> #DIV/0! | Q37: =+P37/O37 -> #DIV/0!
A38: Coût total à l'hectare prod | B38: =+(B29+B31-B10)/B4 -> #DIV/0! | C38: =+(C29+C31-C10)/C4 -> #DIV/0! | D38: =+(D29+D31-D10)/D4 -> #DIV/0! | E38: =+(E29+E31-E10)/E4 -> #DIV/0! | F38: =+(F29+F31-F10)/F4 -> #DIV/0! | G38: =+(G29+G31-G10)/G4 -> #DIV/0! | H38: =+(H29+H31-H10)/H4 -> #DIV/0! | I38: =+(I29+I31-I10)/I4 -> #DIV/0! | ... O38: =+(O29+O31-O10)/O4 -> 719893.37 | P38: =+N38-O38 -> #DIV/0! | Q38: =+P38/O38 -> #DIV/0!
A39: REX à l'hectare prod | B39: =B32/B4 -> #DIV/0! | C39: =C32/C4 -> #DIV/0! | D39: =D32/D4 -> #DIV/0! | E39: =E32/E4 -> #DIV/0! | F39: =F32/F4 -> #DIV/0! | G39: =G32/G4 -> #DIV/0! | H39: =H32/H4 -> #DIV/0! | I39: =I32/I4 -> #DIV/0! | ... O39: =O32/O4 -> -195992.46 | P39: =+N39-O39 -> #DIV/0! | Q39: =+P39/O39 -> #DIV/0!
A40: Détail des coûts à l'hectare
A41: Coût total à l'hectare | B41: =+(B29+B31)/B3 -> #DIV/0! | C41: =+(C29+C31)/C3 -> #DIV/0! | D41: =+(D29+D31)/D3 -> #DIV/0! | E41: =+(E29+E31)/E3 -> #DIV/0! | F41: =+(F29+F31)/F3 -> #DIV/0! | G41: =+(G29+G31)/G3 -> #DIV/0! | H41: =+(H29+H31)/H3 -> #DIV/0! | I41: =+(I29+I31)/I3 -> #DIV/0! | ... M41: =+(M29+M31)/M3 -> #DIV/0! | N41: =+(N29+N31-N10)/N3 -> #DIV/0! | O41: =+(O29+O31-O10)/O3 -> 719893.37 | P41: =+N41-O41 -> #DIV/0! | Q41: =+P41/O41 -> #DIV/0!
A42: Coût à l'hectare (hors Amort) | B42: =+B29/B3 -> #DIV/0! | C42: =+C29/C3 -> #DIV/0! | D42: =+D29/D3 -> #DIV/0! | E42: =+E29/E3 -> #DIV/0! | F42: =+F29/F3 -> #DIV/0! | G42: =+G29/G3 -> #DIV/0! | H42: =+H29/H3 -> #DIV/0! | I42: =+I29/I3 -> #DIV/0! | ... M42: =+M29/M3 -> #DIV/0! | N42: =+(N29-N10)/N3 -> #DIV/0! | O42: =+(O29-O10)/O3 -> 598856.16 | P42: =+N42-O42 -> #DIV/0! | Q42: =+P42/O42 -> #DIV/0!
A43: Semences | B43: =+B12/B3 -> #DIV/0! | C43: =+C12/C3 -> #DIV/0! | D43: =+D12/D3 -> #DIV/0! | E43: =+E12/E3 -> #DIV/0! | F43: =+F12/F3 -> #DIV/0! | G43: =+G12/G3 -> #DIV/0! | H43: =+H12/H3 -> #DIV/0! | I43: =+I12/I3 -> #DIV/0! | ... O43: =+O12/O3 -> 29764.706 | P43: =+N43-O43 -> #DIV/0! | Q43: =+P43/O43 -> #DIV/0!
A44: Engrais | B44: =+B13/B3 -> #DIV/0! | C44: =+C13/C3 -> #DIV/0! | D44: =+D13/D3 -> #DIV/0! | E44: =+E13/E3 -> #DIV/0! | F44: =+F13/F3 -> #DIV/0! | G44: =+G13/G3 -> #DIV/0! | H44: =+H13/H3 -> #DIV/0! | I44: =+I13/I3 -> #DIV/0! | ... O44: =+O13/O3 -> 79047.086 | P44: =+N44-O44 -> #DIV/0! | Q44: =+P44/O44 -> #DIV/0!
A45: Plants | B45: =+B14/B3 -> #DIV/0! | C45: =+C14/C3 -> #DIV/0! | D45: =+D14/D3 -> #DIV/0! | E45: =+E14/E3 -> #DIV/0! | F45: =+F14/F3 -> #DIV/0! | G45: =+G14/G3 -> #DIV/0! | H45: =+H14/H3 -> #DIV/0! | I45: =+I14/I3 -> #DIV/0! | ... O45: =+O14/O3 -> 37483.382 | P45: =+N45-O45 -> #DIV/0! | Q45: =+P45/O45 -> #DIV/0!
A46: Phytos | B46: =+B15/B3 -> #DIV/0! | C46: =+C15/C3 -> #DIV/0! | D46: =+D15/D3 -> #DIV/0! | E46: =+E15/E3 -> #DIV/0! | F46: =+F15/F3 -> #DIV/0! | G46: =+G15/G3 -> #DIV/0! | H46: =+H15/H3 -> #DIV/0! | I46: =+I15/I3 -> #DIV/0! | ... O46: =+O15/O3 -> 85686.503 | P46: =+N46-O46 -> #DIV/0! | Q46: =+P46/O46 -> #DIV/0!
A47: Insectes | B47: =+B16/B3 -> #DIV/0! | C47: =+C16/C3 -> #DIV/0! | D47: =+D16/D3 -> #DIV/0! | E47: =+E16/E3 -> #DIV/0! | F47: =+F16/F3 -> #DIV/0! | G47: =+G16/G3 -> #DIV/0! | H47: =+H16/H3 -> #DIV/0! | I47: =+I16/I3 -> #DIV/0! | ... O47: =+O16/O3 -> 15828.683 | P47: =+N47-O47 -> #DIV/0! | Q47: =+P47/O47 -> #DIV/0!
A48: Autres fournitures agricoles | B48: =+B17/B3 -> #DIV/0! | C48: =+C17/C3 -> #DIV/0! | D48: =+D17/D3 -> #DIV/0! | E48: =+E17/E3 -> #DIV/0! | F48: =+F17/F3 -> #DIV/0! | G48: =+G17/G3 -> #DIV/0! | H48: =+H17/H3 -> #DIV/0! | I48: =+I17/I3 -> #DIV/0! | ... O48: =+O17/O3 -> 10816.456 | P48: =+N48-O48 -> #DIV/0! | Q48: =+P48/O48 -> #DIV/0!
A49: Electricité | B49: =+B19/B3 -> #DIV/0! | C49: =+C19/C3 -> #DIV/0! | D49: =+D19/D3 -> #DIV/0! | E49: =+E19/E3 -> #DIV/0! | F49: =+F19/F3 -> #DIV/0! | G49: =+G19/G3 -> #DIV/0! | H49: =+H19/H3 -> #DIV/0! | I49: =+I19/I3 -> #DIV/0! | ... O49: =+O19/O3 -> 13489.326 | P49: =+N49-O49 -> #DIV/0! | Q49: =+P49/O49 -> #DIV/0!
A50: Eau | B50: =+B20/B3 -> #DIV/0! | C50: =+C20/C3 -> #DIV/0! | D50: =+D20/D3 -> #DIV/0! | E50: =+E20/E3 -> #DIV/0! | F50: =+F20/F3 -> #DIV/0! | G50: =+G20/G3 -> #DIV/0! | H50: =+H20/H3 -> #DIV/0! | I50: =+I20/I3 -> #DIV/0! | ... O50: =+O20/O3 -> 3034.9473 | P50: =+N50-O50 -> #DIV/0! | Q50: =+P50/O50 -> #DIV/0!
A51: Prestations & analyses | B51: =+B22/B3 -> #DIV/0! | C51: =+C22/C3 -> #DIV/0! | D51: =+D22/D3 -> #DIV/0! | E51: =+E22/E3 -> #DIV/0! | F51: =+F22/F3 -> #DIV/0! | G51: =+G22/G3 -> #DIV/0! | H51: =+H22/H3 -> #DIV/0! | I51: =+I22/I3 -> #DIV/0! | ... O51: =+O22/O3 -> 6411.0161 | P51: =+N51-O51 -> #DIV/0! | Q51: =+P51/O51 -> #DIV/0!
A52: Loyers fermes | B52: =+B23/B3 -> #DIV/0! | C52: =+C23/C3 -> #DIV/0! | D52: =+D23/D3 -> #DIV/0! | E52: =+E23/E3 -> #DIV/0! | F52: =+F23/F3 -> #DIV/0! | G52: =+G23/G3 -> #DIV/0! | H52: =+H23/H3 -> #DIV/0! | I52: =+I23/I3 -> #DIV/0! | ... O52: =+O23/O3 -> 28186.275 | P52: =+N52-O52 -> #DIV/0! | Q52: =+P52/O52 -> #DIV/0!
A53: Entretien | B53: =+B24/B3 -> #DIV/0! | C53: =+C24/C3 -> #DIV/0! | D53: =+D24/D3 -> #DIV/0! | E53: =+E24/E3 -> #DIV/0! | F53: =+F24/F3 -> #DIV/0! | G53: =+G24/G3 -> #DIV/0! | H53: =+H24/H3 -> #DIV/0! | I53: =+I24/I3 -> #DIV/0! | ... O53: =+O24/O3 -> 15506.202 | P53: =+N53-O53 -> #DIV/0! | Q53: =+P53/O53 -> #DIV/0!
A54: Main d'œuvre Directe | B54: =+B25/B3 -> #DIV/0! | C54: =+C25/C3 -> #DIV/0! | D54: =+D25/D3 -> #DIV/0! | E54: =+E25/E3 -> #DIV/0! | F54: =+F25/F3 -> #DIV/0! | G54: =+G25/G3 -> #DIV/0! | H54: =+H25/H3 -> #DIV/0! | I54: =+I25/I3 -> #DIV/0! | ... O54: =+O25/O3 -> 204514.08 | P54: =+N54-O54 -> #DIV/0! | Q54: =+P54/O54 -> #DIV/0!
A55: Main d'œuvre Adm. | B55: =+B26/B3 -> #DIV/0! | C55: =+C26/C3 -> #DIV/0! | D55: =+D26/D3 -> #DIV/0! | E55: =+E26/E3 -> #DIV/0! | F55: =+F26/F3 -> #DIV/0! | G55: =+G26/G3 -> #DIV/0! | H55: =+H26/H3 -> #DIV/0! | I55: =+I26/I3 -> #DIV/0! | ... O55: =+O26/O3 -> 47044.181 | P55: =+N55-O55 -> #DIV/0! | Q55: =+P55/O55 -> #DIV/0!
A56: Refact. HIJOS DE FEDERICO LIS | B56: =+#REF!/B3 -> #REF! | C56: =+#REF!/C3 -> #REF! | D56: =+#REF!/D3 -> #REF! | E56: =+#REF!/E3 -> #REF! | F56: =+#REF!/F3 -> #REF! | G56: =+#REF!/G3 -> #REF! | H56: =+#REF!/H3 -> #REF! | I56: =+#REF!/I3 -> #REF! | ... O56: =+#REF!/O3 -> #REF! | P56: =+N56-O56 -> #REF! | Q56: =+P56/O56 -> #REF!
A57: Transport | B57: =+B27/B3 -> #DIV/0! | C57: =+C27/C3 -> #DIV/0! | D57: =+D27/D3 -> #DIV/0! | E57: =+E27/E3 -> #DIV/0! | F57: =+F27/F3 -> #DIV/0! | G57: =+G27/G3 -> #DIV/0! | H57: =+H27/H3 -> #DIV/0! | I57: =+I27/I3 -> #DIV/0! | ... O57: =+O27/O3 -> 10373.557 | P57: =+N57-O57 -> #DIV/0! | Q57: =+P57/O57 -> #DIV/0!
A58: Autres frais généraux | B58: =+B28/B3 -> #DIV/0! | C58: =+C28/C3 -> #DIV/0! | D58: =+D28/D3 -> #DIV/0! | E58: =+E28/E3 -> #DIV/0! | F58: =+F28/F3 -> #DIV/0! | G58: =+G28/G3 -> #DIV/0! | H58: =+H28/H3 -> #DIV/0! | I58: =+I28/I3 -> #DIV/0! | ... O58: =+O28/O3 -> 11669.757 | P58: =+N58-O58 -> #DIV/0! | Q58: =+P58/O58 -> #DIV/0!
A59: Amortissements | B59: =+B31/B3 -> #DIV/0! | C59: =+C31/C3 -> #DIV/0! | D59: =+D31/D3 -> #DIV/0! | E59: =+E31/E3 -> #DIV/0! | F59: =+F31/F3 -> #DIV/0! | G59: =+G31/G3 -> #DIV/0! | H59: =+H31/H3 -> #DIV/0! | I59: =+I31/I3 -> #DIV/0! | ... O59: =+O31/O3 -> 121037.21 | P59: =+N59-O59 -> #DIV/0! | Q59: =+P59/O59 -> #DIV/0!
A60: Calcul des encours
A61: Encours initial | D61: =SUM(B67:D83) -> #DIV/0!
A62: Coût des encours | D62: =+D61/('Budget Volumes Export'!N16*1000) -> #DIV/0! | E62: =+D62 -> #DIV/0! | F62: =+E62 -> #DIV/0! | G62: =+F62 -> #DIV/0! | H62: =+G62 -> #DIV/0! | I62: =+H62 -> #DIV/0! | J62: =+I62 -> #DIV/0! | K62: =+J62 -> #DIV/0! | L62: =+K62 -> #DIV/0! | M62: =+L62 -> #DIV/0!
A63: Coût des ventes | E63: =+E62*'Budget Volumes Export'!E16*1000 -> #DIV/0! | F63: =+F62*'Budget Volumes Export'!F16*1000 -> #DIV/0! | G63: =+G62*'Budget Volumes Export'!G16*1000 -> #DIV/0! | H63: =+H62*'Budget Volumes Export'!H16*1000 -> #DIV/0! | I63: =+I62*'Budget Volumes Export'!I16*1000 -> #DIV/0! | J63: =+J62*'Budget Volumes Export'!J16*1000 -> #DIV/0! | K63: =+K62*'Budget Volumes Export'!K16*1000 -> #DIV/0! | L63: =+L62*'Budget Volumes Export'!L16*1000 -> #DIV/0! | M63: =+M62*'Budget Volumes Export'!M16*1000 -> #DIV/0!
A64: Encours fin de période | E64: =+D61-E63 -> #DIV/0! | F64: =+E64-F63 -> #DIV/0! | G64: =+F64-G63 -> #DIV/0! | H64: =+G64-H63 -> #DIV/0! | I64: =+H64-I63 -> #DIV/0! | J64: =+I64-J63 -> #DIV/0! | K64: =+J64-K63 -> #DIV/0! | L64: =+K64-L63 -> #DIV/0! | M64: =+L64-M63 -> #DIV/0!
A65: Variation encours | E65: =+E64-D61 -> #DIV/0! | F65: =+F64-E64 -> #DIV/0! | G65: =+G64-F64 -> #DIV/0! | H65: =+H64-G64 -> #DIV/0! | I65: =+I64-H64 -> #DIV/0! | J65: =+J64-I64 -> #DIV/0! | K65: =+K64-J64 -> #DIV/0! | L65: =+L64-K64 -> #DIV/0! | M65: =+M64-L64 -> #DIV/0!
A66: Calcul encours initial culture hiver
A67: Semences | B67: =B12 -> 0 | C67: =C12 -> 1494600 | D67: =D12 -> 0
A68: Plants | B68: =B14 -> 0 | C68: =C14 -> 1113000 | D68: =D14 -> 0
A69: Fournitures agricoles | B69: =B17 -> 479534 | C69: =C17 -> 15350 | D69: =D17 -> 15350
A70: Engrais | B70: =B13*('Plan de culture 104 '!$X$13/'Plan de culture 104 '!$B$3) -> #DIV/0! | C70: =C13*('Plan de culture 104 '!$X$13/'Plan de culture 104 '!$B$3) -> #DIV/0! | D70: =D13*('Plan de culture 104 '!$X$13/'Plan de culture 104 '!$B$3) -> #DIV/0!
A71: Phytos | B71: =B15*('Plan de culture 104 '!$X$13/'Plan de culture 104 '!$B$3) -> #DIV/0! | C71: =C15*('Plan de culture 104 '!$X$13/'Plan de culture 104 '!$B$3) -> #DIV/0! | D71: =D15*('Plan de culture 104 '!$X$13/'Plan de culture 104 '!$B$3) -> #DIV/0!
A72: Insectes | B72: =B16*('Plan de culture 104 '!$X$13/'Plan de culture 104 '!$B$3) -> #DIV/0! | C72: =C16*('Plan de culture 104 '!$X$13/'Plan de culture 104 '!$B$3) -> #DIV/0! | D72: =D16*('Plan de culture 104 '!$X$13/'Plan de culture 104 '!$B$3) -> #DIV/0!
A73: Energie | B73: =B21*('Plan de culture 104 '!$X$13/'Plan de culture 104 '!$B$3) -> #DIV/0! | C73: =C21*('Plan de culture 104 '!$X$13/'Plan de culture 104 '!$B$3) -> #DIV/0! | D73: =D21*('Plan de culture 104 '!$X$13/'Plan de culture 104 '!$B$3) -> #DIV/0!
A74: Prestations & analyses | B74: =B22*('Plan de culture 104 '!$X$13/'Plan de culture 104 '!$B$3) -> #DIV/0! | C74: =C22*('Plan de culture 104 '!$X$13/'Plan de culture 104 '!$B$3) -> #DIV/0! | D74: =D22*('Plan de culture 104 '!$X$13/'Plan de culture 104 '!$B$3) -> #DIV/0!
A75: Loyers fermes | B75: =B23*('Plan de culture 104 '!$X$13/'Plan de culture 104 '!$B$3) -> #DIV/0! | C75: =C23*('Plan de culture 104 '!$X$13/'Plan de culture 104 '!$B$3) -> #DIV/0! | D75: =D23*('Plan de culture 104 '!$X$13/'Plan de culture 104 '!$B$3) -> #DIV/0!
A76: Entretien | B76: =B24*('Plan de culture 104 '!$X$13/'Plan de culture 104 '!$B$3) -> #DIV/0! | C76: =C24*('Plan de culture 104 '!$X$13/'Plan de culture 104 '!$B$3) -> #DIV/0! | D76: =D24*('Plan de culture 104 '!$X$13/'Plan de culture 104 '!$B$3) -> #DIV/0!
A77: Main d'œuvre Directe | B77: =B25*('Plan de culture 104 '!$X$13/'Plan de culture 104 '!$B$3) -> #DIV/0! | C77: =C25*('Plan de culture 104 '!$X$13/'Plan de culture 104 '!$B$3) -> #DIV/0! | D77: =D25*('Plan de culture 104 '!$X$13/'Plan de culture 104 '!$B$3) -> #DIV/0!
A78: Main d'œuvre Adm. | B78: =B26*('Plan de culture 104 '!$X$13/'Plan de culture 104 '!$B$3) -> #DIV/0! | C78: =C26*('Plan de culture 104 '!$X$13/'Plan de culture 104 '!$B$3) -> #DIV/0! | D78: =D26*('Plan de culture 104 '!$X$13/'Plan de culture 104 '!$B$3) -> #DIV/0!
A79: Refact. HIJOS DE FEDERICO LIS | B79: =#REF!*('Plan de culture 104 '!$X$13/'Plan de culture 104 '!$B$3) -> #REF! | C79: =#REF!*('Plan de culture 104 '!$X$13/'Plan de culture 104 '!$B$3) -> #REF! | D79: =#REF!*('Plan de culture 104 '!$X$13/'Plan de culture 104 '!$B$3) -> #REF!
A80: Autres frais généraux | B80: =B28*('Plan de culture 104 '!$X$13/'Plan de culture 104 '!$B$3) -> #DIV/0! | C80: =C28*('Plan de culture 104 '!$X$13/'Plan de culture 104 '!$B$3) -> #DIV/0! | D80: =D28*('Plan de culture 104 '!$X$13/'Plan de culture 104 '!$B$3) -> #DIV/0!
A81: Amortissements | B81: =B31*('Plan de culture 104 '!$X$13/'Plan de culture 104 '!$B$3) -> #DIV/0! | C81: =C31*('Plan de culture 104 '!$X$13/'Plan de culture 104 '!$B$3) -> #DIV/0! | D81: =D31*('Plan de culture 104 '!$X$13/'Plan de culture 104 '!$B$3) -> #DIV/0!

Sheet Plan de culture 104 
A1: BUDGET DOMAINE 104 PLAN DE CULTURE
A3: TOTAL SUPERFICIE PRODUCTIVE 104 (ha) | C3: =X7+X13+X19+X25+X31+X37 -> 15.35
A4: SUPERFICIE PAR SERRRE | B4: 0.7 | C4: 0.63 | D4: 0.7 | E4: 0.63 | F4: 0.74 | G4: 0.71 | H4: 0.74 | I4: 0.74 | J4: 0.74 | K4: 0.74 | L4: 0.74 | M4: 0.74 | N4: 0.62 | O4: 0.8 | P4: 0.71 | Q4: 0.71 | R4: 0.71 | S4: 0.71 | T4: 0.57 | U4: 0.68 | V4: 0.91 | W4: 0.38 | X4: =SUM(B4:W4) -> 15.35
B5: S1 | C5: S2 | D5: S3 | E5: S4 | F5: S5 | G5: S6 | H5: S7 | I5: S8 | J5: S9 | K5: S10 | L5: S11 | M5: S12 | N5: S13 | O5: S14 | P5: S15 | Q5: S16 | R5: S17 | S5: S18 | T5: S19 | U5: S20 | V5: S21 | W5: S22 | X5: TOTAL
A6: TCR
A7: Superficie (ha) | B7: 0.7 | C7: 0.63 | D7: 0.7 | E7: 0.63 | F7: 0.74 | G7: 0.71 | H7: 0.74 | I7: 0.74 | J7: 0.74 | K7: 0.74 | L7: 0.74 | M7: 0.74 | N7: 0.62 | O7: 0.8 | P7: 0.71 | Q7: 0.71 | R7: 0.71 | S7: 0.71 | T7: 0.57 | U7: 0.68 | V7: 0.91 | W7: 0.38 | X7: =SUM(B7:W7) -> 15.35
A8: Date plantation | B8: 45870 | C8: 45870 | D8: 45870 | E8: 45870 | F8: 45870 | G8: 45870 | H8: 45870 | I8: 45870 | J8: 45870 | K8: 45870 | L8: 45870 | M8: 45870 | N8: 45870 | O8: 45870 | P8: 45870 | Q8: 45870 | R8: 45870 | S8: 45870 | T8: 45870 | U8: 45870 | V8: 45870 | W8: 45870
A9: Date entrée en production | B9: 45940 | C9: 45940 | D9: 45940 | E9: 45940 | F9: 45940 | G9: 45940 | H9: 45940 | I9: 45940 | J9: 45940 | K9: 45940 | L9: 45940 | M9: 45940 | N9: 45940 | O9: 45940 | P9: 45940 | Q9: 45940 | R9: 45940 | S9: 45940 | T9: 45940 | U9: 45940 | V9: 45940 | W9: 45940
A10: Date arrachage | B10: 46172 | C10: 46172 | D10: 46172 | E10: 46172 | F10: 46172 | G10: 46172 | H10: 46172 | I10: 46172 | J10: 46172 | K10: 46172 | L10: 46172 | M10: 46172 | N10: 46172 | O10: 46172 | P10: 46172 | Q10: 46172 | R10: 46172 | S10: 46172 | T10: 46172 | U10: 46172 | V10: 46172 | W10: 46172
A11: Cycle en mois | B11: =+(B10-B8)/30 -> 10.066667 | C11: =+(C10-C8)/30 -> 10.066667 | D11: =+(D10-D8)/30 -> 10.066667 | E11: =+(E10-E8)/30 -> 10.066667 | F11: =+(F10-F8)/30 -> 10.066667 | G11: =+(G10-G8)/30 -> 10.066667 | H11: =+(H10-H8)/30 -> 10.066667 | I11: =+(I10-I8)/30 -> 10.066667 | ... W11: =+(W10-W8)/30 -> 10.066667
A12: TCA
A13: Superficie (ha) | X13: =SUM(B13:W13) -> 0
A14: Date plantation
A15: Date entrée en production
A16: Date arrachage
A17: Cycle en mois | B17: =+(B16-B14)/30 -> 0 | C17: =+(C16-C14)/30 -> 0 | D17: =+(D16-D14)/30 -> 0 | E17: =+(E16-E14)/30 -> 0 | F17: =+(F16-F14)/30 -> 0 | G17: =+(G16-G14)/30 -> 0 | H17: =+(H16-H14)/30 -> 0 | I17: =+(I16-I14)/30 -> 0 | ... W17: =+(W16-W14)/30 -> 0
A18: TCG
A19: Superficie (ha) | X19: =SUM(B19:W19) -> 0
A20: Date plantation
A21: Date entrée en production
A22: Date arrachage
A23: Cycle en mois | B23: =+(B22-B20)/30 -> 0 | C23: =+(C22-C20)/30 -> 0 | E23: =+(E22-E20)/30 -> 0 | F23: =+(F22-F20)/30 -> 0 | G23: =+(G22-G20)/30 -> 0 | H23: =+(H22-H20)/30 -> 0 | I23: =+(I22-I20)/30 -> 0 | J23: =+(J22-J20)/30 -> 0 | K23: =+(K22-K20)/30 -> 0 | L23: =+(L22-L20)/30 -> 0 | ... W23: =+(W22-W20)/30 -> 0
A24: TR
A25: Superficie (ha) | X25: =SUM(B25:W25) -> 0
A26: Date plantation
A27: Date entrée en production
A28: Date arrachage
A29: Cycle en mois | B29: =+(B28-B26)/30 -> 0 | C29: =+(C28-C26)/30 -> 0 | D29: =+(D28-D26)/30 -> 0 | E29: =+(E28-E26)/30 -> 0 | F29: =+(F28-F26)/30 -> 0 | G29: =+(G28-G26)/30 -> 0 | H29: =+(H28-H26)/30 -> 0 | I29: =+(I28-I26)/30 -> 0 | ... W29: =+(W28-W26)/30 -> 0
A30: MYR
A31: Superficie (ha) | X31: =SUM(B31:W31) -> 0
A32: Date plantation
A33: Date entrée en production
A34: Date arrachage
A35: Cycle en mois | B35: =+(B34-B32)/30 -> 0 | C35: =+(C34-C32)/30 -> 0 | D35: =+(D34-D32)/30 -> 0 | E35: =+(E34-E32)/30 -> 0 | F35: =+(F34-F32)/30 -> 0 | G35: =+(G34-G32)/30 -> 0 | H35: =+(H34-H32)/30 -> 0 | I35: =+(I34-I32)/30 -> 0 | ... W35: =+(W34-W32)/30 -> 0
A36: PVR
A37: Superficie (ha) | X37: =SUM(B37:W37) -> 0
A38: Date plantation
A39: Date entrée en production
A40: Date arrachage
A41: Cycle en mois | B41: =+(B40-B38)/30 -> 0 | C41: =+(C40-C38)/30 -> 0 | D41: =+(D40-D38)/30 -> 0 | E41: =+(E40-E38)/30 -> 0 | F41: =+(F40-F38)/30 -> 0 | G41: =+(G40-G38)/30 -> 0 | H41: =+(H40-H38)/30 -> 0 | I41: =+(I40-I38)/30 -> 0 | ... W41: =+(W40-W38)/30 -> 0

Sheet Plan de culture 105
A1: BUDGET DOMAINE 105 PLAN DE CULTURE
A3: TOTAL SUPERFICIE PRODUCTIVE 105 (ha) | C3: =+I7+I13+I19+I25+I31+I37 -> 5.395
A4: SUPERFICIE PAR SERRRE | B4: 0.875 | C4: 0.91 | D4: 0.875 | E4: 0.91 | F4: 0.42 | G4: 0.875 | H4: 0.53 | I4: =SUM(B4:H4) -> 5.395
B5: S1 | C5: S2 | D5: S3 | E5: S4 | F5: S5 | G5: S6 | H5: S7 | I5: TOTAL
A6: TCR
A7: Superficie (ha) | I7: =SUM(B7:H7) -> 0
A8: Date plantation
A9: Date entrée en production
A10: Date arrachage
A11: Cycle en mois | B11: =+(B10-B8)/30 -> 0 | C11: =+(C10-C8)/30 -> 0 | D11: =+(D10-D8)/30 -> 0 | E11: =+(E10-E8)/30 -> 0 | F11: =+(F10-F8)/30 -> 0 | G11: =+(G10-G8)/30 -> 0 | H11: =+(H10-H8)/30 -> 0
A12: TCA
A13: Superficie (ha) | B13: 0.875 | C13: 0.91 | D13: 0.875 | E13: 0.91 | F13: 0.42 | G13: 0.875 | H13: 0.53 | I13: =SUM(B13:H13) -> 5.395
A14: Date plantation | B14: 45870 | C14: 45870 | D14: 45870 | E14: 45870 | F14: 45870 | G14: 45870 | H14: 45870
A15: Date entrée en production | B15: 45940 | C15: 45940 | D15: 45940 | E15: 45940 | F15: 45940 | G15: 45940 | H15: 45940
A16: Date arrachage | B16: 46172 | C16: 46172 | D16: 46172 | E16: 46172 | F16: 46172 | G16: 46172 | H16: 46172
A17: Cycle en mois | B17: =+(B16-B14)/30 -> 10.066667 | C17: =+(C16-C14)/30 -> 10.066667 | D17: =+(D16-D14)/30 -> 10.066667 | E17: =+(E16-E14)/30 -> 10.066667 | F17: =+(F16-F14)/30 -> 10.066667 | G17: =+(G16-G14)/30 -> 10.066667 | H17: =+(H16-H14)/30 -> 10.066667
A18: TCG
A19: Superficie (ha) | I19: =SUM(B19:H19) -> 0
A20: Date plantation
A21: Date entrée en production
A22: Date arrachage
A23: Cycle en mois | B23: =+(B22-B20)/30 -> 0 | C23: =+(C22-C20)/30 -> 0 | E23: =+(E22-E20)/30 -> 0 | F23: =+(F22-F20)/30 -> 0 | G23: =+(G22-G20)/30 -> 0 | H23: =+(H22-H20)/30 -> 0
A24: TR
